Workbook

Sheet Dashboard
A1: AST SPACEMOBILE (NASDAQ: ASTS) - INTRINSIC VALUATION MODEL
A2: Valuation date 10-Sep-2026. USD. Balance sheet 30-Jun-2026 pro forma Jul-2026 convertible. Live links unless marked 'stamped'.
A4: MODEL STATUS | B4: =Checks!$C$3 -> ALL PASS
A6: Headline
A7: Current share price (IBKR) | B7: =Market_Data!$J$7 -> 62.42
A8: Probability-weighted intrinsic value | B8: =Valuation_Summary!F11 -> 52.878954
A9: Upside / (downside) vs price | B9: =Valuation_Summary!F11/Market_Data!$J$7-1 -> -0.15285239
A10: Monte Carlo mean (stamped) | B10: =Monte_Carlo!$B$36 -> 55.230451
A11: Monte Carlo P10 - P90 (stamped) | B11: =TEXT(Monte_Carlo!$B$39,"$0")&" - "&TEXT(Monte_Carlo!$B$43,"$0") -> $0 - $128
A12: P(intrinsic value > price) (stamped) | B12: =Monte_Carlo!$B$45 -> 0.3456
A13: Model-implied expected return p.a., 3-yr (prob-weighted) | B13: =Valuation_Summary!F24 -> 0.045555578
A14: Model-implied expected return p.a., 3-yr (MC mean) | B14: =Monte_Carlo!$B$51 -> 0.060829775
A15: Realised volatility (annualised) | B15: =Market_Data!$J$14 -> 0.93751899
A16: Growth-phase WACC / terminal WACC | B16: =TEXT(WACC!$C$11,"0.0%")&" / "&TEXT(WACC!$C$16,"0.0%") -> 10.3% / 8.3%
A17: Market-implied Base Tier-1 take rate (stamped reverse DCF) | B17: 0.10635771
A19: Scenarios (live)
B20: Distress | C20: Bear | D20: Base | E20: Bull | F20: Weighted
A21: Probability | B21: =Valuation_Summary!B5 -> 0.15 | C21: =Valuation_Summary!C5 -> 0.25 | D21: =Valuation_Summary!D5 -> 0.4 | E21: =Valuation_Summary!E5 -> 0.2 | F21: =Valuation_Summary!F5 -> 1
A22: Value per share ($) | B22: =Valuation_Summary!B11 -> 0 | C22: =Valuation_Summary!C11 -> 1.1878934 | D22: =Valuation_Summary!D11 -> 57.398181 | E22: =Valuation_Summary!E11 -> 148.11354 | F22: =Valuation_Summary!F11 -> 52.878954
A23: Enterprise value ($mm) | B23: =Valuation_Summary!B6 -> -12156.033 | C23: =Valuation_Summary!C6 -> 889.33938 | D23: =Valuation_Summary!D6 -> 23596.959 | E23: =Valuation_Summary!E6 -> 61532.382
A24: Revenue 2030 ($mm) | B24: =Valuation_Summary!B13 -> 196.85866 | C24: =Valuation_Summary!C13 -> 900.41765 | D24: =Valuation_Summary!D13 -> 3252.7922 | E24: =Valuation_Summary!E13 -> 7616.6973
A25: Revenue 2035 ($mm) | B25: =Valuation_Summary!B14 -> 630.97518 | C25: =Valuation_Summary!C14 -> 2754.0556 | D25: =Valuation_Summary!D14 -> 5926.9154 | E25: =Valuation_Summary!E14 -> 11462.384
A26: EBITDA margin 2040 | B26: =Valuation_Summary!B15 -> -0.56379242 | C26: =Valuation_Summary!C15 -> 0.45040789 | D26: =Valuation_Summary!D15 -> 0.63829787 | E26: =Valuation_Summary!E15 -> 0.72668415
A27: Peak funding need ($mm) | B27: =Valuation_Summary!B17 -> -13563.687 | C27: =Valuation_Summary!C17 -> -5827.8503 | D27: =Valuation_Summary!D17 -> -3413.2802 | E27: =Valuation_Summary!E17 -> -2121.0043
A29: For the portfolio analysis
A30: The earlier portfolio work used a 12% expected return for ASTS as an explicit placeholder guess.
A31: This model replaces it with the model-implied figures above: expected return and volatility for the ASTS sleeve.
A32: Interpretation: at today's price the market is paying roughly for Base-case execution; the payoff is highly skewed
A33: (meaningful probability of ~zero equity value, long right tail). Not investment advice.

Sheet Valuation_Summary
A1: VALUATION SUMMARY
A2: Probability-weighted DCF across four scenarios (all live). USD.
A4: Metric | B4: Distress | C4: Bear | D4: Base | E4: Bull | F4: Prob-weighted
A5: Probability | B5: =Inputs!D57 -> 0.15 | C5: =Inputs!E57 -> 0.25 | D5: =Inputs!F57 -> 0.4 | E5: =Inputs!G57 -> 0.2 | F5: =SUM(B5:E5) -> 1
A6: Enterprise value ($mm) | B6: =Calc_Distress!$C$87 -> -12156.033 | C6: =Calc_Bear!$C$87 -> 889.33938 | D6: =Calc_Base!$C$87 -> 23596.959 | E6: =Calc_Bull!$C$87 -> 61532.382
A7: PV of terminal value ($mm) | B7: =Calc_Distress!$C$85 -> -3888.1316 | C7: =Calc_Bear!$C$85 -> 3615.5397 | D7: =Calc_Base!$C$85 -> 14896.304 | E7: =Calc_Bull!$C$85 -> 34477.442
A8: Terminal value % of EV | B8: =Calc_Distress!$C$88 -> 0 | C8: =Calc_Bear!$C$88 -> 4.0654218 | D8: =Calc_Base!$C$88 -> 0.63128067 | E8: =Calc_Bull!$C$88 -> 0.56031379
A9: Equity before conversions ($mm) | B9: =Calc_Distress!$C$94 -> -12572.982 | C9: =Calc_Bear!$C$94 -> 472.39038 | D9: =Calc_Base!$C$94 -> 23180.01 | E9: =Calc_Bull!$C$94 -> 61115.433
A10: Diluted shares (mm) | B10: =Calc_Distress!$C$108 -> 389.16749 | C10: =Calc_Bear!$C$108 -> 402.19475 | D10: =Calc_Base!$C$108 -> 404.33827 | E10: =Calc_Bull!$C$108 -> 430.03296
A11: Value per share ($) | B11: =Calc_Distress!$C$109 -> 0 | C11: =Calc_Bear!$C$109 -> 1.1878934 | D11: =Calc_Base!$C$109 -> 57.398181 | E11: =Calc_Bull!$C$109 -> 148.11354 | F11: =SUMPRODUCT($B$5:$E$5,B11:E11) -> 52.878954
A12: Upside vs price | B12: =Calc_Distress!$C$110 -> -1 | C12: =Calc_Bear!$C$110 -> -0.98096935 | D12: =Calc_Base!$C$110 -> -0.080452089 | E12: =Calc_Bull!$C$110 -> 1.3728539
A13: Revenue 2030 ($mm) | B13: =Calc_Distress!$C$117 -> 196.85866 | C13: =Calc_Bear!$C$117 -> 900.41765 | D13: =Calc_Base!$C$117 -> 3252.7922 | E13: =Calc_Bull!$C$117 -> 7616.6973
A14: Revenue 2035 ($mm) | B14: =Calc_Distress!$C$118 -> 630.97518 | C14: =Calc_Bear!$C$118 -> 2754.0556 | D14: =Calc_Base!$C$118 -> 5926.9154 | E14: =Calc_Bull!$C$118 -> 11462.384
A15: EBITDA margin 2040 | B15: =Calc_Distress!$C$116 -> -0.56379242 | C15: =Calc_Bear!$C$116 -> 0.45040789 | D15: =Calc_Base!$C$116 -> 0.63829787 | E15: =Calc_Bull!$C$116 -> 0.72668415
A16: Implied terminal EV/EBITDA | B16: =Calc_Distress!$C$89 -> n/m | C16: =Calc_Bear!$C$89 -> 8.4252855 | D16: =Calc_Base!$C$89 -> 11.708219 | E16: =Calc_Bull!$C$89 -> 12.323268
A17: Peak funding need, cumulative FCFF ($mm) | B17: =Calc_Distress!$C$113 -> -13563.687 | C17: =Calc_Bear!$C$113 -> -5827.8503 | D17: =Calc_Base!$C$113 -> -3413.2802 | E17: =Calc_Bull!$C$113 -> -2121.0043
A18: Max paying users per satellite (mm) | B18: =Calc_Distress!$C$114 -> 0.35777866 | C18: =Calc_Bear!$C$114 -> 1.0043034 | D18: =Calc_Base!$C$114 -> 1.8197635 | E18: =Calc_Bull!$C$114 -> 2.1552533
A19: FY2026 revenue ($mm) | B19: =Calc_Distress!$C$112 -> 151.255 | C19: =Calc_Bear!$C$112 -> 166.255 | D19: =Calc_Base!$C$112 -> 174.955 | E19: =Calc_Bull!$C$112 -> 186.255
A21: Current share price ($, IBKR) | F21: =Market_Data!$J$7 -> 62.42
A22: Probability-weighted upside / (downside) | F22: =F11/F21-1 -> -0.15285239
A23: Growth-phase cost of equity (Ke) | F23: =WACC!$C$8 -> 0.10499614
A24: Model-implied expected return p.a. if price converges to value in 3 yrs | F24: =IF(F11<=0,-1,(F11*(1+F23)^3/F21)^(1/3)-1) -> 0.045555578 | G24: E[R] = (V x (1+Ke)^H / P)^(1/H) - 1. Replaces the 12% placeholder in the portfolio analysis.
A25: Model-implied expected return p.a. if price converges to value in 5 yrs | F25: =IF(F11<=0,-1,(F11*(1+F23)^5/F21)^(1/5)-1) -> 0.068938152 | G25: E[R] = (V x (1+Ke)^H / P)^(1/H) - 1. Replaces the 12% placeholder in the portfolio analysis.
A26: Market-implied EV ($mm) | F26: =Capital_Structure!$B$61 -> 24708.784
A27: Base-case EV / market-implied EV | F27: =D6/Capital_Structure!$B$61 -> 0.95500283

Sheet Inputs
A1: INPUTS & ASSUMPTIONS
A2: Blue = hard-coded input (edit here only). Yellow = key value driver. Every formula in the model references this sheet. Units in column C. $mm unless stated.
A4: Key | B4: Global parameter | C4: Unit | D4: Value | H4: Source / rationale
A5: VALUATION & MARKET
A6: val_date | B6: Valuation date (year fraction) | C6: yr | D6: 2026.69 | H6: DATA: 10-Sep-2026 = 2026 + 252/365.
A7: rf | B7: Risk-free rate (10y UST) | C7: % | D7: 0.0484 | H7: DATA: 10y UST 4.84% on 10-Sep-2026 (TradingEconomics / CNBC).
A8: erp | B8: Equity risk premium (US implied) | C8: % | D8: 0.0442 | H8: DATA: Damodaran implied US ERP 4.42% at 1-Jul-2026 (Musings on Markets, Jul-2026).
A9: blume_w | B9: Blume weight on raw beta | C9: x | D9: 0.67 | H9: METHOD: Blume (1971) adjustment beta_adj = 0.67*raw + 0.33. Resolution R-01.
A10: dv_hi | B10: Debt / capital - growth phase | C10: % | D10: 0.15 | H10: DATA-DERIVED: ~$4.2bn debt face vs ~$24.3bn equity mkt cap (Sep-2026) = 14.6%.
A11: kd_hi | B11: Pre-tax cost of straight debt - growth phase | C11: % | D11: 0.095 | H11: ASSUMPTION: unrated issuer; straight-bond yield ~Rf+4.7%. Converts' coupons understate cost (embedded option).
A12: t_hi | B12: Tax rate in WACC - growth phase | C12: % | D12: 0 | H12: LOGIC: no cash taxes paid while loss-making (NOLs/bonus depreciation) -> no interest tax shield.
A13: beta_term | B13: Beta - mature phase | C13: x | D13: 1 | H13: ASSUMPTION: mature satellite operator converges to market beta (Damodaran young-firm lifecycle method).
A14: dv_term | B14: Debt / capital - mature phase | C14: % | D14: 0.25 | H14: ASSUMPTION: mature telecom-like leverage.
A15: kd_term | B15: Pre-tax cost of debt - mature phase | C15: % | D15: 0.07 | H15: ASSUMPTION: BB-area mature issuer.
A16: t_term | B16: Tax rate in WACC - mature phase | C16: % | D16: 0.25 | H16: Equals cash tax rate.
A17: wacc_fade_start | B17: WACC fade start year | C17: yr | D17: 2031 | H17: ASSUMPTION: fade begins after build-out.
... A20: g | B20: Terminal growth (nominal) | C20: % | D20: 0.025 | H20: ASSUMPTION: <= long-run nominal GDP and < Rf (checked).
A21: OPERATIONS (all scenarios)
A22: tax_rate | B22: Cash tax rate (fed 21% + state) | C22: % | D22: 0.25 | H22: ASSUMPTION: 21% federal + ~4% blended state.
A23: nol_open | B23: Opening tax NOL pool (30-Jun-2026) | C23: $mm | D23: 1000 | H23: ASSUMPTION (flagged): accumulated deficit $1,253.6mm (10-Q) includes non-deductible items; haircut to $1.0bn.
A24: nol_limit | B24: NOL usage cap (% of taxable income) | C24: % | D24: 0.8 | H24: LAW: post-TCJA federal 80% limitation.
A25: bonus_dep | B25: 100% bonus depreciation on capex (1=on) | C25: flag | D25: 1 | H25: LAW: OBBBA (Jul-2025) permanently restored 100% bonus depreciation. Verify with tax adviser.
A26: sat_life | B26: Block 2 satellite design life | C26: yrs | D26: 7 | H26: SECONDARY DATA: 7-yr lifetime per Gunter's Space Page (BlueBird Block 2). Flagged for confirmation.
A27: loss_rate | B27: Launch / early-life loss rate | C27: % | D27: 0.05 | H27: ASSUMPTION: 1 of 8 Block 2 lost (BB7, Apr-2026) = 12.5% observed; industry mature ~3-5%.
A28: fleet_open | B28: Block 2 satellites launched at 30-Jun-2026 | C28: # | D28: 4 | H28: DATA: BB6 (Dec-2025) + BB8-10 (17-Jun-2026). BB7 lost. (10-Q Note 1)
A29: cip_sat | B29: Satellite CIP / advance launch payments 30-Jun-2026 | C29: $mm | D29: 1724.085 | H29: DATA: 10-Q Note 4, 'Satellite materials ... advance launch payments'.
A30: partner_subs | B30: MNO partner subscriber base | C30: mm | D30: 3000 | H30: DATA: company - 60+ MNO partners covering 'over 3 billion' subscribers (Q2-26 deck).
A31: t1_share | B31: Share of partner base in Tier-1 (developed) markets | C31: % | D31: 0.25 | H31: ASSUMPTION: US/Canada/Europe/Japan/Gulf partners ~ 750mm of 3bn.
A32: s0_t1 | B32: Tier-1 coverage starts at fleet of | C32: # | D32: 20 | H32: ASSUMPTION: intermittent service below ~20.
A33: sf_t1 | B33: Tier-1 continuous coverage at fleet of | C33: # | D33: 60 | H33: DATA: mgmt '~45-60 BlueBirds' for continuous US/Europe/Japan service (Q2-26 call); upper end used.
... A53: gov_cogs | B53: Government revenue COGS % | C53: % | D53: 0.35 | H53: ASSUMPTION: Q2-26 services COGS 16%; normalised higher at scale.
A55: Key | B55: Scenario parameter | C55: Unit | D55: Distress | E55: Bear | F55: Base | G55: Bull | H55: Source / rationale
A56: SCENARIO PROBABILITIES
A57: prob | B57: Scenario probability | C57: % | D57: 0.15 | E57: 0.25 | F57: 0.4 | G57: 0.2 | H57: ASSUMPTION: Distress reflects failure-to-scale/competitive loss; must sum to 100% (checked).
A58: CONSTELLATION DEPLOYMENT (Block 2 in orbit, end of period)
A59: fl_26 | B59: Fleet end-2026 | C59: # | D59: 15 | E59: 20 | F59: 25 | G59: 35 | H59: DATA anchor: 7 in orbit Aug-2026; mgmt target ~45 in early 2027. Base haircuts for BB7 loss / slip history.
A60: fl_27 | B60: Fleet end-2027 | C60: # | D60: 30 | E60: 45 | F60: 60 | G60: 75 | H60: ASSUMPTION.
A61: fl_28 | B61: Fleet end-2028 | C61: # | D61: 45 | E61: 60 | F61: 90 | G61: 100 | H61: ASSUMPTION.
A62: fl_29 | B62: Fleet end-2029 | C62: # | D62: 45 | E62: 75 | F62: 90 | G62: 110 | H62: ASSUMPTION.
A63: fl_ss | B63: Steady-state fleet (2030+) | C63: # | D63: 45 | E63: 90 | F63: 90 | G63: 120 | H63: ASSUMPTION: Distress = cannot fund beyond ~45.
A64: unit_cost | B64: Satellite cost incl. launch | C64: $mm | D64: 25 | E64: 24 | F64: 22 | G64: 21 | H64: DATA: mgmt $21-23mm/sat incl. direct materials & launch (Q2-26 call). Bear/Distress = overrun.
A65: unit_infl | B65: Unit cost inflation after 2028 | C65: % | D65: 0.025 | E65: 0.025 | F65: 0.02 | G65: 0.015 | H65: ASSUMPTION.
A66: cip_credit | B66: Share of satellite CIP that pre-funds future launches | C66: % | D66: 0.4 | E66: 0.45 | F66: 0.5 | G66: 0.6 | H66: ASSUMPTION (Tier-1 sensitivity): CIP also holds NRE, early-unit overruns, later-year launch deposits. R-04.
A67: COMMERCIAL SERVICE (MNO wholesale revenue share)
A68: t1_start | B68: Tier-1 commercial service start year | C68: yr | D68: 2029 | E68: 2028 | F68: 2027 | G68: 2027 | H68: DATA anchor: beta service 2026 (Q2-26 deck); commercial thereafter.
A69: t2_start | B69: Tier-2 commercial service start year | C69: yr | D69: 2031 | E69: 2030 | F69: 2029 | G69: 2028 | H69: ASSUMPTION.
A70: take_t1 | B70: Tier-1 peak take rate (% covered partner subs) | C70: % | D70: 0.03 | E70: 0.06 | F70: 0.1 | G70: 0.15 | H70: ASSUMPTION: incl. subs bundled in premium plans. Reverse-DCF solves market-implied value.
A71: take_t2 | B71: Tier-2 peak take rate | C71: % | D71: 0.005 | E71: 0.015 | F71: 0.03 | G71: 0.05 | H71: ASSUMPTION.
A72: ramp | B72: Adoption ramp: years from 5% to 95% of peak | C72: yrs | D72: 8 | E72: 7 | F72: 6 | G72: 5 | H72: ASSUMPTION (logistic).
A73: arpu_t1 | B73: Tier-1 ASTS monthly ARPU (after MNO share) | C73: $/mo | D73: 3.5 | E73: 4.25 | F73: 5 | G73: 6 | H73: DATA anchor: T-Mobile/Starlink T-Satellite retail $10/mo; ~50/50 wholesale share -> $5.
A74: arpu_t2 | B74: Tier-2 ASTS monthly ARPU | C74: $/mo | D74: 0.4 | E74: 0.6 | F74: 0.75 | G74: 1 | H74: ASSUMPTION: emerging-market pricing.
A75: px_g | B75: Annual ARPU change (from 2027) | C75: % | D75: -0.03 | E75: -0.02 | F75: -0.01 | G75: 0 | H75: ASSUMPTION: competitive pressure (Starlink D2C) vs inflation.
A76: var_cost | B76: Service variable cost % of service revenue | C76: % | D76: 0.15 | E76: 0.13 | F76: 0.12 | G76: 0.11 | H76: ASSUMPTION.
A77: GOVERNMENT & PRODUCT REVENUE
A78: gov_26 | B78: Government revenue 2026H2 | C78: $mm | D78: 35 | E78: 40 | F78: 45 | G78: 50 | H78: DATA anchor: >$125mm USG awards; ~$100mm funded 2026-27 (Q2-26 call).
A79: gov_27 | B79: Government revenue 2027 | C79: $mm | D79: 60 | E79: 80 | F79: 100 | G79: 130 | H79: ASSUMPTION.
A80: gov_28 | B80: Government revenue 2028 | C80: $mm | D80: 80 | E80: 120 | F80: 160 | G80: 220 | H80: ASSUMPTION.
A81: gov_29 | B81: Government revenue 2029 | C81: $mm | D81: 90 | E81: 150 | F81: 220 | G81: 320 | H81: ASSUMPTION.
A82: gov_30 | B82: Government revenue 2030 | C82: $mm | D82: 100 | E82: 180 | F82: 280 | G82: 420 | H82: ASSUMPTION.
A83: gov_g | B83: Government revenue growth after 2030 | C83: % | D83: 0.02 | E83: 0.04 | F83: 0.06 | G83: 0.08 | H83: ASSUMPTION.
A84: prod_26 | B84: Gateway/product revenue 2026H2 | C84: $mm | D84: 70 | E84: 80 | F84: 83.7 | G84: 90 | H84: DATA-DERIVED: Base ties FY26 to guidance midpoint $175mm (H1 $46.3mm + H2).
A85: prod_27 | B85: Gateway/product revenue 2027 | C85: $mm | D85: 60 | E85: 90 | F85: 120 | G85: 150 | H85: ASSUMPTION.
A86: prod_28 | B86: Gateway/product revenue 2028 | C86: $mm | D86: 30 | E86: 50 | F86: 80 | G86: 100 | H86: ASSUMPTION.
A87: prod_ss | B87: Gateway/product revenue 2029+ | C87: $mm | D87: 20 | E87: 30 | F87: 40 | G87: 50 | H87: ASSUMPTION.
A88: OPERATING COSTS (ex-D&A)
A89: opex_26 | B89: Fixed adj. opex (ex-COGS, ex-SBC) 2026H2 | C89: $mm | D89: 215 | E89: 210 | F89: 210 | G89: 205 | H89: DATA anchor: Q2-26 adj. opex ex-COGS $95.9mm/qtr, rising.
A90: opex_27 | B90: Fixed adj. opex 2027 | C90: $mm | D90: 480 | E90: 470 | F90: 460 | G90: 450 | H90: ASSUMPTION.
A91: opex_g28 | B91: Fixed opex growth 2028 | C91: % | D91: 0.08 | E91: 0.09 | F91: 0.1 | G91: 0.12 | H91: ASSUMPTION.
A92: opex_g29 | B92: Fixed opex growth 2029 | C92: % | D92: 0.05 | E92: 0.07 | F92: 0.08 | G92: 0.1 | H92: ASSUMPTION.
A93: opex_g30 | B93: Fixed opex growth 2030 | C93: % | D93: 0.03 | E93: 0.05 | F93: 0.06 | G93: 0.08 | H93: ASSUMPTION.
A94: opex_gss | B94: Fixed opex growth 2031+ | C94: % | D94: 0.035 | E94: 0.035 | F94: 0.035 | G94: 0.035 | H94: ASSUMPTION: ~inflation + 1%.
A95: sbc_26 | B95: Stock-based comp 2026H2 | C95: $mm | D95: 125 | E95: 125 | F95: 120 | G95: 120 | H95: DATA anchor: Q2-26 SBC $63.5mm/qtr. Treated as a real cost (R-06).
A96: sbc_27 | B96: Stock-based comp 2027 | C96: $mm | D96: 250 | E96: 240 | F96: 230 | G96: 230 | H96: ASSUMPTION.
A97: sbc_decay | B97: SBC annual decline (absolute) after 2027 | C97: % | D97: 0.08 | E97: 0.1 | F97: 0.1 | G97: 0.12 | H97: ASSUMPTION.
A98: sbc_floor | B98: SBC floor (% revenue) | C98: % | D98: 0.04 | E98: 0.035 | F98: 0.035 | G98: 0.03 | H98: ASSUMPTION.
A99: OTHER CAPEX & NON-DILUTIVE FUNDING
A100: ocx_26 | B100: Other capex (ground, facilities) 2026H2 | C100: $mm | D100: 180 | E100: 170 | F100: 150 | G100: 150 | H100: ASSUMPTION.
A101: ocx_27 | B101: Other capex 2027 | C101: $mm | D101: 250 | E101: 230 | F101: 200 | G101: 220 | H101: ASSUMPTION.
A102: ocx_28 | B102: Other capex 2028 | C102: $mm | D102: 150 | E102: 170 | F102: 150 | G102: 180 | H102: ASSUMPTION.
A103: ocx_pct | B103: Other capex % revenue (2029+) | C103: % | D103: 0.04 | E103: 0.035 | F103: 0.03 | G103: 0.03 | H103: ASSUMPTION.
A104: ocx_floor | B104: Other capex floor (2029+) | C104: $mm | D104: 60 | E104: 80 | F104: 80 | G104: 100 | H104: ASSUMPTION.
A105: jleo | B105: J-LEO non-dilutive capital received (2028) | C105: $mm | D105: 0 | E105: 0 | F105: 0 | G105: 300 | H105: DATA anchor: preliminary J-LEO selection, up to ~$1bn to Rakuten JV (Q2-26 deck). Bull only.
B107: Sum of scenario probabilities (must = 100%) | D107: =SUM(D57:G57) -> 1

Sheet Capital_Structure
A1: CAPITAL STRUCTURE & EQUITY BRIDGE INPUTS
A2: Balance sheet at 30-Jun-2026 (10-Q) pro forma for the Jul-2026 $1.15bn 2034 convertible. Share count at 6-Aug-2026. $mm; shares in mm unless stated.
A4: Share count (economic interests)
A5: Class | B5: Shares | G5: Source
A6: Class A common (6-Aug-2026) | B6: 299789305 | G6: 10-Q cover page
A7: Class B common = AST LLC units (exchangeable 1:1) | B7: 11215111 | G7: 10-Q cover page
A8: Class C common = AST LLC units (exchangeable 1:1) | B8: 78163078 | G8: 10-Q cover page
A9: Basic economic shares (mm) - S0 | B9: =SUM(B6:B8)/1000000 -> 389.16749 | G9: Up-C: Class B/C are voting-only; economics sit in AST LLC units exchangeable 1:1 (R-05).
A11: Cash & liquid assets
A12: Item | B12: $mm | C12: Include (1/0) | D12: Included $mm
A13: Cash & cash equivalents (30-Jun-2026) | B13: 2288.253 | C13: 1 | D13: =B13*C13 -> 2288.253 | G13: 10-Q balance sheet
A14: Restricted cash - non-current (UBS bridge collateral) | B14: 428.4 | C14: 1 | D14: =B14*C14 -> 428.4 | G14: 10-Q Note 3; nets vs UBS loan
A15: Restricted cash - current (LC/customs collateral) | B15: 6.181 | C15: 0 | D15: =B15*C15 -> 0 | G15: 10-Q; excluded - not available
A16: 2034 notes gross proceeds (Jul-2026, $1.15bn) | B16: 1150 | C16: 1 | D16: =B16*C16 -> 1150 | G16: 8-K / PR 21-Jul-2026
A17: less: discounts & expenses | B17: -18.8 | C17: 1 | D17: =B17*C17 -> -18.8 | G17: Net proceeds $1,131.2mm (pricing PR)
A18: less: capped-call cost (scaled to $1.15bn) | B18: -111.435 | C18: 1 | D18: =B18*C18 -> -111.435 | G18: $96.9mm for $1.0bn (PR) x 1.15 - ESTIMATE
A19: Related-party notes receivable | B19: 18.785 | C19: 1 | D19: =B19*C19 -> 18.785 | G19: 10-Q balance sheet
A20: Total cash & liquid assets | D20: =SUM(D13:D19) -> 3755.203
A21: Check: pro forma cash+restricted vs company-reported 'over $3.7bn' | D21: =D13+D14+B15+D16+D17+D18 -> 3742.599 | G21: Company: 'over $3.7 billion ... pro forma for convertible notes offering' (Q2-26 deck).
A23: Non-convertible debt (face)
A24: Trinity Capital equipment loan | B24: 48.638 | G24: 10-Q Note 6
A25: UBS bridge loan (cash-collateralised) | B25: 420 | G25: 10-Q Note 6
A26: Total non-convertible debt | B26: =SUM(B24:B25) -> 468.638
A28: Convertible notes
A29: Tranche | B29: Face $mm | C29: Conv. price $ | D29: Cap price $ | E29: Shares mm | F29: Trigger K $ | G29: Source
A30: 2032 4.25% converts | B30: 3.514 | C30: 26.99 | D30: 0 | E30: =B30/C30 -> 0.13019637 | F30: =IF(D30>0,D30,C30) -> 26.99 | G30: 10-Q Note 6; conv. rate 37.0535
A31: 2032 2.375% converts | B31: 325 | C31: 72.07 | D31: 0 | E31: =B31/C31 -> 4.5095046 | F31: =IF(D31>0,D31,C31) -> 72.07 | G31: 10-Q Note 6; conv. rate 13.8750 (capped call ignored - conservative)
A32: 2036 2.00% converts | B32: 1150 | C32: 96.3 | D32: 0 | E32: =B32/C32 -> 11.941848 | F32: =IF(D32>0,D32,C32) -> 96.3 | G32: Pricing PR Oct-2025, $96.30
A33: 2036 2.25% converts | B33: 1075 | C33: 116.3 | D33: 0 | E33: =B33/C33 -> 9.2433362 | F33: =IF(D33>0,D33,C33) -> 116.3 | G33: Pricing 8-K Feb-2026, conv. rate 8.5982
A34: 2034 1.625% converts (Jul-2026) | B34: 1150 | C34: 79.57 | D34: 149.2 | E34: =B34/C34 -> 14.452683 | F34: =IF(D34>0,D34,C34) -> 149.2 | G34: Pricing 8-K Jul-2026; capped call cap $149.20
A35: Total convertible face | B35: =SUM(B30:B34) -> 3703.514
A36: Check: total debt face at 30-Jun-2026 vs 10-Q ($3,022.2mm) | B36: =Capital_Structure!$B$26+Capital_Structure!$B$35-B34 -> 3022.152 | G36: 10-Q Note 6 total debt face $3,022,152k (excludes Jul-2026 notes).
A38: Equity awards (treasury-stock logic via value-consistent dilution engine)
A39: Award | B39: Count | C39: Strike $ | G39: Source
A40: 2020 Plan stock options | B40: 1957612 | C40: 9.2 | G40: Q1-26 10-Q (31-Mar-2026, latest disclosed)
A41: 2024 Plan stock options | B41: 55718 | C41: 24.65 | G41: Q2-26 10-Q count; strike = 10-K WAEP
A42: AST LLC incentive options | B42: 5320887 | C42: 1.01 | G42: Q2-25 10-Q (STALE - latest found)
A43: 2020 Plan RSUs | B43: 832699 | C43: 0 | G43: Q2-26 10-Q
A44: 2024 Plan RSUs | B44: 6873666 | C44: 0 | G44: FY25 proxy (STALE, Dec-2025 - latest found)
A46: Dilutive instrument table (feeds every Calc sheet)
A47: Instrument | B47: Trigger K $ | C47: Shares n (mm) | D47: Value added on conversion D $mm | G47: Convert: D = face (plain) or n x cap (capped call). Option: D = n x strike (cash in). RSU: K=0, D=0.
A48: =A30 -> 2032 4.25% converts | B48: =F30 -> 26.99 | C48: =E30 -> 0.13019637 | D48: =C48*B48 -> 3.514
A49: =A31 -> 2032 2.375% converts | B49: =F31 -> 72.07 | C49: =E31 -> 4.5095046 | D49: =C49*B49 -> 325
A50: =A32 -> 2036 2.00% converts | B50: =F32 -> 96.3 | C50: =E32 -> 11.941848 | D50: =C50*B50 -> 1150
A51: =A33 -> 2036 2.25% converts | B51: =F33 -> 116.3 | C51: =E33 -> 9.2433362 | D51: =C51*B51 -> 1075
A52: =A34 -> 2034 1.625% converts (Jul-2026) | B52: =F34 -> 149.2 | C52: =E34 -> 14.452683 | D52: =C52*B52 -> 2156.3403
A53: =A40 -> 2020 Plan stock options | B53: =C40 -> 9.2 | C53: =B40/1000000 -> 1.957612 | D53: =C53*B53 -> 18.01003
A54: =A41 -> 2024 Plan stock options | B54: =C41 -> 24.65 | C54: =B41/1000000 -> 0.055718 | D54: =C54*B54 -> 1.3734487
A55: =A42 -> AST LLC incentive options | B55: =C42 -> 1.01 | C55: =B42/1000000 -> 5.320887 | D55: =C55*B55 -> 5.3740959
A56: =A43 -> 2020 Plan RSUs | B56: =C43 -> 0 | C56: =B43/1000000 -> 0.832699 | D56: =C56*B56 -> 0
A57: =A44 -> 2024 Plan RSUs | B57: =C44 -> 0 | C57: =B44/1000000 -> 6.873666 | D57: =C57*B57 -> 0
A59: Market-implied reference points
A60: Equity market value at current price ($mm, basic) | B60: =Market_Data!$J$7*Capital_Structure!$B$9 -> 24291.835
A61: Market-implied EV ($mm) = mkt cap + all debt face - cash | B61: =Capital_Structure!$B$60+Capital_Structure!$B$26+Capital_Structure!$B$35-Capital_Structure!$D$20 -> 24708.784
A62: Debt / (debt + equity) at market | B62: =(Capital_Structure!$B$26+Capital_Structure!$B$35)/(Capital_Structure!$B$26+Capital_Structure!$B$35+Capital_Structure!$B$60) -> 0.14657651

Sheet WACC
A1: DISCOUNT RATE
A2: CAPM cost of equity; beta estimated live from IBKR data (Market_Data). Growth-phase WACC fades linearly to a mature WACC. Same WACC for every scenario - scenario risk is in cash flows, not the rate (R-03).
A5: Risk-free rate | C5: =Inputs!$D$7 -> 0.0484
A6: Equity risk premium | C6: =Inputs!$D$8 -> 0.0442
A7: Beta - growth phase (Blume-adjusted, live) | C7: =Market_Data!$J$13 -> 1.2804556
A8: Cost of equity - growth phase | C8: =C5+C7*C6 -> 0.10499614
A9: Debt / capital - growth phase | C9: =Inputs!$D$10 -> 0.15
A10: After-tax cost of debt - growth phase | C10: =Inputs!$D$11*(1-Inputs!$D$12) -> 0.095
A11: WACC - growth phase | C11: =(1-C9)*C8+C9*C10+Inputs!$D$19 -> 0.10349672
A12: Beta - mature phase | C12: =Inputs!$D$13 -> 1
A13: Cost of equity - mature phase | C13: =C5+C12*C6 -> 0.0926
A14: Debt / capital - mature phase | C14: =Inputs!$D$14 -> 0.25
A15: After-tax cost of debt - mature phase | C15: =Inputs!$D$15*(1-Inputs!$D$16) -> 0.0525
A16: WACC - mature / terminal | C16: =(1-C14)*C13+C14*C15+Inputs!$D$19 -> 0.082575
A19: Period | D19: 2026H2 | E19: 2027 | F19: 2028 | G19: 2029 | H19: 2030 | I19: 2031 | J19: 2032 | K19: 2033 | L19: 2034 | M19: 2035 | N19: 2036 | O19: 2037 | P19: 2038 | Q19: 2039 | R19: 2040
A20: Year | D20: 2026 | E20: 2027 | F20: 2028 | G20: 2029 | H20: 2030 | I20: 2031 | J20: 2032 | K20: 2033 | L20: 2034 | M20: 2035 | N20: 2036 | O20: 2037 | P20: 2038 | Q20: 2039 | R20: 2040
A21: WACC applied | D21: =IF(D20<Inputs!$D$17,$C$11,IF(D20>=Inputs!$D$18,$C$16,$C$11+($C$16-$C$11)*(D20-Inputs!$D$17+1)/(Inputs!$D$18-Inputs!$D$17+1))) -> 0.10349672 | E21: =IF(E20<Inputs!$D$17,$C$11,IF(E20>=Inputs!$D$18,$C$16,$C$11+($C$16-$C$11)*(E20-Inputs!$D$17+1)/(Inputs!$D$18-Inputs!$D$17+1))) -> 0.10349672 | F21: =IF(F20<Inputs!$D$17,$C$11,IF(F20>=Inputs!$D$18,$C$16,$C$11+($C$16-$C$11)*(F20-Inputs!$D$17+1)/(Inputs!$D$18-Inputs!$D$17+1))) -> 0.10349672 | G21: =IF(G20<Inputs!$D$17,$C$11,IF(G20>=Inputs!$D$18,$C$16,$C$11+($C$16-$C$11)*(G20-Inputs!$D$17+1)/(Inputs!$D$18-Inputs!$D$17+1))) -> 0.10349672 | H21: =IF(H20<Inputs!$D$17,$C$11,IF(H20>=Inputs!$D$18,$C$16,$C$11+($C$16-$C$11)*(H20-Inputs!$D$17+1)/(Inputs!$D$18-Inputs!$D$17+1))) -> 0.10349672 | I21: =IF(I20<Inputs!$D$17,$C$11,IF(I20>=Inputs!$D$18,$C$16,$C$11+($C$16-$C$11)*(I20-Inputs!$D$17+1)/(Inputs!$D$18-Inputs!$D$17+1))) -> 0.099312374 | J21: =IF(J20<Inputs!$D$17,$C$11,IF(J20>=Inputs!$D$18,$C$16,$C$11+($C$16-$C$11)*(J20-Inputs!$D$17+1)/(Inputs!$D$18-Inputs!$D$17+1))) -> 0.095128031 | K21: =IF(K20<Inputs!$D$17,$C$11,IF(K20>=Inputs!$D$18,$C$16,$C$11+($C$16-$C$11)*(K20-Inputs!$D$17+1)/(Inputs!$D$18-Inputs!$D$17+1))) -> 0.090943687 | ... R21: =IF(R20<Inputs!$D$17,$C$11,IF(R20>=Inputs!$D$18,$C$16,$C$11+($C$16-$C$11)*(R20-Inputs!$D$17+1)/(Inputs!$D$18-Inputs!$D$17+1))) -> 0.082575

Sheet Market_Data
A1: MARKET DATA (Interactive Brokers)
A2: Weekly closes, 2-yr window, retrieved from IBKR 10-Sep-2026. ASTS conid 480745767 (NASDAQ), SPY conid 756733 (ARCA). Last bar is a partial week (excluded from regression).
A5: Week start | B5: ASTS close | C5: SPY close | D5: ASTS ret | E5: SPY ret | F5: ASTS peak | G5: Drawdown | I5: Statistic | J5: Value | K5: Note
A6: 2024-09-11 | B6: 29.83 | C6: 562.01 | F6: =B6 -> 29.83 | G6: =B6/F6-1 -> 0
A7: 2024-09-16 | B7: 26.5 | C7: 568.25 | D7: =B7/B6-1 -> -0.11163258 | E7: =C7/C6-1 -> 0.011103005 | F7: =MAX(F6,B7) -> 29.83 | G7: =B7/F7-1 -> -0.11163258 | I7: Current price (last close, $) | J7: =B110 -> 62.42
A8: 2024-09-23 | B8: 25.32 | C8: 571.47 | D8: =B8/B7-1 -> -0.044528302 | E8: =C8/C7-1 -> 0.00566652 | F8: =MAX(F7,B8) -> 29.83 | G8: =B8/F8-1 -> -0.15119008 | I8: Full-week returns in regression (n) | J8: =COUNT(D7:D109) -> 103
A9: 2024-09-30 | B9: 26.11 | C9: 572.98 | D9: =B9/B8-1 -> 0.031200632 | E9: =C9/C8-1 -> 0.0026423084 | F9: =MAX(F8,B9) -> 29.83 | G9: =B9/F9-1 -> -0.12470667 | I9: Raw beta vs SPY (weekly, 2y) | J9: =SLOPE(D7:D109,E7:E109) -> 1.4185905 | K9: 95% CI roughly beta +/- 1.96 x SE: statistically weak (R-01).
A10: 2024-10-07 | B10: 24.18 | C10: 579.58 | D10: =B10/B9-1 -> -0.073918039 | E10: =C10/C9-1 -> 0.011518727 | F10: =MAX(F9,B10) -> 29.83 | G10: =B10/F10-1 -> -0.18940664 | I10: Std. error of beta | J10: =STEYX(D7:D109,E7:E109)/(STDEV(E7:E109)*SQRT(COUNT(E7:E109)-1)) -> 0.60270766
A11: 2024-10-14 | B11: 28.14 | C11: 584.59 | D11: =B11/B10-1 -> 0.16377171 | E11: =C11/C10-1 -> 0.0086441906 | F11: =MAX(F10,B11) -> 29.83 | G11: =B11/F11-1 -> -0.056654375 | I11: t-statistic | J11: =J9/J10 -> 2.3536958
A12: 2024-10-21 | B12: 25.62 | C12: 579.04 | D12: =B12/B11-1 -> -0.089552239 | E12: =C12/C11-1 -> -0.0094938333 | F12: =MAX(F11,B12) -> 29.83 | G12: =B12/F12-1 -> -0.14113309 | I12: R-squared (systematic share of variance) | J12: =RSQ(D7:D109,E7:E109) -> 0.051998215
A13: 2024-10-28 | B13: 23.85 | C13: 571.04 | D13: =B13/B12-1 -> -0.069086651 | E13: =C13/C12-1 -> -0.013815971 | F13: =MAX(F12,B13) -> 29.83 | G13: =B13/F13-1 -> -0.20046933 | I13: Blume-adjusted beta (used in WACC) | J13: =Inputs!$D$9*J9+(1-Inputs!$D$9) -> 1.2804556 | K13: Blume (1971): 0.67 x raw + 0.33. Chosen over raw/shrinkage - see Review_Log R-01.
A14: 2024-11-04 | B14: 21.99 | C14: 598.19 | D14: =B14/B13-1 -> -0.077987421 | E14: =C14/C13-1 -> 0.04754483 | F14: =MAX(F13,B14) -> 29.83 | G14: =B14/F14-1 -> -0.26282266 | I14: ASTS annualised volatility | J14: =STDEV(D7:D109)*SQRT(52) -> 0.93751899
A15: 2024-11-11 | B15: 24.23 | C15: 585.75 | D15: =B15/B14-1 -> 0.10186448 | E15: =C15/C14-1 -> -0.020796068 | F15: =MAX(F14,B15) -> 29.83 | G15: =B15/F15-1 -> -0.18773047 | I15: SPY annualised volatility | J15: =STDEV(E7:E109)*SQRT(52) -> 0.15070139
A16: 2024-11-18 | B16: 24.1 | C16: 595.51 | D16: =B16/B15-1 -> -0.0053652497 | E16: =C16/C15-1 -> 0.016662399 | F16: =MAX(F15,B16) -> 29.83 | G16: =B16/F16-1 -> -0.1920885 | I16: Idiosyncratic volatility | J16: =J14*SQRT(1-J12) -> 0.91281896
A17: 2024-11-25 | B17: 23.81 | C17: 602.55 | D17: =B17/B16-1 -> -0.012033195 | E17: =C17/C16-1 -> 0.0118218 | F17: =MAX(F16,B17) -> 29.83 | G17: =B17/F17-1 -> -0.20181026 | I17: Max drawdown (2y) | J17: =MIN(G6:G110) -> -0.51455472
A18: 2024-12-02 | B18: 25.32 | C18: 607.81 | D18: =B18/B17-1 -> 0.063418732 | E18: =C18/C17-1 -> 0.008729566 | F18: =MAX(F17,B18) -> 29.83 | G18: =B18/F18-1 -> -0.15119008 | I18: 1-week historical VaR 95% (return) | J18: =PERCENTILE(D7:D109,0.05) -> -0.15690771
A19: 2024-12-09 | B19: 23.48 | C19: 604.21 | D19: =B19/B18-1 -> -0.072669826 | E19: =C19/C18-1 -> -0.0059229035 | F19: =MAX(F18,B19) -> 29.83 | G19: =B19/F19-1 -> -0.21287295 | I19: 1-week CVaR 95% (mean of returns <= VaR) | J19: =AVERAGEIF(D7:D109,"<="&J18) -> -0.17702274
A20: 2024-12-16 | B20: 22.88 | C20: 591.15 | D20: =B20/B19-1 -> -0.025553663 | E20: =C20/C19-1 -> -0.021615001 | F20: =MAX(F19,B20) -> 29.83 | G20: =B20/F20-1 -> -0.23298693 | I20: 1-week parametric VaR 95% (normal) | J20: =AVERAGE(D7:D109)-1.645*STDEV(D7:D109) -> -0.19882201
A21: 2024-12-23 | B21: 22.92 | C21: 595.01 | D21: =B21/B20-1 -> 0.0017482517 | E21: =C21/C20-1 -> 0.0065296456 | F21: =MAX(F20,B21) -> 29.83 | G21: =B21/F21-1 -> -0.23164599 | I21: Annualised downside deviation (MAR 0) | J21: =SQRT(SUMPRODUCT((D7:D109<0)*(D7:D109)^2)/COUNT(D7:D109))*SQRT(52) -> 0.50496483
A22: 2024-12-30 | B22: 23.97 | C22: 591.95 | D22: =B22/B21-1 -> 0.045811518 | E22: =C22/C21-1 -> -0.0051427707 | F22: =MAX(F21,B22) -> 29.83 | G22: =B22/F22-1 -> -0.19644653 | I22: 2-yr high close | J22: =MAX(B6:B110) -> 115.77
A23: 2025-01-06 | B23: 22.37 | C23: 580.49 | D23: =B23/B22-1 -> -0.066750104 | E23: =C23/C22-1 -> -0.019359743 | F23: =MAX(F22,B23) -> 29.83 | G23: =B23/F23-1 -> -0.25008381 | I23: 2-yr low close | J23: =MIN(B6:B110) -> 20.07
A24: 2025-01-13 | B24: 20.78 | C24: 597.58 | D24: =B24/B23-1 -> -0.071077336 | E24: =C24/C23-1 -> 0.029440645 | F24: =MAX(F23,B24) -> 29.83 | G24: =B24/F24-1 -> -0.30338585
A25: 2025-01-21 | B25: 20.35 | C25: 607.97 | D25: =B25/B24-1 -> -0.020692974 | E25: =C25/C24-1 -> 0.017386793 | F25: =MAX(F24,B25) -> 29.83 | G25: =B25/F25-1 -> -0.31780087
A26: 2025-01-27 | B26: 20.24 | C26: 601.82 | D26: =B26/B25-1 -> -0.0054054054 | E26: =C26/C25-1 -> -0.010115631 | F26: =MAX(F25,B26) -> 29.83 | G26: =B26/F26-1 -> -0.32148843
A27: 2025-02-03 | B27: 26.51 | C27: 600.77 | D27: =B27/B26-1 -> 0.30978261 | E27: =C27/C26-1 -> -0.0017447077 | F27: =MAX(F26,B27) -> 29.83 | G27: =B27/F27-1 -> -0.11129735
A28: 2025-02-10 | B28: 32.1 | C28: 609.7 | D28: =B28/B27-1 -> 0.21086382 | E28: =C28/C27-1 -> 0.014864258 | F28: =MAX(F27,B28) -> 32.1 | G28: =B28/F28-1 -> 0
A29: 2025-02-18 | B29: 28.64 | C29: 599.94 | D29: =B29/B28-1 -> -0.10778816 | E29: =C29/C28-1 -> -0.016007873 | F29: =MAX(F28,B29) -> 32.1 | G29: =B29/F29-1 -> -0.10778816
A30: 2025-02-24 | B30: 27.11 | C30: 594.18 | D30: =B30/B29-1 -> -0.053421788 | E30: =C30/C29-1 -> -0.0096009601 | F30: =MAX(F29,B30) -> 32.1 | G30: =B30/F30-1 -> -0.15545171
A31: 2025-03-03 | B31: 33.4 | C31: 575.92 | D31: =B31/B30-1 -> 0.23201771 | E31: =C31/C30-1 -> -0.030731428 | F31: =MAX(F30,B31) -> 33.4 | G31: =B31/F31-1 -> 0
A32: 2025-03-10 | B32: 28.15 | C32: 562.81 | D32: =B32/B31-1 -> -0.15718563 | E32: =C32/C31-1 -> -0.022763578 | F32: =MAX(F31,B32) -> 33.4 | G32: =B32/F32-1 -> -0.15718563
A33: 2025-03-17 | B33: 25.71 | C33: 563.98 | D33: =B33/B32-1 -> -0.086678508 | E33: =C33/C32-1 -> 0.0020788543 | F33: =MAX(F32,B33) -> 33.4 | G33: =B33/F33-1 -> -0.23023952
A34: 2025-03-24 | B34: 24.06 | C34: 555.66 | D34: =B34/B33-1 -> -0.064177363 | E34: =C34/C33-1 -> -0.014752296 | F34: =MAX(F33,B34) -> 33.4 | G34: =B34/F34-1 -> -0.27964072
A35: 2025-03-31 | B35: 20.07 | C35: 505.28 | D35: =B35/B34-1 -> -0.16583541 | E35: =C35/C34-1 -> -0.090666955 | F35: =MAX(F34,B35) -> 33.4 | G35: =B35/F35-1 -> -0.3991018
... A110: 2026-09-08 | B110: 62.42 | C110: 762.4 | D110: =B110/B109-1 -> 0.0017653667 | E110: =C110/C109-1 -> -0.010114387 | F110: =MAX(F109,B110) -> 115.77 | G110: =B110/F110-1 -> -0.4608275

Sheet Calc_Base
A1: MODEL - BASE SCENARIO
A2: Live formulas. Inputs from 'Inputs' column F (scenario) / D (global). $mm unless stated. Periods: 2026H2 stub + 2027-2040; col S = 2041 normalised.
A5: Period | D5: 2026H2 | E5: 2027 | F5: 2028 | G5: 2029 | H5: 2030 | I5: 2031 | J5: 2032 | K5: 2033 | L5: 2034 | M5: 2035 | N5: 2036 | O5: 2037 | P5: 2038 | Q5: 2039 | R5: 2040 | S5: 2041N
A6: Calendar year | B6: yr | D6: 2026 | E6: 2027 | F6: 2028 | G6: 2029 | H6: 2030 | I6: 2031 | J6: 2032 | K6: 2033 | L6: 2034 | M6: 2035 | N6: 2036 | O6: 2037 | P6: 2038 | Q6: 2039 | R6: 2040 | S6: 2041
A7: Period length (years) | B7: yrs | D7: 0.5 | E7: 1 | F7: 1 | G7: 1 | H7: 1 | I7: 1 | J7: 1 | K7: 1 | L7: 1 | M7: 1 | N7: 1 | O7: 1 | P7: 1 | Q7: 1 | R7: 1
A8: Period start (year fraction) | B8: yrs | D8: 2026.5 | E8: 2027 | F8: 2028 | G8: 2029 | H8: 2030 | I8: 2031 | J8: 2032 | K8: 2033 | L8: 2034 | M8: 2035 | N8: 2036 | O8: 2037 | P8: 2038 | Q8: 2039 | R8: 2040
A9: Cash-flow timing (mid-period) | B9: yrs | D9: =D8+D7/2 -> 2026.75 | E9: =E8+E7/2 -> 2027.5 | F9: =F8+F7/2 -> 2028.5 | G9: =G8+G7/2 -> 2029.5 | H9: =H8+H7/2 -> 2030.5 | I9: =I8+I7/2 -> 2031.5 | J9: =J8+J7/2 -> 2032.5 | K9: =K8+K7/2 -> 2033.5 | ... R9: =R8+R7/2 -> 2040.5
A10: CONSTELLATION (Block 2 satellites)
A11: Target fleet, end of period | B11: # | D11: =IF(D$6=2026,Inputs!$F$59,IF(D$6=2027,Inputs!$F$60,IF(D$6=2028,Inputs!$F$61,IF(D$6=2029,Inputs!$F$62,Inputs!$F$63)))) -> 25 | E11: =IF(E$6=2026,Inputs!$F$59,IF(E$6=2027,Inputs!$F$60,IF(E$6=2028,Inputs!$F$61,IF(E$6=2029,Inputs!$F$62,Inputs!$F$63)))) -> 60 | F11: =IF(F$6=2026,Inputs!$F$59,IF(F$6=2027,Inputs!$F$60,IF(F$6=2028,Inputs!$F$61,IF(F$6=2029,Inputs!$F$62,Inputs!$F$63)))) -> 90 | G11: =IF(G$6=2026,Inputs!$F$59,IF(G$6=2027,Inputs!$F$60,IF(G$6=2028,Inputs!$F$61,IF(G$6=2029,Inputs!$F$62,Inputs!$F$63)))) -> 90 | H11: =IF(H$6=2026,Inputs!$F$59,IF(H$6=2027,Inputs!$F$60,IF(H$6=2028,Inputs!$F$61,IF(H$6=2029,Inputs!$F$62,Inputs!$F$63)))) -> 90 | I11: =IF(I$6=2026,Inputs!$F$59,IF(I$6=2027,Inputs!$F$60,IF(I$6=2028,Inputs!$F$61,IF(I$6=2029,Inputs!$F$62,Inputs!$F$63)))) -> 90 | J11: =IF(J$6=2026,Inputs!$F$59,IF(J$6=2027,Inputs!$F$60,IF(J$6=2028,Inputs!$F$61,IF(J$6=2029,Inputs!$F$62,Inputs!$F$63)))) -> 90 | K11: =IF(K$6=2026,Inputs!$F$59,IF(K$6=2027,Inputs!$F$60,IF(K$6=2028,Inputs!$F$61,IF(K$6=2029,Inputs!$F$62,Inputs!$F$63)))) -> 90 | ... R11: =IF(R$6=2026,Inputs!$F$59,IF(R$6=2027,Inputs!$F$60,IF(R$6=2028,Inputs!$F$61,IF(R$6=2029,Inputs!$F$62,Inputs!$F$63)))) -> 90
A12: Beginning fleet | B12: # | D12: =Inputs!$D$28 -> 4 | E12: =D15 -> 25 | F12: =E15 -> 60 | G12: =F15 -> 90 | H12: =G15 -> 90 | I12: =H15 -> 90 | J12: =I15 -> 90 | K12: =J15 -> 90 | L12: =K15 -> 90 | ... R12: =Q15 -> 90
A13: Retirements (end of design life) | B13: # | D13: =0 -> 0 | E13: =IF(E$6-ROUND(Inputs!$D$26,0)=2026,$D$14+Inputs!$D$28,IF(E$6-ROUND(Inputs!$D$26,0)>=2027,INDEX($D$14:D14,1,E$6-ROUND(Inputs!$D$26,0)-2026+1),0)) -> 0 | F13: =IF(F$6-ROUND(Inputs!$D$26,0)=2026,$D$14+Inputs!$D$28,IF(F$6-ROUND(Inputs!$D$26,0)>=2027,INDEX($D$14:E14,1,F$6-ROUND(Inputs!$D$26,0)-2026+1),0)) -> 0 | G13: =IF(G$6-ROUND(Inputs!$D$26,0)=2026,$D$14+Inputs!$D$28,IF(G$6-ROUND(Inputs!$D$26,0)>=2027,INDEX($D$14:F14,1,G$6-ROUND(Inputs!$D$26,0)-2026+1),0)) -> 0 | H13: =IF(H$6-ROUND(Inputs!$D$26,0)=2026,$D$14+Inputs!$D$28,IF(H$6-ROUND(Inputs!$D$26,0)>=2027,INDEX($D$14:G14,1,H$6-ROUND(Inputs!$D$26,0)-2026+1),0)) -> 0 | I13: =IF(I$6-ROUND(Inputs!$D$26,0)=2026,$D$14+Inputs!$D$28,IF(I$6-ROUND(Inputs!$D$26,0)>=2027,INDEX($D$14:H14,1,I$6-ROUND(Inputs!$D$26,0)-2026+1),0)) -> 0 | J13: =IF(J$6-ROUND(Inputs!$D$26,0)=2026,$D$14+Inputs!$D$28,IF(J$6-ROUND(Inputs!$D$26,0)>=2027,INDEX($D$14:I14,1,J$6-ROUND(Inputs!$D$26,0)-2026+1),0)) -> 0 | K13: =IF(K$6-ROUND(Inputs!$D$26,0)=2026,$D$14+Inputs!$D$28,IF(K$6-ROUND(Inputs!$D$26,0)>=2027,INDEX($D$14:J14,1,K$6-ROUND(Inputs!$D$26,0)-2026+1),0)) -> 25 | L13: =IF(L$6-ROUND(Inputs!$D$26,0)=2026,$D$14+Inputs!$D$28,IF(L$6-ROUND(Inputs!$D$26,0)>=2027,INDEX($D$14:K14,1,L$6-ROUND(Inputs!$D$26,0)-2026+1),0)) -> 35 | ... R13: =IF(R$6-ROUND(Inputs!$D$26,0)=2026,$D$14+Inputs!$D$28,IF(R$6-ROUND(Inputs!$D$26,0)>=2027,INDEX($D$14:Q14,1,R$6-ROUND(Inputs!$D$26,0)-2026+1),0)) -> 25
A14: Successful launches (net adds + replacements) | B14: # | D14: =MAX(0,D11-D12+D13) -> 21 | E14: =MAX(0,E11-E12+E13) -> 35 | F14: =MAX(0,F11-F12+F13) -> 30 | G14: =MAX(0,G11-G12+G13) -> 0 | H14: =MAX(0,H11-H12+H13) -> 0 | I14: =MAX(0,I11-I12+I13) -> 0 | J14: =MAX(0,J11-J12+J13) -> 0 | K14: =MAX(0,K11-K12+K13) -> 25 | ... R14: =MAX(0,R11-R12+R13) -> 25
A15: Ending fleet | B15: # | D15: =D12-D13+D14 -> 25 | E15: =E12-E13+E14 -> 60 | F15: =F12-F13+F14 -> 90 | G15: =G12-G13+G14 -> 90 | H15: =H12-H13+H14 -> 90 | I15: =I12-I13+I14 -> 90 | J15: =J12-J13+J14 -> 90 | K15: =K12-K13+K14 -> 90 | ... R15: =R12-R13+R14 -> 90
A16: Satellites built incl. launch losses | B16: # | D16: =D14/(1-Inputs!$D$27) -> 22.105263 | E16: =E14/(1-Inputs!$D$27) -> 36.842105 | F16: =F14/(1-Inputs!$D$27) -> 31.578947 | G16: =G14/(1-Inputs!$D$27) -> 0 | H16: =H14/(1-Inputs!$D$27) -> 0 | I16: =I14/(1-Inputs!$D$27) -> 0 | J16: =J14/(1-Inputs!$D$27) -> 0 | K16: =K14/(1-Inputs!$D$27) -> 26.315789 | ... R16: =R14/(1-Inputs!$D$27) -> 26.315789
A17: Average fleet in orbit | B17: # | D17: =(D12+D15)/2 -> 14.5 | E17: =(E12+E15)/2 -> 42.5 | F17: =(F12+F15)/2 -> 75 | G17: =(G12+G15)/2 -> 90 | H17: =(H12+H15)/2 -> 90 | I17: =(I12+I15)/2 -> 90 | J17: =(J12+J15)/2 -> 90 | K17: =(K12+K15)/2 -> 90 | ... R17: =(R12+R15)/2 -> 90
A18: Unit cost incl. launch ($mm/sat) | B18: $mm | D18: =Inputs!$F$64*(1+Inputs!$F$65)^MAX(0,D$6-2028) -> 22 | E18: =Inputs!$F$64*(1+Inputs!$F$65)^MAX(0,E$6-2028) -> 22 | F18: =Inputs!$F$64*(1+Inputs!$F$65)^MAX(0,F$6-2028) -> 22 | G18: =Inputs!$F$64*(1+Inputs!$F$65)^MAX(0,G$6-2028) -> 22.44 | H18: =Inputs!$F$64*(1+Inputs!$F$65)^MAX(0,H$6-2028) -> 22.8888 | I18: =Inputs!$F$64*(1+Inputs!$F$65)^MAX(0,I$6-2028) -> 23.346576 | J18: =Inputs!$F$64*(1+Inputs!$F$65)^MAX(0,J$6-2028) -> 23.813508 | K18: =Inputs!$F$64*(1+Inputs!$F$65)^MAX(0,K$6-2028) -> 24.289778 | ... R18: =Inputs!$F$64*(1+Inputs!$F$65)^MAX(0,R$6-2028) -> 27.901319
A19: Satellite capex (gross, placed in service) | B19: $mm | D19: =D16*D18 -> 486.31579 | E19: =E16*E18 -> 810.52632 | F19: =F16*F18 -> 694.73684 | G19: =G16*G18 -> 0 | H19: =H16*H18 -> 0 | I19: =I16*I18 -> 0 | J19: =J16*J18 -> 0 | K19: =K16*K18 -> 639.20468 | ... R19: =R16*R18 -> 734.24525
A20: CIP pre-funding pool (scalar, col C) | C20: =Inputs!$D$29*Inputs!$F$66 -> 862.0425
A21: CIP credit applied (already-paid capex) | B21: $mm | D21: =MIN(D19,$C$20) -> 486.31579 | E21: =MIN(E19,$C$20-SUM($D$21:D21)) -> 375.72671 | F21: =MIN(F19,$C$20-SUM($D$21:E21)) -> 0 | G21: =MIN(G19,$C$20-SUM($D$21:F21)) -> 0 | H21: =MIN(H19,$C$20-SUM($D$21:G21)) -> 0 | I21: =MIN(I19,$C$20-SUM($D$21:H21)) -> 0 | J21: =MIN(J19,$C$20-SUM($D$21:I21)) -> 0 | K21: =MIN(K19,$C$20-SUM($D$21:J21)) -> 0 | L21: =MIN(L19,$C$20-SUM($D$21:K21)) -> 0 | ... R21: =MIN(R19,$C$20-SUM($D$21:Q21)) -> 0
A22: Satellite capex, cash | B22: $mm | D22: =D19-D21 -> 0 | E22: =E19-E21 -> 434.79961 | F22: =F19-F21 -> 694.73684 | G22: =G19-G21 -> 0 | H22: =H19-H21 -> 0 | I22: =I19-I21 -> 0 | J22: =J19-J21 -> 0 | K22: =K19-K21 -> 639.20468 | ... R22: =R19-R21 -> 734.24525
A23: REVENUE BUILD
A24: Tier-1 coverage (fraction of partner base) | B24: % | D24: =MIN(1,MAX(0,(D17-Inputs!$D$32)/(Inputs!$D$33-Inputs!$D$32))) -> 0 | E24: =MIN(1,MAX(0,(E17-Inputs!$D$32)/(Inputs!$D$33-Inputs!$D$32))) -> 0.5625 | F24: =MIN(1,MAX(0,(F17-Inputs!$D$32)/(Inputs!$D$33-Inputs!$D$32))) -> 1 | G24: =MIN(1,MAX(0,(G17-Inputs!$D$32)/(Inputs!$D$33-Inputs!$D$32))) -> 1 | H24: =MIN(1,MAX(0,(H17-Inputs!$D$32)/(Inputs!$D$33-Inputs!$D$32))) -> 1 | I24: =MIN(1,MAX(0,(I17-Inputs!$D$32)/(Inputs!$D$33-Inputs!$D$32))) -> 1 | J24: =MIN(1,MAX(0,(J17-Inputs!$D$32)/(Inputs!$D$33-Inputs!$D$32))) -> 1 | K24: =MIN(1,MAX(0,(K17-Inputs!$D$32)/(Inputs!$D$33-Inputs!$D$32))) -> 1 | ... R24: =MIN(1,MAX(0,(R17-Inputs!$D$32)/(Inputs!$D$33-Inputs!$D$32))) -> 1
A25: Tier-2 coverage | B25: % | D25: =MIN(1,MAX(0,(D17-Inputs!$D$34)/(Inputs!$D$35-Inputs!$D$34))) -> 0 | E25: =MIN(1,MAX(0,(E17-Inputs!$D$34)/(Inputs!$D$35-Inputs!$D$34))) -> 0 | F25: =MIN(1,MAX(0,(F17-Inputs!$D$34)/(Inputs!$D$35-Inputs!$D$34))) -> 0.5 | G25: =MIN(1,MAX(0,(G17-Inputs!$D$34)/(Inputs!$D$35-Inputs!$D$34))) -> 1 | H25: =MIN(1,MAX(0,(H17-Inputs!$D$34)/(Inputs!$D$35-Inputs!$D$34))) -> 1 | I25: =MIN(1,MAX(0,(I17-Inputs!$D$34)/(Inputs!$D$35-Inputs!$D$34))) -> 1 | J25: =MIN(1,MAX(0,(J17-Inputs!$D$34)/(Inputs!$D$35-Inputs!$D$34))) -> 1 | K25: =MIN(1,MAX(0,(K17-Inputs!$D$34)/(Inputs!$D$35-Inputs!$D$34))) -> 1 | ... R25: =MIN(1,MAX(0,(R17-Inputs!$D$34)/(Inputs!$D$35-Inputs!$D$34))) -> 1
A26: Logistic steepness k = 2 ln(19) / ramp (col C) | C26: =2*LN(19)/Inputs!$F$72 -> 0.98147966
A27: Tier-1 adoption (take rate of covered subs) | B27: % | D27: =IF(D9>=Inputs!$F$68,Inputs!$F$70/(1+EXP(-$C$26*(D9-(Inputs!$F$68+Inputs!$F$72/2)))),0) -> 0 | E27: =IF(E9>=Inputs!$F$68,Inputs!$F$70/(1+EXP(-$C$26*(E9-(Inputs!$F$68+Inputs!$F$72/2)))),0) -> 0.0079168458 | F27: =IF(F9>=Inputs!$F$68,Inputs!$F$70/(1+EXP(-$C$26*(F9-(Inputs!$F$68+Inputs!$F$72/2)))),0) -> 0.01866055 | G27: =IF(G9>=Inputs!$F$68,Inputs!$F$70/(1+EXP(-$C$26*(G9-(Inputs!$F$68+Inputs!$F$72/2)))),0) -> 0.03797193 | H27: =IF(H9>=Inputs!$F$68,Inputs!$F$70/(1+EXP(-$C$26*(H9-(Inputs!$F$68+Inputs!$F$72/2)))),0) -> 0.06202807 | I27: =IF(I9>=Inputs!$F$68,Inputs!$F$70/(1+EXP(-$C$26*(I9-(Inputs!$F$68+Inputs!$F$72/2)))),0) -> 0.08133945 | J27: =IF(J9>=Inputs!$F$68,Inputs!$F$70/(1+EXP(-$C$26*(J9-(Inputs!$F$68+Inputs!$F$72/2)))),0) -> 0.092083154 | K27: =IF(K9>=Inputs!$F$68,Inputs!$F$70/(1+EXP(-$C$26*(K9-(Inputs!$F$68+Inputs!$F$72/2)))),0) -> 0.096878605 | ... R27: =IF(R9>=Inputs!$F$68,Inputs!$F$70/(1+EXP(-$C$26*(R9-(Inputs!$F$68+Inputs!$F$72/2)))),0) -> 0.099996655
A28: Tier-2 adoption (take rate of covered subs) | B28: % | D28: =IF(D9>=Inputs!$F$69,Inputs!$F$71/(1+EXP(-$C$26*(D9-(Inputs!$F$69+Inputs!$F$72/2)))),0) -> 0 | E28: =IF(E9>=Inputs!$F$69,Inputs!$F$71/(1+EXP(-$C$26*(E9-(Inputs!$F$69+Inputs!$F$72/2)))),0) -> 0 | F28: =IF(F9>=Inputs!$F$69,Inputs!$F$71/(1+EXP(-$C$26*(F9-(Inputs!$F$69+Inputs!$F$72/2)))),0) -> 0 | G28: =IF(G9>=Inputs!$F$69,Inputs!$F$71/(1+EXP(-$C$26*(G9-(Inputs!$F$69+Inputs!$F$72/2)))),0) -> 0.0023750537 | H28: =IF(H9>=Inputs!$F$69,Inputs!$F$71/(1+EXP(-$C$26*(H9-(Inputs!$F$69+Inputs!$F$72/2)))),0) -> 0.0055981649 | I28: =IF(I9>=Inputs!$F$69,Inputs!$F$71/(1+EXP(-$C$26*(I9-(Inputs!$F$69+Inputs!$F$72/2)))),0) -> 0.011391579 | J28: =IF(J9>=Inputs!$F$69,Inputs!$F$71/(1+EXP(-$C$26*(J9-(Inputs!$F$69+Inputs!$F$72/2)))),0) -> 0.018608421 | K28: =IF(K9>=Inputs!$F$69,Inputs!$F$71/(1+EXP(-$C$26*(K9-(Inputs!$F$69+Inputs!$F$72/2)))),0) -> 0.024401835 | ... R28: =IF(R9>=Inputs!$F$69,Inputs!$F$71/(1+EXP(-$C$26*(R9-(Inputs!$F$69+Inputs!$F$72/2)))),0) -> 0.029992857
A29: MNO partner subscriber base (mm) | B29: mm | D29: =Inputs!$D$30*(1+Inputs!$D$51)^MAX(0,D$6-2026) -> 3000 | E29: =Inputs!$D$30*(1+Inputs!$D$51)^MAX(0,E$6-2026) -> 3030 | F29: =Inputs!$D$30*(1+Inputs!$D$51)^MAX(0,F$6-2026) -> 3060.3 | G29: =Inputs!$D$30*(1+Inputs!$D$51)^MAX(0,G$6-2026) -> 3090.903 | H29: =Inputs!$D$30*(1+Inputs!$D$51)^MAX(0,H$6-2026) -> 3121.812 | I29: =Inputs!$D$30*(1+Inputs!$D$51)^MAX(0,I$6-2026) -> 3153.0302 | J29: =Inputs!$D$30*(1+Inputs!$D$51)^MAX(0,J$6-2026) -> 3184.5605 | K29: =Inputs!$D$30*(1+Inputs!$D$51)^MAX(0,K$6-2026) -> 3216.4061 | ... R29: =Inputs!$D$30*(1+Inputs!$D$51)^MAX(0,R$6-2026) -> 3448.4226
A30: Tier-1 paying users (mm, period avg) | B30: mm | D30: =D29*Inputs!$D$31*D24*D27 -> 0 | E30: =E29*Inputs!$D$31*E24*E27 -> 3.3733185 | F30: =F29*Inputs!$D$31*F24*F27 -> 14.27672 | G30: =G29*Inputs!$D$31*G24*G27 -> 29.341888 | H30: =H29*Inputs!$D$31*H24*H27 -> 48.409994 | I30: =I29*Inputs!$D$31*I24*I27 -> 64.116435 | J30: =J29*Inputs!$D$31*J24*J27 -> 73.311093 | K30: =K29*Inputs!$D$31*K24*K27 -> 77.900233 | ... R30: =R29*Inputs!$D$31*R24*R27 -> 86.207683
A31: Tier-2 paying users (mm, period avg) | B31: mm | D31: =D29*(1-Inputs!$D$31)*D25*D28 -> 0 | E31: =E29*(1-Inputs!$D$31)*E25*E28 -> 0 | F31: =F29*(1-Inputs!$D$31)*F25*F28 -> 0 | G31: =G29*(1-Inputs!$D$31)*G25*G28 -> 5.5057956 | H31: =H29*(1-Inputs!$D$31)*H25*H28 -> 13.107314 | I31: =I29*(1-Inputs!$D$31)*I25*I28 -> 26.938494 | J31: =J29*(1-Inputs!$D$31)*J25*J28 -> 44.444731 | K31: =K29*(1-Inputs!$D$31)*K25*K28 -> 58.864658 | ... R31: =R29*(1-Inputs!$D$31)*R25*R28 -> 77.571035
A32: ARPU index (2027 = 1.00) | B32: x | D32: =(1+Inputs!$F$75)^MIN(MAX(0,D$6-2027),Inputs!$D$49-2027)*(1+Inputs!$D$50)^MAX(0,D$6-Inputs!$D$49) -> 1 | E32: =(1+Inputs!$F$75)^MIN(MAX(0,E$6-2027),Inputs!$D$49-2027)*(1+Inputs!$D$50)^MAX(0,E$6-Inputs!$D$49) -> 1 | F32: =(1+Inputs!$F$75)^MIN(MAX(0,F$6-2027),Inputs!$D$49-2027)*(1+Inputs!$D$50)^MAX(0,F$6-Inputs!$D$49) -> 0.99 | G32: =(1+Inputs!$F$75)^MIN(MAX(0,G$6-2027),Inputs!$D$49-2027)*(1+Inputs!$D$50)^MAX(0,G$6-Inputs!$D$49) -> 0.9801 | H32: =(1+Inputs!$F$75)^MIN(MAX(0,H$6-2027),Inputs!$D$49-2027)*(1+Inputs!$D$50)^MAX(0,H$6-Inputs!$D$49) -> 0.970299 | I32: =(1+Inputs!$F$75)^MIN(MAX(0,I$6-2027),Inputs!$D$49-2027)*(1+Inputs!$D$50)^MAX(0,I$6-Inputs!$D$49) -> 0.96059601 | J32: =(1+Inputs!$F$75)^MIN(MAX(0,J$6-2027),Inputs!$D$49-2027)*(1+Inputs!$D$50)^MAX(0,J$6-Inputs!$D$49) -> 0.95099005 | K32: =(1+Inputs!$F$75)^MIN(MAX(0,K$6-2027),Inputs!$D$49-2027)*(1+Inputs!$D$50)^MAX(0,K$6-Inputs!$D$49) -> 0.9652549 | ... R32: =(1+Inputs!$F$75)^MIN(MAX(0,R$6-2027),Inputs!$D$49-2027)*(1+Inputs!$D$50)^MAX(0,R$6-Inputs!$D$49) -> 1.0712832
A33: Tier-1 service revenue | B33: $mm | D33: =D30*Inputs!$F$73*D32*12*D7 -> 0 | E33: =E30*Inputs!$F$73*E32*12*E7 -> 202.39911 | F33: =F30*Inputs!$F$73*F32*12*F7 -> 848.03717 | G33: =G30*Inputs!$F$73*G32*12*G7 -> 1725.4791 | H33: =H30*Inputs!$F$73*H32*12*H7 -> 2818.3301 | I33: =I30*Inputs!$F$73*I32*12*I7 -> 3695.3995 | J33: =J30*Inputs!$F$73*J32*12*J7 -> 4183.0872 | K33: =K30*Inputs!$F$73*K32*12*K7 -> 4511.6149 | ... R33: =R30*Inputs!$F$73*R32*12*R7 -> 5541.1707
A34: Tier-2 service revenue | B34: $mm | D34: =D31*Inputs!$F$74*D32*12*D7 -> 0 | E34: =E31*Inputs!$F$74*E32*12*E7 -> 0 | F34: =F31*Inputs!$F$74*F32*12*F7 -> 0 | G34: =G31*Inputs!$F$74*G32*12*G7 -> 48.566072 | H34: =H31*Inputs!$F$74*H32*12*H7 -> 114.46212 | I34: =I31*Inputs!$F$74*I32*12*I7 -> 232.89309 | J34: =J31*Inputs!$F$74*J32*12*J7 -> 380.39848 | K34: =K31*Inputs!$F$74*K32*12*K7 -> 511.37459 | ... R34: =R31*Inputs!$F$74*R32*12*R7 -> 747.90495
A35: Government revenue | B35: $mm | D35: =IF(D$6=2026,Inputs!$F$78,IF(D$6=2027,Inputs!$F$79,IF(D$6=2028,Inputs!$F$80,IF(D$6=2029,Inputs!$F$81,Inputs!$F$82*(1+Inputs!$F$83)^(D$6-2030))))) -> 45 | E35: =IF(E$6=2026,Inputs!$F$78,IF(E$6=2027,Inputs!$F$79,IF(E$6=2028,Inputs!$F$80,IF(E$6=2029,Inputs!$F$81,Inputs!$F$82*(1+Inputs!$F$83)^(E$6-2030))))) -> 100 | F35: =IF(F$6=2026,Inputs!$F$78,IF(F$6=2027,Inputs!$F$79,IF(F$6=2028,Inputs!$F$80,IF(F$6=2029,Inputs!$F$81,Inputs!$F$82*(1+Inputs!$F$83)^(F$6-2030))))) -> 160 | G35: =IF(G$6=2026,Inputs!$F$78,IF(G$6=2027,Inputs!$F$79,IF(G$6=2028,Inputs!$F$80,IF(G$6=2029,Inputs!$F$81,Inputs!$F$82*(1+Inputs!$F$83)^(G$6-2030))))) -> 220 | H35: =IF(H$6=2026,Inputs!$F$78,IF(H$6=2027,Inputs!$F$79,IF(H$6=2028,Inputs!$F$80,IF(H$6=2029,Inputs!$F$81,Inputs!$F$82*(1+Inputs!$F$83)^(H$6-2030))))) -> 280 | I35: =IF(I$6=2026,Inputs!$F$78,IF(I$6=2027,Inputs!$F$79,IF(I$6=2028,Inputs!$F$80,IF(I$6=2029,Inputs!$F$81,Inputs!$F$82*(1+Inputs!$F$83)^(I$6-2030))))) -> 296.8 | J35: =IF(J$6=2026,Inputs!$F$78,IF(J$6=2027,Inputs!$F$79,IF(J$6=2028,Inputs!$F$80,IF(J$6=2029,Inputs!$F$81,Inputs!$F$82*(1+Inputs!$F$83)^(J$6-2030))))) -> 314.608 | K35: =IF(K$6=2026,Inputs!$F$78,IF(K$6=2027,Inputs!$F$79,IF(K$6=2028,Inputs!$F$80,IF(K$6=2029,Inputs!$F$81,Inputs!$F$82*(1+Inputs!$F$83)^(K$6-2030))))) -> 333.48448 | ... R35: =IF(R$6=2026,Inputs!$F$78,IF(R$6=2027,Inputs!$F$79,IF(R$6=2028,Inputs!$F$80,IF(R$6=2029,Inputs!$F$81,Inputs!$F$82*(1+Inputs!$F$83)^(R$6-2030))))) -> 501.43736
A36: Gateway / product revenue | B36: $mm | D36: =IF(D$6=2026,Inputs!$F$84,IF(D$6=2027,Inputs!$F$85,IF(D$6=2028,Inputs!$F$86,Inputs!$F$87))) -> 83.7 | E36: =IF(E$6=2026,Inputs!$F$84,IF(E$6=2027,Inputs!$F$85,IF(E$6=2028,Inputs!$F$86,Inputs!$F$87))) -> 120 | F36: =IF(F$6=2026,Inputs!$F$84,IF(F$6=2027,Inputs!$F$85,IF(F$6=2028,Inputs!$F$86,Inputs!$F$87))) -> 80 | G36: =IF(G$6=2026,Inputs!$F$84,IF(G$6=2027,Inputs!$F$85,IF(G$6=2028,Inputs!$F$86,Inputs!$F$87))) -> 40 | H36: =IF(H$6=2026,Inputs!$F$84,IF(H$6=2027,Inputs!$F$85,IF(H$6=2028,Inputs!$F$86,Inputs!$F$87))) -> 40 | I36: =IF(I$6=2026,Inputs!$F$84,IF(I$6=2027,Inputs!$F$85,IF(I$6=2028,Inputs!$F$86,Inputs!$F$87))) -> 40 | J36: =IF(J$6=2026,Inputs!$F$84,IF(J$6=2027,Inputs!$F$85,IF(J$6=2028,Inputs!$F$86,Inputs!$F$87))) -> 40 | K36: =IF(K$6=2026,Inputs!$F$84,IF(K$6=2027,Inputs!$F$85,IF(K$6=2028,Inputs!$F$86,Inputs!$F$87))) -> 40 | ... R36: =IF(R$6=2026,Inputs!$F$84,IF(R$6=2027,Inputs!$F$85,IF(R$6=2028,Inputs!$F$86,Inputs!$F$87))) -> 40
A37: Total revenue | B37: $mm | D37: =SUM(D33:D36) -> 128.7 | E37: =SUM(E33:E36) -> 422.39911 | F37: =SUM(F33:F36) -> 1088.0372 | G37: =SUM(G33:G36) -> 2034.0451 | H37: =SUM(H33:H36) -> 3252.7922 | I37: =SUM(I33:I36) -> 4265.0926 | J37: =SUM(J33:J36) -> 4918.0937 | K37: =SUM(K33:K36) -> 5396.474 | ... R37: =SUM(R33:R36) -> 6830.513 | S37: =R37*(1+Inputs!$D$20) -> 7001.2759
A38: Revenue growth (annualised) | B38: % | D38: =IF(Inputs!$D$36=0,0,(D37/D7)/(Inputs!$D$36/0.5)-1) -> 1.7824019 | E38: =IF(D37=0,0,(E37/E7)/(D37/D7)-1) -> 0.64102219 | F38: =IF(E37=0,0,(F37/F7)/(E37/E7)-1) -> 1.575851 | G38: =IF(F37=0,0,(G37/G7)/(F37/F7)-1) -> 0.86946291 | H38: =IF(G37=0,0,(H37/H7)/(G37/G7)-1) -> 0.59917407 | I38: =IF(H37=0,0,(I37/I7)/(H37/H7)-1) -> 0.31120965 | J38: =IF(I37=0,0,(J37/J7)/(I37/I7)-1) -> 0.15310361 | K38: =IF(J37=0,0,(K37/K7)/(J37/J7)-1) -> 0.097269462 | L38: =IF(K37=0,0,(L37/L7)/(K37/K7)-1) -> 0.057007988 | ... R38: =IF(Q37=0,0,(R37/R7)/(Q37/Q7)-1) -> 0.027569965
A39: Paying users per satellite in orbit (mm) | B39: mm | D39: =IF(D17=0,0,(D30+D31)/D17) -> 0 | E39: =IF(E17=0,0,(E30+E31)/E17) -> 0.0793722 | F39: =IF(F17=0,0,(F30+F31)/F17) -> 0.19035627 | G39: =IF(G17=0,0,(G30+G31)/G17) -> 0.38719648 | H39: =IF(H17=0,0,(H30+H31)/H17) -> 0.68352564 | I39: =IF(I17=0,0,(I30+I31)/I17) -> 1.0117214 | J39: =IF(J17=0,0,(J30+J31)/J17) -> 1.308398 | K39: =IF(K17=0,0,(K30+K31)/K17) -> 1.5196099 | ... R39: =IF(R17=0,0,(R30+R31)/R17) -> 1.8197635
A40: OPERATING COSTS & EBITDA
A41: Cost of revenue (gateway + government) | B41: $mm | D41: =D36*(1-Inputs!$D$52)+D35*Inputs!$D$53 -> 95.265 | E41: =E36*(1-Inputs!$D$52)+E35*Inputs!$D$53 -> 149 | F41: =F36*(1-Inputs!$D$52)+F35*Inputs!$D$53 -> 132 | G41: =G36*(1-Inputs!$D$52)+G35*Inputs!$D$53 -> 115 | H41: =H36*(1-Inputs!$D$52)+H35*Inputs!$D$53 -> 136 | I41: =I36*(1-Inputs!$D$52)+I35*Inputs!$D$53 -> 141.88 | J41: =J36*(1-Inputs!$D$52)+J35*Inputs!$D$53 -> 148.1128 | K41: =K36*(1-Inputs!$D$52)+K35*Inputs!$D$53 -> 154.71957 | ... R41: =R36*(1-Inputs!$D$52)+R35*Inputs!$D$53 -> 213.50307
A42: Service variable cost | B42: $mm | D42: =(D33+D34)*Inputs!$F$76 -> 0 | E42: =(E33+E34)*Inputs!$F$76 -> 24.287893 | F42: =(F33+F34)*Inputs!$F$76 -> 101.76446 | G42: =(G33+G34)*Inputs!$F$76 -> 212.88542 | H42: =(H33+H34)*Inputs!$F$76 -> 351.93507 | I42: =(I33+I34)*Inputs!$F$76 -> 471.39511 | J42: =(J33+J34)*Inputs!$F$76 -> 547.61828 | K42: =(K33+K34)*Inputs!$F$76 -> 602.75874 | ... R42: =(R33+R34)*Inputs!$F$76 -> 754.68908
A43: Ligado revenue share | B43: $mm | D43: =D33*Inputs!$D$47 -> 0 | E43: =E33*Inputs!$D$47 -> 6.0719733 | F43: =F33*Inputs!$D$47 -> 25.441115 | G43: =G33*Inputs!$D$47 -> 51.764372 | H43: =H33*Inputs!$D$47 -> 84.549904 | I43: =I33*Inputs!$D$47 -> 110.86198 | J43: =J33*Inputs!$D$47 -> 125.49262 | K43: =K33*Inputs!$D$47 -> 135.34845 | ... R43: =R33*Inputs!$D$47 -> 166.23512
A44: Spectrum usage payments | B44: $mm | D44: =IF(D$6>=Inputs!$D$45,Inputs!$D$46*D7,0) -> 0 | E44: =IF(E$6>=Inputs!$D$45,Inputs!$D$46*E7,0) -> 100 | F44: =IF(F$6>=Inputs!$D$45,Inputs!$D$46*F7,0) -> 100 | G44: =IF(G$6>=Inputs!$D$45,Inputs!$D$46*G7,0) -> 100 | H44: =IF(H$6>=Inputs!$D$45,Inputs!$D$46*H7,0) -> 100 | I44: =IF(I$6>=Inputs!$D$45,Inputs!$D$46*I7,0) -> 100 | J44: =IF(J$6>=Inputs!$D$45,Inputs!$D$46*J7,0) -> 100 | K44: =IF(K$6>=Inputs!$D$45,Inputs!$D$46*K7,0) -> 100 | ... R44: =IF(R$6>=Inputs!$D$45,Inputs!$D$46*R7,0) -> 100
A45: Fixed adj. opex (ex-COGS, ex-SBC) | B45: $mm | D45: =Inputs!$F$89 -> 210 | E45: =IF(E$6=2027,Inputs!$F$90,D45*(1+IF(E$6=2028,Inputs!$F$91,IF(E$6=2029,Inputs!$F$92,IF(E$6=2030,Inputs!$F$93,Inputs!$F$94))))) -> 460 | F45: =IF(F$6=2027,Inputs!$F$90,E45*(1+IF(F$6=2028,Inputs!$F$91,IF(F$6=2029,Inputs!$F$92,IF(F$6=2030,Inputs!$F$93,Inputs!$F$94))))) -> 506 | G45: =IF(G$6=2027,Inputs!$F$90,F45*(1+IF(G$6=2028,Inputs!$F$91,IF(G$6=2029,Inputs!$F$92,IF(G$6=2030,Inputs!$F$93,Inputs!$F$94))))) -> 546.48 | H45: =IF(H$6=2027,Inputs!$F$90,G45*(1+IF(H$6=2028,Inputs!$F$91,IF(H$6=2029,Inputs!$F$92,IF(H$6=2030,Inputs!$F$93,Inputs!$F$94))))) -> 579.2688 | I45: =IF(I$6=2027,Inputs!$F$90,H45*(1+IF(I$6=2028,Inputs!$F$91,IF(I$6=2029,Inputs!$F$92,IF(I$6=2030,Inputs!$F$93,Inputs!$F$94))))) -> 599.54321 | J45: =IF(J$6=2027,Inputs!$F$90,I45*(1+IF(J$6=2028,Inputs!$F$91,IF(J$6=2029,Inputs!$F$92,IF(J$6=2030,Inputs!$F$93,Inputs!$F$94))))) -> 620.52722 | K45: =IF(K$6=2027,Inputs!$F$90,J45*(1+IF(K$6=2028,Inputs!$F$91,IF(K$6=2029,Inputs!$F$92,IF(K$6=2030,Inputs!$F$93,Inputs!$F$94))))) -> 642.24567 | L45: =IF(L$6=2027,Inputs!$F$90,K45*(1+IF(L$6=2028,Inputs!$F$91,IF(L$6=2029,Inputs!$F$92,IF(L$6=2030,Inputs!$F$93,Inputs!$F$94))))) -> 664.72427 | ... R45: =IF(R$6=2027,Inputs!$F$90,Q45*(1+IF(R$6=2028,Inputs!$F$91,IF(R$6=2029,Inputs!$F$92,IF(R$6=2030,Inputs!$F$93,Inputs!$F$94))))) -> 817.11585
A46: Network, ground & insurance opex | B46: $mm | D46: =D17*Inputs!$D$48*D7 -> 14.5 | E46: =E17*Inputs!$D$48*E7 -> 85 | F46: =F17*Inputs!$D$48*F7 -> 150 | G46: =G17*Inputs!$D$48*G7 -> 180 | H46: =H17*Inputs!$D$48*H7 -> 180 | I46: =I17*Inputs!$D$48*I7 -> 180 | J46: =J17*Inputs!$D$48*J7 -> 180 | K46: =K17*Inputs!$D$48*K7 -> 180 | ... R46: =R17*Inputs!$D$48*R7 -> 180
A47: Stock-based compensation (treated as cost) | B47: $mm | D47: =Inputs!$F$95 -> 120 | E47: =MAX(Inputs!$F$96*(1-Inputs!$F$97)^MAX(0,E$6-2027),Inputs!$F$98*E37) -> 230 | F47: =MAX(Inputs!$F$96*(1-Inputs!$F$97)^MAX(0,F$6-2027),Inputs!$F$98*F37) -> 207 | G47: =MAX(Inputs!$F$96*(1-Inputs!$F$97)^MAX(0,G$6-2027),Inputs!$F$98*G37) -> 186.3 | H47: =MAX(Inputs!$F$96*(1-Inputs!$F$97)^MAX(0,H$6-2027),Inputs!$F$98*H37) -> 167.67 | I47: =MAX(Inputs!$F$96*(1-Inputs!$F$97)^MAX(0,I$6-2027),Inputs!$F$98*I37) -> 150.903 | J47: =MAX(Inputs!$F$96*(1-Inputs!$F$97)^MAX(0,J$6-2027),Inputs!$F$98*J37) -> 172.13328 | K47: =MAX(Inputs!$F$96*(1-Inputs!$F$97)^MAX(0,K$6-2027),Inputs!$F$98*K37) -> 188.87659 | L47: =MAX(Inputs!$F$96*(1-Inputs!$F$97)^MAX(0,L$6-2027),Inputs!$F$98*L37) -> 199.64406 | ... R47: =MAX(Inputs!$F$96*(1-Inputs!$F$97)^MAX(0,R$6-2027),Inputs!$F$98*R37) -> 239.06796
A48: Total operating costs | B48: $mm | D48: =SUM(D41:D47) -> 439.765 | E48: =SUM(E41:E47) -> 1054.3599 | F48: =SUM(F41:F47) -> 1222.2056 | G48: =SUM(G41:G47) -> 1392.4298 | H48: =SUM(H41:H47) -> 1599.4238 | I48: =SUM(I41:I47) -> 1754.5833 | J48: =SUM(J41:J47) -> 1893.8842 | K48: =SUM(K41:K47) -> 2003.949 | ... R48: =SUM(R41:R47) -> 2470.6111
A49: EBITDA (after SBC) | B49: $mm | D49: =D37-D48 -> -311.065 | E49: =E37-E48 -> -631.96076 | F49: =F37-F48 -> -134.1684 | G49: =G37-G48 -> 641.61535 | H49: =H37-H48 -> 1653.3685 | I49: =I37-I48 -> 2510.5093 | J49: =J37-J48 -> 3024.2095 | K49: =K37-K48 -> 3392.525 | ... R49: =R37-R48 -> 4359.902 | S49: =R49*(1+Inputs!$D$20) -> 4468.8995
A50: EBITDA margin | B50: % | D50: =IF(D37=0,0,D49/D37) -> -2.4169775 | E50: =IF(E37=0,0,E49/E37) -> -1.4961224 | F50: =IF(F37=0,0,F49/F37) -> -0.12331234 | G50: =IF(G37=0,0,G49/G37) -> 0.31543811 | H50: =IF(H37=0,0,H49/H37) -> 0.50829206 | I50: =IF(I37=0,0,I49/I37) -> 0.58861777 | J50: =IF(J37=0,0,J49/J37) -> 0.61491498 | K50: =IF(K37=0,0,K49/K37) -> 0.62865586 | ... R50: =IF(R37=0,0,R49/R37) -> 0.63829787
A51: CAPEX & OTHER INVESTING ITEMS
A52: Other capex (ground, facilities) | B52: $mm | D52: =IF(D$6=2026,Inputs!$F$100,IF(D$6=2027,Inputs!$F$101,IF(D$6=2028,Inputs!$F$102,MAX(Inputs!$F$104,Inputs!$F$103*D37)))) -> 150 | E52: =IF(E$6=2026,Inputs!$F$100,IF(E$6=2027,Inputs!$F$101,IF(E$6=2028,Inputs!$F$102,MAX(Inputs!$F$104,Inputs!$F$103*E37)))) -> 200 | F52: =IF(F$6=2026,Inputs!$F$100,IF(F$6=2027,Inputs!$F$101,IF(F$6=2028,Inputs!$F$102,MAX(Inputs!$F$104,Inputs!$F$103*F37)))) -> 150 | G52: =IF(G$6=2026,Inputs!$F$100,IF(G$6=2027,Inputs!$F$101,IF(G$6=2028,Inputs!$F$102,MAX(Inputs!$F$104,Inputs!$F$103*G37)))) -> 80 | H52: =IF(H$6=2026,Inputs!$F$100,IF(H$6=2027,Inputs!$F$101,IF(H$6=2028,Inputs!$F$102,MAX(Inputs!$F$104,Inputs!$F$103*H37)))) -> 97.583767 | I52: =IF(I$6=2026,Inputs!$F$100,IF(I$6=2027,Inputs!$F$101,IF(I$6=2028,Inputs!$F$102,MAX(Inputs!$F$104,Inputs!$F$103*I37)))) -> 127.95278 | J52: =IF(J$6=2026,Inputs!$F$100,IF(J$6=2027,Inputs!$F$101,IF(J$6=2028,Inputs!$F$102,MAX(Inputs!$F$104,Inputs!$F$103*J37)))) -> 147.54281 | K52: =IF(K$6=2026,Inputs!$F$100,IF(K$6=2027,Inputs!$F$101,IF(K$6=2028,Inputs!$F$102,MAX(Inputs!$F$104,Inputs!$F$103*K37)))) -> 161.89422 | ... R52: =IF(R$6=2026,Inputs!$F$100,IF(R$6=2027,Inputs!$F$101,IF(R$6=2028,Inputs!$F$102,MAX(Inputs!$F$104,Inputs!$F$103*R37)))) -> 204.91539
A53: Ligado spectrum closing payment | B53: $mm | D53: =IF(D$6=Inputs!$D$45,Inputs!$D$44,0) -> 0 | E53: =IF(E$6=Inputs!$D$45,Inputs!$D$44,0) -> 550 | F53: =IF(F$6=Inputs!$D$45,Inputs!$D$44,0) -> 0 | G53: =IF(G$6=Inputs!$D$45,Inputs!$D$44,0) -> 0 | H53: =IF(H$6=Inputs!$D$45,Inputs!$D$44,0) -> 0 | I53: =IF(I$6=Inputs!$D$45,Inputs!$D$44,0) -> 0 | J53: =IF(J$6=Inputs!$D$45,Inputs!$D$44,0) -> 0 | K53: =IF(K$6=Inputs!$D$45,Inputs!$D$44,0) -> 0 | ... R53: =IF(R$6=Inputs!$D$45,Inputs!$D$44,0) -> 0
A54: J-LEO non-dilutive capital (inflow) | B54: $mm | D54: =IF(D$6=2028,Inputs!$F$105,0) -> 0 | E54: =IF(E$6=2028,Inputs!$F$105,0) -> 0 | F54: =IF(F$6=2028,Inputs!$F$105,0) -> 0 | G54: =IF(G$6=2028,Inputs!$F$105,0) -> 0 | H54: =IF(H$6=2028,Inputs!$F$105,0) -> 0 | I54: =IF(I$6=2028,Inputs!$F$105,0) -> 0 | J54: =IF(J$6=2028,Inputs!$F$105,0) -> 0 | K54: =IF(K$6=2028,Inputs!$F$105,0) -> 0 | ... R54: =IF(R$6=2028,Inputs!$F$105,0) -> 0
A55: CASH TAXES (NOL + depreciation)
A56: Tax-basis capex placed in service | B56: $mm | D56: =D19+D52 -> 636.31579 | E56: =E19+E52 -> 1010.5263 | F56: =F19+F52 -> 844.73684 | G56: =G19+G52 -> 80 | H56: =H19+H52 -> 97.583767 | I56: =I19+I52 -> 127.95278 | J56: =J19+J52 -> 147.54281 | K56: =K19+K52 -> 801.0989 | ... R56: =R19+R52 -> 939.16064
A57: Tax depreciation | B57: $mm | D57: =IF(Inputs!$D$25=1,D56,SUMIFS($D$56:D56,$D$6:D6,">"&(D$6-ROUND(Inputs!$D$26,0)))/ROUND(Inputs!$D$26,0)*D7) -> 636.31579 | E57: =IF(Inputs!$D$25=1,E56,SUMIFS($D$56:E56,$D$6:E6,">"&(E$6-ROUND(Inputs!$D$26,0)))/ROUND(Inputs!$D$26,0)*E7) -> 1010.5263 | F57: =IF(Inputs!$D$25=1,F56,SUMIFS($D$56:F56,$D$6:F6,">"&(F$6-ROUND(Inputs!$D$26,0)))/ROUND(Inputs!$D$26,0)*F7) -> 844.73684 | G57: =IF(Inputs!$D$25=1,G56,SUMIFS($D$56:G56,$D$6:G6,">"&(G$6-ROUND(Inputs!$D$26,0)))/ROUND(Inputs!$D$26,0)*G7) -> 80 | H57: =IF(Inputs!$D$25=1,H56,SUMIFS($D$56:H56,$D$6:H6,">"&(H$6-ROUND(Inputs!$D$26,0)))/ROUND(Inputs!$D$26,0)*H7) -> 97.583767 | I57: =IF(Inputs!$D$25=1,I56,SUMIFS($D$56:I56,$D$6:I6,">"&(I$6-ROUND(Inputs!$D$26,0)))/ROUND(Inputs!$D$26,0)*I7) -> 127.95278 | J57: =IF(Inputs!$D$25=1,J56,SUMIFS($D$56:J56,$D$6:J6,">"&(J$6-ROUND(Inputs!$D$26,0)))/ROUND(Inputs!$D$26,0)*J7) -> 147.54281 | K57: =IF(Inputs!$D$25=1,K56,SUMIFS($D$56:K56,$D$6:K6,">"&(K$6-ROUND(Inputs!$D$26,0)))/ROUND(Inputs!$D$26,0)*K7) -> 801.0989 | ... R57: =IF(Inputs!$D$25=1,R56,SUMIFS($D$56:R56,$D$6:R6,">"&(R$6-ROUND(Inputs!$D$26,0)))/ROUND(Inputs!$D$26,0)*R7) -> 939.16064
A58: Spectrum amortisation (15-yr, s.197) | B58: $mm | D58: =IF(AND(D$6>=Inputs!$D$45,D$6<Inputs!$D$45+15),Inputs!$D$44/15*D7,0) -> 0 | E58: =IF(AND(E$6>=Inputs!$D$45,E$6<Inputs!$D$45+15),Inputs!$D$44/15*E7,0) -> 36.666667 | F58: =IF(AND(F$6>=Inputs!$D$45,F$6<Inputs!$D$45+15),Inputs!$D$44/15*F7,0) -> 36.666667 | G58: =IF(AND(G$6>=Inputs!$D$45,G$6<Inputs!$D$45+15),Inputs!$D$44/15*G7,0) -> 36.666667 | H58: =IF(AND(H$6>=Inputs!$D$45,H$6<Inputs!$D$45+15),Inputs!$D$44/15*H7,0) -> 36.666667 | I58: =IF(AND(I$6>=Inputs!$D$45,I$6<Inputs!$D$45+15),Inputs!$D$44/15*I7,0) -> 36.666667 | J58: =IF(AND(J$6>=Inputs!$D$45,J$6<Inputs!$D$45+15),Inputs!$D$44/15*J7,0) -> 36.666667 | K58: =IF(AND(K$6>=Inputs!$D$45,K$6<Inputs!$D$45+15),Inputs!$D$44/15*K7,0) -> 36.666667 | ... R58: =IF(AND(R$6>=Inputs!$D$45,R$6<Inputs!$D$45+15),Inputs!$D$44/15*R7,0) -> 36.666667
A59: Taxable income | B59: $mm | D59: =D49-D57-D58 -> -947.38079 | E59: =E49-E57-E58 -> -1679.1537 | F59: =F49-F57-F58 -> -1015.5719 | G59: =G49-G57-G58 -> 524.94868 | H59: =H49-H57-H58 -> 1519.118 | I59: =I49-I57-I58 -> 2345.8898 | J59: =J49-J57-J58 -> 2840 | K59: =K49-K57-K58 -> 2554.7594 | ... R59: =R49-R57-R58 -> 3384.0746
A60: NOL pool - beginning | B60: $mm | D60: =Inputs!$D$23 -> 1000 | E60: =D62 -> 1947.3808 | F60: =E62 -> 3626.5345 | G60: =F62 -> 4642.1064 | H60: =G62 -> 4222.1475 | I60: =H62 -> 3006.8531 | J60: =I62 -> 1130.1412 | K60: =J62 -> 0 | L60: =K62 -> 0 | ... R60: =Q62 -> 0
A61: NOL utilised (80% cap) | B61: $mm | D61: =MIN(D60,MAX(0,D59)*Inputs!$D$24) -> 0 | E61: =MIN(E60,MAX(0,E59)*Inputs!$D$24) -> 0 | F61: =MIN(F60,MAX(0,F59)*Inputs!$D$24) -> 0 | G61: =MIN(G60,MAX(0,G59)*Inputs!$D$24) -> 419.95894 | H61: =MIN(H60,MAX(0,H59)*Inputs!$D$24) -> 1215.2944 | I61: =MIN(I60,MAX(0,I59)*Inputs!$D$24) -> 1876.7119 | J61: =MIN(J60,MAX(0,J59)*Inputs!$D$24) -> 1130.1412 | K61: =MIN(K60,MAX(0,K59)*Inputs!$D$24) -> 0 | ... R61: =MIN(R60,MAX(0,R59)*Inputs!$D$24) -> 0
A62: NOL pool - ending | B62: $mm | D62: =D60-D61+MAX(0,-D59) -> 1947.3808 | E62: =E60-E61+MAX(0,-E59) -> 3626.5345 | F62: =F60-F61+MAX(0,-F59) -> 4642.1064 | G62: =G60-G61+MAX(0,-G59) -> 4222.1475 | H62: =H60-H61+MAX(0,-H59) -> 3006.8531 | I62: =I60-I61+MAX(0,-I59) -> 1130.1412 | J62: =J60-J61+MAX(0,-J59) -> 0 | K62: =K60-K61+MAX(0,-K59) -> 0 | ... R62: =R60-R61+MAX(0,-R59) -> 0
A63: Cash taxes | B63: $mm | D63: =Inputs!$D$22*MAX(0,D59-D61) -> 0 | E63: =Inputs!$D$22*MAX(0,E59-E61) -> 0 | F63: =Inputs!$D$22*MAX(0,F59-F61) -> 0 | G63: =Inputs!$D$22*MAX(0,G59-G61) -> 26.247434 | H63: =Inputs!$D$22*MAX(0,H59-H61) -> 75.955902 | I63: =Inputs!$D$22*MAX(0,I59-I61) -> 117.29449 | J63: =Inputs!$D$22*MAX(0,J59-J61) -> 427.4647 | K63: =Inputs!$D$22*MAX(0,K59-K61) -> 638.68985 | ... R63: =Inputs!$D$22*MAX(0,R59-R61) -> 846.01866
A64: FREE CASH FLOW TO THE FIRM
A65: Annualised revenue | B65: $mm | D65: =D37/D7 -> 257.4 | E65: =E37/E7 -> 422.39911 | F65: =F37/F7 -> 1088.0372 | G65: =G37/G7 -> 2034.0451 | H65: =H37/H7 -> 3252.7922 | I65: =I37/I7 -> 4265.0926 | J65: =J37/J7 -> 4918.0937 | K65: =K37/K7 -> 5396.474 | ... R65: =R37/R7 -> 6830.513
A66: Increase in net working capital | B66: $mm | D66: =Inputs!$D$42*(D65-Inputs!$D$43) -> 8.2445 | E66: =Inputs!$D$42*(E65-D65) -> 8.2499556 | F66: =Inputs!$D$42*(F65-E65) -> 33.281903 | G66: =Inputs!$D$42*(G65-F65) -> 47.300398 | H66: =Inputs!$D$42*(H65-G65) -> 60.937355 | I66: =Inputs!$D$42*(I65-H65) -> 50.615017 | J66: =Inputs!$D$42*(J65-I65) -> 32.650054 | K66: =Inputs!$D$42*(K65-J65) -> 23.919016 | L66: =Inputs!$D$42*(L65-K65) -> 15.382106 | ... R66: =Inputs!$D$42*(R65-Q65) -> 9.1632207
A67: Contract-liability unwind (revenue already paid in cash) | B67: $mm | D67: =IF(AND(D$6>=Inputs!$D$40,D$6<Inputs!$D$40+Inputs!$D$41),Inputs!$D$39/Inputs!$D$41*D7,0) -> 0 | E67: =IF(AND(E$6>=Inputs!$D$40,E$6<Inputs!$D$40+Inputs!$D$41),Inputs!$D$39/Inputs!$D$41*E7,0) -> 53.3866 | F67: =IF(AND(F$6>=Inputs!$D$40,F$6<Inputs!$D$40+Inputs!$D$41),Inputs!$D$39/Inputs!$D$41*F7,0) -> 53.3866 | G67: =IF(AND(G$6>=Inputs!$D$40,G$6<Inputs!$D$40+Inputs!$D$41),Inputs!$D$39/Inputs!$D$41*G7,0) -> 53.3866 | H67: =IF(AND(H$6>=Inputs!$D$40,H$6<Inputs!$D$40+Inputs!$D$41),Inputs!$D$39/Inputs!$D$41*H7,0) -> 53.3866 | I67: =IF(AND(I$6>=Inputs!$D$40,I$6<Inputs!$D$40+Inputs!$D$41),Inputs!$D$39/Inputs!$D$41*I7,0) -> 53.3866 | J67: =IF(AND(J$6>=Inputs!$D$40,J$6<Inputs!$D$40+Inputs!$D$41),Inputs!$D$39/Inputs!$D$41*J7,0) -> 0 | K67: =IF(AND(K$6>=Inputs!$D$40,K$6<Inputs!$D$40+Inputs!$D$41),Inputs!$D$39/Inputs!$D$41*K7,0) -> 0 | ... R67: =IF(AND(R$6>=Inputs!$D$40,R$6<Inputs!$D$40+Inputs!$D$41),Inputs!$D$39/Inputs!$D$41*R7,0) -> 0
A68: FCFF | B68: $mm | D68: =D49-D63-D22-D52-D53+D54-D66-D67 -> -469.3095 | E68: =E49-E63-E22-E52-E53+E54-E66-E67 -> -1878.3969 | F68: =F49-F63-F22-F52-F53+F54-F66-F67 -> -1065.5737 | G68: =G49-G63-G22-G52-G53+G54-G66-G67 -> 434.68091 | H68: =H49-H63-H22-H52-H53+H54-H66-H67 -> 1365.5048 | I68: =I49-I63-I22-I52-I53+I54-I66-I67 -> 2161.2604 | J68: =J49-J63-J22-J52-J53+J54-J66-J67 -> 2416.5519 | K68: =K49-K63-K22-K52-K53+K54-K66-K67 -> 1928.8172 | ... R68: =R49-R63-R22-R52-R53+R54-R66-R67 -> 2565.5594
A69: Cumulative FCFF from 1-Jul-2026 | B69: $mm | D69: =SUM($D$68:D68) -> -469.3095 | E69: =SUM($D$68:E68) -> -2347.7064 | F69: =SUM($D$68:F68) -> -3413.2802 | G69: =SUM($D$68:G68) -> -2978.5993 | H69: =SUM($D$68:H68) -> -1613.0944 | I69: =SUM($D$68:I68) -> 548.16598 | J69: =SUM($D$68:J68) -> 2964.7179 | K69: =SUM($D$68:K68) -> 4893.5351 | ... R69: =SUM($D$68:R68) -> 23094.436
A70: DISCOUNTING (mid-period, from valuation date)
A71: WACC | B71: % | D71: =WACC!D$21 -> 0.10349672 | E71: =WACC!E$21 -> 0.10349672 | F71: =WACC!F$21 -> 0.10349672 | G71: =WACC!G$21 -> 0.10349672 | H71: =WACC!H$21 -> 0.10349672 | I71: =WACC!I$21 -> 0.099312374 | J71: =WACC!J$21 -> 0.095128031 | K71: =WACC!K$21 -> 0.090943687 | ... R71: =WACC!R$21 -> 0.082575
A72: Compounding factor to period end | B72: f | D72: =(1+D71)^(D8+D7-Inputs!$D$6) -> 1.0310009 | E72: =D72*(1+E71)^E7 -> 1.1377061 | F72: =E72*(1+F71)^F7 -> 1.2554549 | G72: =F72*(1+G71)^G7 -> 1.3853904 | H72: =G72*(1+H71)^H7 -> 1.5287737 | I72: =H72*(1+I71)^I7 -> 1.6805999 | J72: =I72*(1+J71)^J7 -> 1.840472 | K72: =J72*(1+K71)^K7 -> 2.0078513 | L72: =K72*(1+L71)^L7 -> 2.1820512 | ... R72: =Q72*(1+R71)^R7 -> 3.5124722
A73: Discount factor (mid-period) | B73: f | D73: =1/(1+D71)^(D9-Inputs!$D$6) -> 0.99410839 | E73: =1/(D72*(1+E71)^(E7/2)) -> 0.92332682 | F73: =1/(E72*(1+F71)^(F7/2)) -> 0.8367282 | G73: =1/(F72*(1+G71)^(G7/2)) -> 0.75825165 | H73: =1/(G72*(1+H71)^(H7/2)) -> 0.68713539 | I73: =1/(H72*(1+I71)^(I7/2)) -> 0.62387306 | J73: =1/(I72*(1+J71)^(J7/2)) -> 0.56859525 | K73: =1/(J72*(1+K71)^(K7/2)) -> 0.52019912 | L73: =1/(K72*(1+L71)^(L7/2)) -> 0.47775117 | ... R73: =1/(Q72*(1+R71)^(R7/2)) -> 0.29622117
A74: PV of FCFF | B74: $mm | D74: =D68*D73 -> -466.54451 | E74: =E68*E73 -> -1734.3743 | F74: =F68*F73 -> -891.59561 | G74: =G68*G73 -> 329.59752 | H74: =H68*H73 -> 938.2867 | I74: =I68*I73 -> 1348.3521 | J74: =J68*J73 -> 1374.0399 | K74: =K68*K73 -> 1003.369 | ... R74: =R68*R73 -> 759.97303
A75: TERMINAL VALUE & ENTERPRISE VALUE (col C)
A76: Terminal WACC | C76: =WACC!$C$16 -> 0.082575
A77: Terminal growth g | C77: =Inputs!$D$20 -> 0.025
A78: EBITDA 2041 (normalised) | C78: =R49*(1+C77) -> 4468.8995
A79: Normalised replacement satellite capex | C79: =Inputs!$F$63/ROUND(Inputs!$D$26,0)/(1-Inputs!$D$27)*R18*(1+C77) -> 387.05214
A80: Other capex 2041 | C80: =R52*(1+C77) -> 210.03828
A81: Normalised cash tax (tax dep = capex in steady state) | C81: =Inputs!$D$22*MAX(0,C78-C79-C80) -> 967.95227
A82: Increase in NWC 2041 | C82: =Inputs!$D$42*R37*C77 -> 8.5381413
A83: FCFF 2041 (normalised) | C83: =C78-C81-C79-C80-C82 -> 2895.3187
A84: Terminal value at end-2040 (Gordon, mid-year consistent) | C84: =C83*(1+C76)^0.5/(C76-C77) -> 52322.854
A85: PV of terminal value | C85: =C84/R72 -> 14896.304
A86: Sum of PV of explicit FCFF | C86: =SUM(D74:R74) -> 8700.6547
A87: ENTERPRISE VALUE | C87: =C86+C85 -> 23596.959
A88: Terminal value % of EV | C88: =IF(C87<=0,0,C85/C87) -> 0.63128067
A89: Implied terminal EV / EBITDA (2041) | C89: =IF(C78<=0,"n/m",C84/C78) -> 11.708219
A90: EQUITY BRIDGE & DILUTION (col C)
A91: + Cash & liquid assets (pro forma) | C91: =Capital_Structure!$D$20 -> 3755.203
A92: - Non-convertible debt | C92: =Capital_Structure!$B$26 -> 468.638
A93: - Convertible notes at face (all treated as debt first) | C93: =Capital_Structure!$B$35 -> 3703.514
A94: Equity value before conversions | C94: =C87+C91-C92-C93 -> 23180.01
A95: Basic economic shares (mm) | C95: =Capital_Structure!$B$9 -> 389.16749
A96: Instrument | B96: Trigger K $ | C96: Shares mm | D96: D $mm | E96: Value/sh if prefix converts | F96: Converts? (1/0) | H96: Order-independent: instrument converts iff value with all K <= its K converting exceeds its K (R-07).
A97: =Capital_Structure!A48 -> 2032 4.25% converts | B97: =Capital_Structure!B48 -> 26.99 | C97: =Capital_Structure!C48 -> 0.13019637 | D97: =Capital_Structure!D48 -> 3.514 | E97: =($C$94+SUMIF($B$97:$B$106,"<="&B97,$D$97:$D$106))/($C$95+SUMIF($B$97:$B$106,"<="&B97,$C$97:$C$106)) -> 57.398181 | F97: =IF(E97>B97,1,0) -> 1
A98: =Capital_Structure!A49 -> 2032 2.375% converts | B98: =Capital_Structure!B49 -> 72.07 | C98: =Capital_Structure!C49 -> 4.5095046 | D98: =Capital_Structure!D49 -> 325 | E98: =($C$94+SUMIF($B$97:$B$106,"<="&B98,$D$97:$D$106))/($C$95+SUMIF($B$97:$B$106,"<="&B98,$C$97:$C$106)) -> 57.560008 | F98: =IF(E98>B98,1,0) -> 0
A99: =Capital_Structure!A50 -> 2036 2.00% converts | B99: =Capital_Structure!B50 -> 96.3 | C99: =Capital_Structure!C50 -> 11.941848 | D99: =Capital_Structure!D50 -> 1150 | E99: =($C$94+SUMIF($B$97:$B$106,"<="&B99,$D$97:$D$106))/($C$95+SUMIF($B$97:$B$106,"<="&B99,$C$97:$C$106)) -> 58.659434 | F99: =IF(E99>B99,1,0) -> 0
A100: =Capital_Structure!A51 -> 2036 2.25% converts | B100: =Capital_Structure!B51 -> 116.3 | C100: =Capital_Structure!C51 -> 9.2433362 | D100: =Capital_Structure!D51 -> 1075 | E100: =($C$94+SUMIF($B$97:$B$106,"<="&B100,$D$97:$D$106))/($C$95+SUMIF($B$97:$B$106,"<="&B100,$C$97:$C$106)) -> 59.898388 | F100: =IF(E100>B100,1,0) -> 0
A101: =Capital_Structure!A52 -> 2034 1.625% converts (Jul-2026) | B101: =Capital_Structure!B52 -> 149.2 | C101: =Capital_Structure!C52 -> 14.452683 | D101: =Capital_Structure!D52 -> 2156.3403 | E101: =($C$94+SUMIF($B$97:$B$106,"<="&B101,$D$97:$D$106))/($C$95+SUMIF($B$97:$B$106,"<="&B101,$C$97:$C$106)) -> 62.802077 | F101: =IF(E101>B101,1,0) -> 0
A102: =Capital_Structure!A53 -> 2020 Plan stock options | B102: =Capital_Structure!B53 -> 9.2 | C102: =Capital_Structure!C53 -> 1.957612 | D102: =Capital_Structure!D53 -> 18.01003 | E102: =($C$94+SUMIF($B$97:$B$106,"<="&B102,$D$97:$D$106))/($C$95+SUMIF($B$97:$B$106,"<="&B102,$C$97:$C$106)) -> 57.412491 | F102: =IF(E102>B102,1,0) -> 1
...

Sheet Calc_Bear
A1: MODEL - BEAR SCENARIO
A2: Live formulas. Inputs from 'Inputs' column E (scenario) / D (global). $mm unless stated. Periods: 2026H2 stub + 2027-2040; col S = 2041 normalised.
A5: Period | D5: 2026H2 | E5: 2027 | F5: 2028 | G5: 2029 | H5: 2030 | I5: 2031 | J5: 2032 | K5: 2033 | L5: 2034 | M5: 2035 | N5: 2036 | O5: 2037 | P5: 2038 | Q5: 2039 | R5: 2040 | S5: 2041N
A6: Calendar year | B6: yr | D6: 2026 | E6: 2027 | F6: 2028 | G6: 2029 | H6: 2030 | I6: 2031 | J6: 2032 | K6: 2033 | L6: 2034 | M6: 2035 | N6: 2036 | O6: 2037 | P6: 2038 | Q6: 2039 | R6: 2040 | S6: 2041
A7: Period length (years) | B7: yrs | D7: 0.5 | E7: 1 | F7: 1 | G7: 1 | H7: 1 | I7: 1 | J7: 1 | K7: 1 | L7: 1 | M7: 1 | N7: 1 | O7: 1 | P7: 1 | Q7: 1 | R7: 1
A8: Period start (year fraction) | B8: yrs | D8: 2026.5 | E8: 2027 | F8: 2028 | G8: 2029 | H8: 2030 | I8: 2031 | J8: 2032 | K8: 2033 | L8: 2034 | M8: 2035 | N8: 2036 | O8: 2037 | P8: 2038 | Q8: 2039 | R8: 2040
A9: Cash-flow timing (mid-period) | B9: yrs | D9: =D8+D7/2 -> 2026.75 | E9: =E8+E7/2 -> 2027.5 | F9: =F8+F7/2 -> 2028.5 | G9: =G8+G7/2 -> 2029.5 | H9: =H8+H7/2 -> 2030.5 | I9: =I8+I7/2 -> 2031.5 | J9: =J8+J7/2 -> 2032.5 | K9: =K8+K7/2 -> 2033.5 | ... R9: =R8+R7/2 -> 2040.5
A10: CONSTELLATION (Block 2 satellites)
A11: Target fleet, end of period | B11: # | D11: =IF(D$6=2026,Inputs!$E$59,IF(D$6=2027,Inputs!$E$60,IF(D$6=2028,Inputs!$E$61,IF(D$6=2029,Inputs!$E$62,Inputs!$E$63)))) -> 20 | E11: =IF(E$6=2026,Inputs!$E$59,IF(E$6=2027,Inputs!$E$60,IF(E$6=2028,Inputs!$E$61,IF(E$6=2029,Inputs!$E$62,Inputs!$E$63)))) -> 45 | F11: =IF(F$6=2026,Inputs!$E$59,IF(F$6=2027,Inputs!$E$60,IF(F$6=2028,Inputs!$E$61,IF(F$6=2029,Inputs!$E$62,Inputs!$E$63)))) -> 60 | G11: =IF(G$6=2026,Inputs!$E$59,IF(G$6=2027,Inputs!$E$60,IF(G$6=2028,Inputs!$E$61,IF(G$6=2029,Inputs!$E$62,Inputs!$E$63)))) -> 75 | H11: =IF(H$6=2026,Inputs!$E$59,IF(H$6=2027,Inputs!$E$60,IF(H$6=2028,Inputs!$E$61,IF(H$6=2029,Inputs!$E$62,Inputs!$E$63)))) -> 90 | I11: =IF(I$6=2026,Inputs!$E$59,IF(I$6=2027,Inputs!$E$60,IF(I$6=2028,Inputs!$E$61,IF(I$6=2029,Inputs!$E$62,Inputs!$E$63)))) -> 90 | J11: =IF(J$6=2026,Inputs!$E$59,IF(J$6=2027,Inputs!$E$60,IF(J$6=2028,Inputs!$E$61,IF(J$6=2029,Inputs!$E$62,Inputs!$E$63)))) -> 90 | K11: =IF(K$6=2026,Inputs!$E$59,IF(K$6=2027,Inputs!$E$60,IF(K$6=2028,Inputs!$E$61,IF(K$6=2029,Inputs!$E$62,Inputs!$E$63)))) -> 90 | ... R11: =IF(R$6=2026,Inputs!$E$59,IF(R$6=2027,Inputs!$E$60,IF(R$6=2028,Inputs!$E$61,IF(R$6=2029,Inputs!$E$62,Inputs!$E$63)))) -> 90
A12: Beginning fleet | B12: # | D12: =Inputs!$D$28 -> 4 | E12: =D15 -> 20 | F12: =E15 -> 45 | G12: =F15 -> 60 | H12: =G15 -> 75 | I12: =H15 -> 90 | J12: =I15 -> 90 | K12: =J15 -> 90 | L12: =K15 -> 90 | ... R12: =Q15 -> 90
A13: Retirements (end of design life) | B13: # | D13: =0 -> 0 | E13: =IF(E$6-ROUND(Inputs!$D$26,0)=2026,$D$14+Inputs!$D$28,IF(E$6-ROUND(Inputs!$D$26,0)>=2027,INDEX($D$14:D14,1,E$6-ROUND(Inputs!$D$26,0)-2026+1),0)) -> 0 | F13: =IF(F$6-ROUND(Inputs!$D$26,0)=2026,$D$14+Inputs!$D$28,IF(F$6-ROUND(Inputs!$D$26,0)>=2027,INDEX($D$14:E14,1,F$6-ROUND(Inputs!$D$26,0)-2026+1),0)) -> 0 | G13: =IF(G$6-ROUND(Inputs!$D$26,0)=2026,$D$14+Inputs!$D$28,IF(G$6-ROUND(Inputs!$D$26,0)>=2027,INDEX($D$14:F14,1,G$6-ROUND(Inputs!$D$26,0)-2026+1),0)) -> 0 | H13: =IF(H$6-ROUND(Inputs!$D$26,0)=2026,$D$14+Inputs!$D$28,IF(H$6-ROUND(Inputs!$D$26,0)>=2027,INDEX($D$14:G14,1,H$6-ROUND(Inputs!$D$26,0)-2026+1),0)) -> 0 | I13: =IF(I$6-ROUND(Inputs!$D$26,0)=2026,$D$14+Inputs!$D$28,IF(I$6-ROUND(Inputs!$D$26,0)>=2027,INDEX($D$14:H14,1,I$6-ROUND(Inputs!$D$26,0)-2026+1),0)) -> 0 | J13: =IF(J$6-ROUND(Inputs!$D$26,0)=2026,$D$14+Inputs!$D$28,IF(J$6-ROUND(Inputs!$D$26,0)>=2027,INDEX($D$14:I14,1,J$6-ROUND(Inputs!$D$26,0)-2026+1),0)) -> 0 | K13: =IF(K$6-ROUND(Inputs!$D$26,0)=2026,$D$14+Inputs!$D$28,IF(K$6-ROUND(Inputs!$D$26,0)>=2027,INDEX($D$14:J14,1,K$6-ROUND(Inputs!$D$26,0)-2026+1),0)) -> 20 | L13: =IF(L$6-ROUND(Inputs!$D$26,0)=2026,$D$14+Inputs!$D$28,IF(L$6-ROUND(Inputs!$D$26,0)>=2027,INDEX($D$14:K14,1,L$6-ROUND(Inputs!$D$26,0)-2026+1),0)) -> 25 | ... R13: =IF(R$6-ROUND(Inputs!$D$26,0)=2026,$D$14+Inputs!$D$28,IF(R$6-ROUND(Inputs!$D$26,0)>=2027,INDEX($D$14:Q14,1,R$6-ROUND(Inputs!$D$26,0)-2026+1),0)) -> 20
A14: Successful launches (net adds + replacements) | B14: # | D14: =MAX(0,D11-D12+D13) -> 16 | E14: =MAX(0,E11-E12+E13) -> 25 | F14: =MAX(0,F11-F12+F13) -> 15 | G14: =MAX(0,G11-G12+G13) -> 15 | H14: =MAX(0,H11-H12+H13) -> 15 | I14: =MAX(0,I11-I12+I13) -> 0 | J14: =MAX(0,J11-J12+J13) -> 0 | K14: =MAX(0,K11-K12+K13) -> 20 | ... R14: =MAX(0,R11-R12+R13) -> 20
A15: Ending fleet | B15: # | D15: =D12-D13+D14 -> 20 | E15: =E12-E13+E14 -> 45 | F15: =F12-F13+F14 -> 60 | G15: =G12-G13+G14 -> 75 | H15: =H12-H13+H14 -> 90 | I15: =I12-I13+I14 -> 90 | J15: =J12-J13+J14 -> 90 | K15: =K12-K13+K14 -> 90 | ... R15: =R12-R13+R14 -> 90
A16: Satellites built incl. launch losses | B16: # | D16: =D14/(1-Inputs!$D$27) -> 16.842105 | E16: =E14/(1-Inputs!$D$27) -> 26.315789 | F16: =F14/(1-Inputs!$D$27) -> 15.789474 | G16: =G14/(1-Inputs!$D$27) -> 15.789474 | H16: =H14/(1-Inputs!$D$27) -> 15.789474 | I16: =I14/(1-Inputs!$D$27) -> 0 | J16: =J14/(1-Inputs!$D$27) -> 0 | K16: =K14/(1-Inputs!$D$27) -> 21.052632 | ... R16: =R14/(1-Inputs!$D$27) -> 21.052632
A17: Average fleet in orbit | B17: # | D17: =(D12+D15)/2 -> 12 | E17: =(E12+E15)/2 -> 32.5 | F17: =(F12+F15)/2 -> 52.5 | G17: =(G12+G15)/2 -> 67.5 | H17: =(H12+H15)/2 -> 82.5 | I17: =(I12+I15)/2 -> 90 | J17: =(J12+J15)/2 -> 90 | K17: =(K12+K15)/2 -> 90 | ... R17: =(R12+R15)/2 -> 90
A18: Unit cost incl. launch ($mm/sat) | B18: $mm | D18: =Inputs!$E$64*(1+Inputs!$E$65)^MAX(0,D$6-2028) -> 24 | E18: =Inputs!$E$64*(1+Inputs!$E$65)^MAX(0,E$6-2028) -> 24 | F18: =Inputs!$E$64*(1+Inputs!$E$65)^MAX(0,F$6-2028) -> 24 | G18: =Inputs!$E$64*(1+Inputs!$E$65)^MAX(0,G$6-2028) -> 24.6 | H18: =Inputs!$E$64*(1+Inputs!$E$65)^MAX(0,H$6-2028) -> 25.215 | I18: =Inputs!$E$64*(1+Inputs!$E$65)^MAX(0,I$6-2028) -> 25.845375 | J18: =Inputs!$E$64*(1+Inputs!$E$65)^MAX(0,J$6-2028) -> 26.491509 | K18: =Inputs!$E$64*(1+Inputs!$E$65)^MAX(0,K$6-2028) -> 27.153797 | ... R18: =Inputs!$E$64*(1+Inputs!$E$65)^MAX(0,R$6-2028) -> 32.277332
A19: Satellite capex (gross, placed in service) | B19: $mm | D19: =D16*D18 -> 404.21053 | E19: =E16*E18 -> 631.57895 | F19: =F16*F18 -> 378.94737 | G19: =G16*G18 -> 388.42105 | H19: =H16*H18 -> 398.13158 | I19: =I16*I18 -> 0 | J19: =J16*J18 -> 0 | K19: =K16*K18 -> 571.65889 | ... R19: =R16*R18 -> 679.52277
A20: CIP pre-funding pool (scalar, col C) | C20: =Inputs!$D$29*Inputs!$E$66 -> 775.83825
A21: CIP credit applied (already-paid capex) | B21: $mm | D21: =MIN(D19,$C$20) -> 404.21053 | E21: =MIN(E19,$C$20-SUM($D$21:D21)) -> 371.62772 | F21: =MIN(F19,$C$20-SUM($D$21:E21)) -> 0 | G21: =MIN(G19,$C$20-SUM($D$21:F21)) -> 0 | H21: =MIN(H19,$C$20-SUM($D$21:G21)) -> 0 | I21: =MIN(I19,$C$20-SUM($D$21:H21)) -> 0 | J21: =MIN(J19,$C$20-SUM($D$21:I21)) -> 0 | K21: =MIN(K19,$C$20-SUM($D$21:J21)) -> 0 | L21: =MIN(L19,$C$20-SUM($D$21:K21)) -> 0 | ... R21: =MIN(R19,$C$20-SUM($D$21:Q21)) -> 0
A22: Satellite capex, cash | B22: $mm | D22: =D19-D21 -> 0 | E22: =E19-E21 -> 259.95122 | F22: =F19-F21 -> 378.94737 | G22: =G19-G21 -> 388.42105 | H22: =H19-H21 -> 398.13158 | I22: =I19-I21 -> 0 | J22: =J19-J21 -> 0 | K22: =K19-K21 -> 571.65889 | ... R22: =R19-R21 -> 679.52277
A23: REVENUE BUILD
A24: Tier-1 coverage (fraction of partner base) | B24: % | D24: =MIN(1,MAX(0,(D17-Inputs!$D$32)/(Inputs!$D$33-Inputs!$D$32))) -> 0 | E24: =MIN(1,MAX(0,(E17-Inputs!$D$32)/(Inputs!$D$33-Inputs!$D$32))) -> 0.3125 | F24: =MIN(1,MAX(0,(F17-Inputs!$D$32)/(Inputs!$D$33-Inputs!$D$32))) -> 0.8125 | G24: =MIN(1,MAX(0,(G17-Inputs!$D$32)/(Inputs!$D$33-Inputs!$D$32))) -> 1 | H24: =MIN(1,MAX(0,(H17-Inputs!$D$32)/(Inputs!$D$33-Inputs!$D$32))) -> 1 | I24: =MIN(1,MAX(0,(I17-Inputs!$D$32)/(Inputs!$D$33-Inputs!$D$32))) -> 1 | J24: =MIN(1,MAX(0,(J17-Inputs!$D$32)/(Inputs!$D$33-Inputs!$D$32))) -> 1 | K24: =MIN(1,MAX(0,(K17-Inputs!$D$32)/(Inputs!$D$33-Inputs!$D$32))) -> 1 | ... R24: =MIN(1,MAX(0,(R17-Inputs!$D$32)/(Inputs!$D$33-Inputs!$D$32))) -> 1
A25: Tier-2 coverage | B25: % | D25: =MIN(1,MAX(0,(D17-Inputs!$D$34)/(Inputs!$D$35-Inputs!$D$34))) -> 0 | E25: =MIN(1,MAX(0,(E17-Inputs!$D$34)/(Inputs!$D$35-Inputs!$D$34))) -> 0 | F25: =MIN(1,MAX(0,(F17-Inputs!$D$34)/(Inputs!$D$35-Inputs!$D$34))) -> 0 | G25: =MIN(1,MAX(0,(G17-Inputs!$D$34)/(Inputs!$D$35-Inputs!$D$34))) -> 0.25 | H25: =MIN(1,MAX(0,(H17-Inputs!$D$34)/(Inputs!$D$35-Inputs!$D$34))) -> 0.75 | I25: =MIN(1,MAX(0,(I17-Inputs!$D$34)/(Inputs!$D$35-Inputs!$D$34))) -> 1 | J25: =MIN(1,MAX(0,(J17-Inputs!$D$34)/(Inputs!$D$35-Inputs!$D$34))) -> 1 | K25: =MIN(1,MAX(0,(K17-Inputs!$D$34)/(Inputs!$D$35-Inputs!$D$34))) -> 1 | ... R25: =MIN(1,MAX(0,(R17-Inputs!$D$34)/(Inputs!$D$35-Inputs!$D$34))) -> 1
A26: Logistic steepness k = 2 ln(19) / ramp (col C) | C26: =2*LN(19)/Inputs!$E$72 -> 0.84126828
A27: Tier-1 adoption (take rate of covered subs) | B27: % | D27: =IF(D9>=Inputs!$E$68,Inputs!$E$70/(1+EXP(-$C$26*(D9-(Inputs!$E$68+Inputs!$E$72/2)))),0) -> 0 | E27: =IF(E9>=Inputs!$E$68,Inputs!$E$70/(1+EXP(-$C$26*(E9-(Inputs!$E$68+Inputs!$E$72/2)))),0) -> 0 | F27: =IF(F9>=Inputs!$E$68,Inputs!$E$70/(1+EXP(-$C$26*(F9-(Inputs!$E$68+Inputs!$E$72/2)))),0) -> 0.0044523678 | G27: =IF(G9>=Inputs!$E$68,Inputs!$E$70/(1+EXP(-$C$26*(G9-(Inputs!$E$68+Inputs!$E$72/2)))),0) -> 0.0094055927 | H27: =IF(H9>=Inputs!$E$68,Inputs!$E$70/(1+EXP(-$C$26*(H9-(Inputs!$E$68+Inputs!$E$72/2)))),0) -> 0.018076064 | I27: =IF(I9>=Inputs!$E$68,Inputs!$E$70/(1+EXP(-$C$26*(I9-(Inputs!$E$68+Inputs!$E$72/2)))),0) -> 0.03 | J27: =IF(J9>=Inputs!$E$68,Inputs!$E$70/(1+EXP(-$C$26*(J9-(Inputs!$E$68+Inputs!$E$72/2)))),0) -> 0.041923936 | K27: =IF(K9>=Inputs!$E$68,Inputs!$E$70/(1+EXP(-$C$26*(K9-(Inputs!$E$68+Inputs!$E$72/2)))),0) -> 0.050594407 | ... R27: =IF(R9>=Inputs!$E$68,Inputs!$E$70/(1+EXP(-$C$26*(R9-(Inputs!$E$68+Inputs!$E$72/2)))),0) -> 0.059969118
A28: Tier-2 adoption (take rate of covered subs) | B28: % | D28: =IF(D9>=Inputs!$E$69,Inputs!$E$71/(1+EXP(-$C$26*(D9-(Inputs!$E$69+Inputs!$E$72/2)))),0) -> 0 | E28: =IF(E9>=Inputs!$E$69,Inputs!$E$71/(1+EXP(-$C$26*(E9-(Inputs!$E$69+Inputs!$E$72/2)))),0) -> 0 | F28: =IF(F9>=Inputs!$E$69,Inputs!$E$71/(1+EXP(-$C$26*(F9-(Inputs!$E$69+Inputs!$E$72/2)))),0) -> 0 | G28: =IF(G9>=Inputs!$E$69,Inputs!$E$71/(1+EXP(-$C$26*(G9-(Inputs!$E$69+Inputs!$E$72/2)))),0) -> 0 | H28: =IF(H9>=Inputs!$E$69,Inputs!$E$71/(1+EXP(-$C$26*(H9-(Inputs!$E$69+Inputs!$E$72/2)))),0) -> 0.001113092 | I28: =IF(I9>=Inputs!$E$69,Inputs!$E$71/(1+EXP(-$C$26*(I9-(Inputs!$E$69+Inputs!$E$72/2)))),0) -> 0.0023513982 | J28: =IF(J9>=Inputs!$E$69,Inputs!$E$71/(1+EXP(-$C$26*(J9-(Inputs!$E$69+Inputs!$E$72/2)))),0) -> 0.0045190161 | K28: =IF(K9>=Inputs!$E$69,Inputs!$E$71/(1+EXP(-$C$26*(K9-(Inputs!$E$69+Inputs!$E$72/2)))),0) -> 0.0075 | ... R28: =IF(R9>=Inputs!$E$69,Inputs!$E$71/(1+EXP(-$C$26*(R9-(Inputs!$E$69+Inputs!$E$72/2)))),0) -> 0.014958564
A29: MNO partner subscriber base (mm) | B29: mm | D29: =Inputs!$D$30*(1+Inputs!$D$51)^MAX(0,D$6-2026) -> 3000 | E29: =Inputs!$D$30*(1+Inputs!$D$51)^MAX(0,E$6-2026) -> 3030 | F29: =Inputs!$D$30*(1+Inputs!$D$51)^MAX(0,F$6-2026) -> 3060.3 | G29: =Inputs!$D$30*(1+Inputs!$D$51)^MAX(0,G$6-2026) -> 3090.903 | H29: =Inputs!$D$30*(1+Inputs!$D$51)^MAX(0,H$6-2026) -> 3121.812 | I29: =Inputs!$D$30*(1+Inputs!$D$51)^MAX(0,I$6-2026) -> 3153.0302 | J29: =Inputs!$D$30*(1+Inputs!$D$51)^MAX(0,J$6-2026) -> 3184.5605 | K29: =Inputs!$D$30*(1+Inputs!$D$51)^MAX(0,K$6-2026) -> 3216.4061 | ... R29: =Inputs!$D$30*(1+Inputs!$D$51)^MAX(0,R$6-2026) -> 3448.4226
A30: Tier-1 paying users (mm, period avg) | B30: mm | D30: =D29*Inputs!$D$31*D24*D27 -> 0 | E30: =E29*Inputs!$D$31*E24*E27 -> 0 | F30: =F29*Inputs!$D$31*F24*F27 -> 2.7676962 | G30: =G29*Inputs!$D$31*G24*G27 -> 7.2679437 | H30: =H29*Inputs!$D$31*H24*H27 -> 14.107519 | I30: =I29*Inputs!$D$31*I24*I27 -> 23.647726 | J30: =J29*Inputs!$D$31*J24*J27 -> 33.377327 | K30: =K29*Inputs!$D$31*K24*K27 -> 40.683039 | ... R30: =R29*Inputs!$D$31*R24*R27 -> 51.699716
A31: Tier-2 paying users (mm, period avg) | B31: mm | D31: =D29*(1-Inputs!$D$31)*D25*D28 -> 0 | E31: =E29*(1-Inputs!$D$31)*E25*E28 -> 0 | F31: =F29*(1-Inputs!$D$31)*F25*F28 -> 0 | G31: =G29*(1-Inputs!$D$31)*G25*G28 -> 0 | H31: =H29*(1-Inputs!$D$31)*H25*H28 -> 1.9546109 | I31: =I29*(1-Inputs!$D$31)*I25*I28 -> 5.560522 | J31: =J29*(1-Inputs!$D$31)*J25*J28 -> 10.79331 | K31: =K29*(1-Inputs!$D$31)*K25*K28 -> 18.092284 | ... R31: =R29*(1-Inputs!$D$31)*R25*R28 -> 38.687587
A32: ARPU index (2027 = 1.00) | B32: x | D32: =(1+Inputs!$E$75)^MIN(MAX(0,D$6-2027),Inputs!$D$49-2027)*(1+Inputs!$D$50)^MAX(0,D$6-Inputs!$D$49) -> 1 | E32: =(1+Inputs!$E$75)^MIN(MAX(0,E$6-2027),Inputs!$D$49-2027)*(1+Inputs!$D$50)^MAX(0,E$6-Inputs!$D$49) -> 1 | F32: =(1+Inputs!$E$75)^MIN(MAX(0,F$6-2027),Inputs!$D$49-2027)*(1+Inputs!$D$50)^MAX(0,F$6-Inputs!$D$49) -> 0.98 | G32: =(1+Inputs!$E$75)^MIN(MAX(0,G$6-2027),Inputs!$D$49-2027)*(1+Inputs!$D$50)^MAX(0,G$6-Inputs!$D$49) -> 0.9604 | H32: =(1+Inputs!$E$75)^MIN(MAX(0,H$6-2027),Inputs!$D$49-2027)*(1+Inputs!$D$50)^MAX(0,H$6-Inputs!$D$49) -> 0.941192 | I32: =(1+Inputs!$E$75)^MIN(MAX(0,I$6-2027),Inputs!$D$49-2027)*(1+Inputs!$D$50)^MAX(0,I$6-Inputs!$D$49) -> 0.92236816 | J32: =(1+Inputs!$E$75)^MIN(MAX(0,J$6-2027),Inputs!$D$49-2027)*(1+Inputs!$D$50)^MAX(0,J$6-Inputs!$D$49) -> 0.9039208 | K32: =(1+Inputs!$E$75)^MIN(MAX(0,K$6-2027),Inputs!$D$49-2027)*(1+Inputs!$D$50)^MAX(0,K$6-Inputs!$D$49) -> 0.91747961 | ... R32: =(1+Inputs!$E$75)^MIN(MAX(0,R$6-2027),Inputs!$D$49-2027)*(1+Inputs!$D$50)^MAX(0,R$6-Inputs!$D$49) -> 1.0182601
A33: Tier-1 service revenue | B33: $mm | D33: =D30*Inputs!$E$73*D32*12*D7 -> 0 | E33: =E30*Inputs!$E$73*E32*12*E7 -> 0 | F33: =F30*Inputs!$E$73*F32*12*F7 -> 138.32946 | G33: =G30*Inputs!$E$73*G32*12*G7 -> 355.98679 | H33: =H30*Inputs!$E$73*H32*12*H7 -> 677.17207 | I33: =I30*Inputs!$E$73*I32*12*I7 -> 1112.4074 | J33: =J30*Inputs!$E$73*J32*12*J7 -> 1538.6935 | K33: =K30*Inputs!$E$73*K32*12*K7 -> 1903.6188 | ... R33: =R30*Inputs!$E$73*R32*12*R7 -> 2684.8316
A34: Tier-2 service revenue | B34: $mm | D34: =D31*Inputs!$E$74*D32*12*D7 -> 0 | E34: =E31*Inputs!$E$74*E32*12*E7 -> 0 | F34: =F31*Inputs!$E$74*F32*12*F7 -> 0 | G34: =G31*Inputs!$E$74*G32*12*G7 -> 0 | H34: =H31*Inputs!$E$74*H32*12*H7 -> 13.245582 | I34: =I31*Inputs!$E$74*I32*12*I7 -> 36.927709 | J34: =J31*Inputs!$E$74*J32*12*J7 -> 70.24534 | K34: =K31*Inputs!$E$74*K32*12*K7 -> 119.51497 | ... R34: =R31*Inputs!$E$74*R32*12*R7 -> 283.63698
A35: Government revenue | B35: $mm | D35: =IF(D$6=2026,Inputs!$E$78,IF(D$6=2027,Inputs!$E$79,IF(D$6=2028,Inputs!$E$80,IF(D$6=2029,Inputs!$E$81,Inputs!$E$82*(1+Inputs!$E$83)^(D$6-2030))))) -> 40 | E35: =IF(E$6=2026,Inputs!$E$78,IF(E$6=2027,Inputs!$E$79,IF(E$6=2028,Inputs!$E$80,IF(E$6=2029,Inputs!$E$81,Inputs!$E$82*(1+Inputs!$E$83)^(E$6-2030))))) -> 80 | F35: =IF(F$6=2026,Inputs!$E$78,IF(F$6=2027,Inputs!$E$79,IF(F$6=2028,Inputs!$E$80,IF(F$6=2029,Inputs!$E$81,Inputs!$E$82*(1+Inputs!$E$83)^(F$6-2030))))) -> 120 | G35: =IF(G$6=2026,Inputs!$E$78,IF(G$6=2027,Inputs!$E$79,IF(G$6=2028,Inputs!$E$80,IF(G$6=2029,Inputs!$E$81,Inputs!$E$82*(1+Inputs!$E$83)^(G$6-2030))))) -> 150 | H35: =IF(H$6=2026,Inputs!$E$78,IF(H$6=2027,Inputs!$E$79,IF(H$6=2028,Inputs!$E$80,IF(H$6=2029,Inputs!$E$81,Inputs!$E$82*(1+Inputs!$E$83)^(H$6-2030))))) -> 180 | I35: =IF(I$6=2026,Inputs!$E$78,IF(I$6=2027,Inputs!$E$79,IF(I$6=2028,Inputs!$E$80,IF(I$6=2029,Inputs!$E$81,Inputs!$E$82*(1+Inputs!$E$83)^(I$6-2030))))) -> 187.2 | J35: =IF(J$6=2026,Inputs!$E$78,IF(J$6=2027,Inputs!$E$79,IF(J$6=2028,Inputs!$E$80,IF(J$6=2029,Inputs!$E$81,Inputs!$E$82*(1+Inputs!$E$83)^(J$6-2030))))) -> 194.688 | K35: =IF(K$6=2026,Inputs!$E$78,IF(K$6=2027,Inputs!$E$79,IF(K$6=2028,Inputs!$E$80,IF(K$6=2029,Inputs!$E$81,Inputs!$E$82*(1+Inputs!$E$83)^(K$6-2030))))) -> 202.47552 | ... R35: =IF(R$6=2026,Inputs!$E$78,IF(R$6=2027,Inputs!$E$79,IF(R$6=2028,Inputs!$E$80,IF(R$6=2029,Inputs!$E$81,Inputs!$E$82*(1+Inputs!$E$83)^(R$6-2030))))) -> 266.44397
A36: Gateway / product revenue | B36: $mm | D36: =IF(D$6=2026,Inputs!$E$84,IF(D$6=2027,Inputs!$E$85,IF(D$6=2028,Inputs!$E$86,Inputs!$E$87))) -> 80 | E36: =IF(E$6=2026,Inputs!$E$84,IF(E$6=2027,Inputs!$E$85,IF(E$6=2028,Inputs!$E$86,Inputs!$E$87))) -> 90 | F36: =IF(F$6=2026,Inputs!$E$84,IF(F$6=2027,Inputs!$E$85,IF(F$6=2028,Inputs!$E$86,Inputs!$E$87))) -> 50 | G36: =IF(G$6=2026,Inputs!$E$84,IF(G$6=2027,Inputs!$E$85,IF(G$6=2028,Inputs!$E$86,Inputs!$E$87))) -> 30 | H36: =IF(H$6=2026,Inputs!$E$84,IF(H$6=2027,Inputs!$E$85,IF(H$6=2028,Inputs!$E$86,Inputs!$E$87))) -> 30 | I36: =IF(I$6=2026,Inputs!$E$84,IF(I$6=2027,Inputs!$E$85,IF(I$6=2028,Inputs!$E$86,Inputs!$E$87))) -> 30 | J36: =IF(J$6=2026,Inputs!$E$84,IF(J$6=2027,Inputs!$E$85,IF(J$6=2028,Inputs!$E$86,Inputs!$E$87))) -> 30 | K36: =IF(K$6=2026,Inputs!$E$84,IF(K$6=2027,Inputs!$E$85,IF(K$6=2028,Inputs!$E$86,Inputs!$E$87))) -> 30 | ... R36: =IF(R$6=2026,Inputs!$E$84,IF(R$6=2027,Inputs!$E$85,IF(R$6=2028,Inputs!$E$86,Inputs!$E$87))) -> 30
A37: Total revenue | B37: $mm | D37: =SUM(D33:D36) -> 120 | E37: =SUM(E33:E36) -> 170 | F37: =SUM(F33:F36) -> 308.32946 | G37: =SUM(G33:G36) -> 535.98679 | H37: =SUM(H33:H36) -> 900.41765 | I37: =SUM(I33:I36) -> 1366.5351 | J37: =SUM(J33:J36) -> 1833.6268 | K37: =SUM(K33:K36) -> 2255.6093 | ... R37: =SUM(R33:R36) -> 3264.9126 | S37: =R37*(1+Inputs!$D$20) -> 3346.5354
A38: Revenue growth (annualised) | B38: % | D38: =IF(Inputs!$D$36=0,0,(D37/D7)/(Inputs!$D$36/0.5)-1) -> 1.5943141 | E38: =IF(D37=0,0,(E37/E7)/(D37/D7)-1) -> -0.29166667 | F38: =IF(E37=0,0,(F37/F7)/(E37/E7)-1) -> 0.81370268 | G38: =IF(F37=0,0,(G37/G7)/(F37/F7)-1) -> 0.73835739 | H38: =IF(G37=0,0,(H37/H7)/(G37/G7)-1) -> 0.67992508 | I38: =IF(H37=0,0,(I37/I7)/(H37/H7)-1) -> 0.51766805 | J38: =IF(I37=0,0,(J37/J7)/(I37/I7)-1) -> 0.34180732 | K38: =IF(J37=0,0,(K37/K7)/(J37/J7)-1) -> 0.23013544 | L38: =IF(K37=0,0,(L37/L7)/(K37/K7)-1) -> 0.1324392 | ... R38: =IF(Q37=0,0,(R37/R7)/(Q37/Q7)-1) -> 0.02700648
A39: Paying users per satellite in orbit (mm) | B39: mm | D39: =IF(D17=0,0,(D30+D31)/D17) -> 0 | E39: =IF(E17=0,0,(E30+E31)/E17) -> 0 | F39: =IF(F17=0,0,(F30+F31)/F17) -> 0.052718023 | G39: =IF(G17=0,0,(G30+G31)/G17) -> 0.10767324 | H39: =IF(H17=0,0,(H30+H31)/H17) -> 0.19469248 | I39: =IF(I17=0,0,(I30+I31)/I17) -> 0.32453609 | J39: =IF(J17=0,0,(J30+J31)/J17) -> 0.49078485 | K39: =IF(K17=0,0,(K30+K31)/K17) -> 0.65305915 | ... R39: =IF(R17=0,0,(R30+R31)/R17) -> 1.0043034
A40: OPERATING COSTS & EBITDA
A41: Cost of revenue (gateway + government) | B41: $mm | D41: =D36*(1-Inputs!$D$52)+D35*Inputs!$D$53 -> 90 | E41: =E36*(1-Inputs!$D$52)+E35*Inputs!$D$53 -> 113.5 | F41: =F36*(1-Inputs!$D$52)+F35*Inputs!$D$53 -> 89.5 | G41: =G36*(1-Inputs!$D$52)+G35*Inputs!$D$53 -> 81 | H41: =H36*(1-Inputs!$D$52)+H35*Inputs!$D$53 -> 91.5 | I41: =I36*(1-Inputs!$D$52)+I35*Inputs!$D$53 -> 94.02 | J41: =J36*(1-Inputs!$D$52)+J35*Inputs!$D$53 -> 96.6408 | K41: =K36*(1-Inputs!$D$52)+K35*Inputs!$D$53 -> 99.366432 | ... R41: =R36*(1-Inputs!$D$52)+R35*Inputs!$D$53 -> 121.75539
A42: Service variable cost | B42: $mm | D42: =(D33+D34)*Inputs!$E$76 -> 0 | E42: =(E33+E34)*Inputs!$E$76 -> 0 | F42: =(F33+F34)*Inputs!$E$76 -> 17.982829 | G42: =(G33+G34)*Inputs!$E$76 -> 46.278283 | H42: =(H33+H34)*Inputs!$E$76 -> 89.754295 | I42: =(I33+I34)*Inputs!$E$76 -> 149.41356 | J42: =(J33+J34)*Inputs!$E$76 -> 209.16204 | K42: =(K33+K34)*Inputs!$E$76 -> 263.00739 | ... R42: =(R33+R34)*Inputs!$E$76 -> 385.90092
A43: Ligado revenue share | B43: $mm | D43: =D33*Inputs!$D$47 -> 0 | E43: =E33*Inputs!$D$47 -> 0 | F43: =F33*Inputs!$D$47 -> 4.1498837 | G43: =G33*Inputs!$D$47 -> 10.679604 | H43: =H33*Inputs!$D$47 -> 20.315162 | I43: =I33*Inputs!$D$47 -> 33.372222 | J43: =J33*Inputs!$D$47 -> 46.160804 | K43: =K33*Inputs!$D$47 -> 57.108565 | ... R43: =R33*Inputs!$D$47 -> 80.544948
A44: Spectrum usage payments | B44: $mm | D44: =IF(D$6>=Inputs!$D$45,Inputs!$D$46*D7,0) -> 0 | E44: =IF(E$6>=Inputs!$D$45,Inputs!$D$46*E7,0) -> 100 | F44: =IF(F$6>=Inputs!$D$45,Inputs!$D$46*F7,0) -> 100 | G44: =IF(G$6>=Inputs!$D$45,Inputs!$D$46*G7,0) -> 100 | H44: =IF(H$6>=Inputs!$D$45,Inputs!$D$46*H7,0) -> 100 | I44: =IF(I$6>=Inputs!$D$45,Inputs!$D$46*I7,0) -> 100 | J44: =IF(J$6>=Inputs!$D$45,Inputs!$D$46*J7,0) -> 100 | K44: =IF(K$6>=Inputs!$D$45,Inputs!$D$46*K7,0) -> 100 | ... R44: =IF(R$6>=Inputs!$D$45,Inputs!$D$46*R7,0) -> 100
A45: Fixed adj. opex (ex-COGS, ex-SBC) | B45: $mm | D45: =Inputs!$E$89 -> 210 | E45: =IF(E$6=2027,Inputs!$E$90,D45*(1+IF(E$6=2028,Inputs!$E$91,IF(E$6=2029,Inputs!$E$92,IF(E$6=2030,Inputs!$E$93,Inputs!$E$94))))) -> 470 | F45: =IF(F$6=2027,Inputs!$E$90,E45*(1+IF(F$6=2028,Inputs!$E$91,IF(F$6=2029,Inputs!$E$92,IF(F$6=2030,Inputs!$E$93,Inputs!$E$94))))) -> 512.3 | G45: =IF(G$6=2027,Inputs!$E$90,F45*(1+IF(G$6=2028,Inputs!$E$91,IF(G$6=2029,Inputs!$E$92,IF(G$6=2030,Inputs!$E$93,Inputs!$E$94))))) -> 548.161 | H45: =IF(H$6=2027,Inputs!$E$90,G45*(1+IF(H$6=2028,Inputs!$E$91,IF(H$6=2029,Inputs!$E$92,IF(H$6=2030,Inputs!$E$93,Inputs!$E$94))))) -> 575.56905 | I45: =IF(I$6=2027,Inputs!$E$90,H45*(1+IF(I$6=2028,Inputs!$E$91,IF(I$6=2029,Inputs!$E$92,IF(I$6=2030,Inputs!$E$93,Inputs!$E$94))))) -> 595.71397 | J45: =IF(J$6=2027,Inputs!$E$90,I45*(1+IF(J$6=2028,Inputs!$E$91,IF(J$6=2029,Inputs!$E$92,IF(J$6=2030,Inputs!$E$93,Inputs!$E$94))))) -> 616.56396 | K45: =IF(K$6=2027,Inputs!$E$90,J45*(1+IF(K$6=2028,Inputs!$E$91,IF(K$6=2029,Inputs!$E$92,IF(K$6=2030,Inputs!$E$93,Inputs!$E$94))))) -> 638.14369 | L45: =IF(L$6=2027,Inputs!$E$90,K45*(1+IF(L$6=2028,Inputs!$E$91,IF(L$6=2029,Inputs!$E$92,IF(L$6=2030,Inputs!$E$93,Inputs!$E$94))))) -> 660.47872 | ... R45: =IF(R$6=2027,Inputs!$E$90,Q45*(1+IF(R$6=2028,Inputs!$E$91,IF(R$6=2029,Inputs!$E$92,IF(R$6=2030,Inputs!$E$93,Inputs!$E$94))))) -> 811.89699
A46: Network, ground & insurance opex | B46: $mm | D46: =D17*Inputs!$D$48*D7 -> 12 | E46: =E17*Inputs!$D$48*E7 -> 65 | F46: =F17*Inputs!$D$48*F7 -> 105 | G46: =G17*Inputs!$D$48*G7 -> 135 | H46: =H17*Inputs!$D$48*H7 -> 165 | I46: =I17*Inputs!$D$48*I7 -> 180 | J46: =J17*Inputs!$D$48*J7 -> 180 | K46: =K17*Inputs!$D$48*K7 -> 180 | ... R46: =R17*Inputs!$D$48*R7 -> 180
A47: Stock-based compensation (treated as cost) | B47: $mm | D47: =Inputs!$E$95 -> 125 | E47: =MAX(Inputs!$E$96*(1-Inputs!$E$97)^MAX(0,E$6-2027),Inputs!$E$98*E37) -> 240 | F47: =MAX(Inputs!$E$96*(1-Inputs!$E$97)^MAX(0,F$6-2027),Inputs!$E$98*F37) -> 216 | G47: =MAX(Inputs!$E$96*(1-Inputs!$E$97)^MAX(0,G$6-2027),Inputs!$E$98*G37) -> 194.4 | H47: =MAX(Inputs!$E$96*(1-Inputs!$E$97)^MAX(0,H$6-2027),Inputs!$E$98*H37) -> 174.96 | I47: =MAX(Inputs!$E$96*(1-Inputs!$E$97)^MAX(0,I$6-2027),Inputs!$E$98*I37) -> 157.464 | J47: =MAX(Inputs!$E$96*(1-Inputs!$E$97)^MAX(0,J$6-2027),Inputs!$E$98*J37) -> 141.7176 | K47: =MAX(Inputs!$E$96*(1-Inputs!$E$97)^MAX(0,K$6-2027),Inputs!$E$98*K37) -> 127.54584 | L47: =MAX(Inputs!$E$96*(1-Inputs!$E$97)^MAX(0,L$6-2027),Inputs!$E$98*L37) -> 114.79126 | ... R47: =MAX(Inputs!$E$96*(1-Inputs!$E$97)^MAX(0,R$6-2027),Inputs!$E$98*R37) -> 114.27194
A48: Total operating costs | B48: $mm | D48: =SUM(D41:D47) -> 437 | E48: =SUM(E41:E47) -> 988.5 | F48: =SUM(F41:F47) -> 1044.9327 | G48: =SUM(G41:G47) -> 1115.5189 | H48: =SUM(H41:H47) -> 1217.0985 | I48: =SUM(I41:I47) -> 1309.9838 | J48: =SUM(J41:J47) -> 1390.2452 | K48: =SUM(K41:K47) -> 1465.1719 | ... R48: =SUM(R41:R47) -> 1794.3702
A49: EBITDA (after SBC) | B49: $mm | D49: =D37-D48 -> -317 | E49: =E37-E48 -> -818.5 | F49: =F37-F48 -> -736.60326 | G49: =G37-G48 -> -579.5321 | H49: =H37-H48 -> -316.68086 | I49: =I37-I48 -> 56.551349 | J49: =J37-J48 -> 443.3816 | K49: =K37-K48 -> 790.43739 | ... R49: =R37-R48 -> 1470.5424 | S49: =R49*(1+Inputs!$D$20) -> 1507.3059
A50: EBITDA margin | B50: % | D50: =IF(D37=0,0,D49/D37) -> -2.6416667 | E50: =IF(E37=0,0,E49/E37) -> -4.8147059 | F50: =IF(F37=0,0,F49/F37) -> -2.3890136 | G50: =IF(G37=0,0,G49/G37) -> -1.0812432 | H50: =IF(H37=0,0,H49/H37) -> -0.35170441 | I50: =IF(I37=0,0,I49/I37) -> 0.04138302 | J50: =IF(J37=0,0,J49/J37) -> 0.2418058 | K50: =IF(K37=0,0,K49/K37) -> 0.35043187 | ... R50: =IF(R37=0,0,R49/R37) -> 0.45040789
A51: CAPEX & OTHER INVESTING ITEMS
A52: Other capex (ground, facilities) | B52: $mm | D52: =IF(D$6=2026,Inputs!$E$100,IF(D$6=2027,Inputs!$E$101,IF(D$6=2028,Inputs!$E$102,MAX(Inputs!$E$104,Inputs!$E$103*D37)))) -> 170 | E52: =IF(E$6=2026,Inputs!$E$100,IF(E$6=2027,Inputs!$E$101,IF(E$6=2028,Inputs!$E$102,MAX(Inputs!$E$104,Inputs!$E$103*E37)))) -> 230 | F52: =IF(F$6=2026,Inputs!$E$100,IF(F$6=2027,Inputs!$E$101,IF(F$6=2028,Inputs!$E$102,MAX(Inputs!$E$104,Inputs!$E$103*F37)))) -> 170 | G52: =IF(G$6=2026,Inputs!$E$100,IF(G$6=2027,Inputs!$E$101,IF(G$6=2028,Inputs!$E$102,MAX(Inputs!$E$104,Inputs!$E$103*G37)))) -> 80 | H52: =IF(H$6=2026,Inputs!$E$100,IF(H$6=2027,Inputs!$E$101,IF(H$6=2028,Inputs!$E$102,MAX(Inputs!$E$104,Inputs!$E$103*H37)))) -> 80 | I52: =IF(I$6=2026,Inputs!$E$100,IF(I$6=2027,Inputs!$E$101,IF(I$6=2028,Inputs!$E$102,MAX(Inputs!$E$104,Inputs!$E$103*I37)))) -> 80 | J52: =IF(J$6=2026,Inputs!$E$100,IF(J$6=2027,Inputs!$E$101,IF(J$6=2028,Inputs!$E$102,MAX(Inputs!$E$104,Inputs!$E$103*J37)))) -> 80 | K52: =IF(K$6=2026,Inputs!$E$100,IF(K$6=2027,Inputs!$E$101,IF(K$6=2028,Inputs!$E$102,MAX(Inputs!$E$104,Inputs!$E$103*K37)))) -> 80 | ... R52: =IF(R$6=2026,Inputs!$E$100,IF(R$6=2027,Inputs!$E$101,IF(R$6=2028,Inputs!$E$102,MAX(Inputs!$E$104,Inputs!$E$103*R37)))) -> 114.27194
A53: Ligado spectrum closing payment | B53: $mm | D53: =IF(D$6=Inputs!$D$45,Inputs!$D$44,0) -> 0 | E53: =IF(E$6=Inputs!$D$45,Inputs!$D$44,0) -> 550 | F53: =IF(F$6=Inputs!$D$45,Inputs!$D$44,0) -> 0 | G53: =IF(G$6=Inputs!$D$45,Inputs!$D$44,0) -> 0 | H53: =IF(H$6=Inputs!$D$45,Inputs!$D$44,0) -> 0 | I53: =IF(I$6=Inputs!$D$45,Inputs!$D$44,0) -> 0 | J53: =IF(J$6=Inputs!$D$45,Inputs!$D$44,0) -> 0 | K53: =IF(K$6=Inputs!$D$45,Inputs!$D$44,0) -> 0 | ... R53: =IF(R$6=Inputs!$D$45,Inputs!$D$44,0) -> 0
A54: J-LEO non-dilutive capital (inflow) | B54: $mm | D54: =IF(D$6=2028,Inputs!$E$105,0) -> 0 | E54: =IF(E$6=2028,Inputs!$E$105,0) -> 0 | F54: =IF(F$6=2028,Inputs!$E$105,0) -> 0 | G54: =IF(G$6=2028,Inputs!$E$105,0) -> 0 | H54: =IF(H$6=2028,Inputs!$E$105,0) -> 0 | I54: =IF(I$6=2028,Inputs!$E$105,0) -> 0 | J54: =IF(J$6=2028,Inputs!$E$105,0) -> 0 | K54: =IF(K$6=2028,Inputs!$E$105,0) -> 0 | ... R54: =IF(R$6=2028,Inputs!$E$105,0) -> 0
A55: CASH TAXES (NOL + depreciation)
A56: Tax-basis capex placed in service | B56: $mm | D56: =D19+D52 -> 574.21053 | E56: =E19+E52 -> 861.57895 | F56: =F19+F52 -> 548.94737 | G56: =G19+G52 -> 468.42105 | H56: =H19+H52 -> 478.13158 | I56: =I19+I52 -> 80 | J56: =J19+J52 -> 80 | K56: =K19+K52 -> 651.65889 | ... R56: =R19+R52 -> 793.79471
A57: Tax depreciation | B57: $mm | D57: =IF(Inputs!$D$25=1,D56,SUMIFS($D$56:D56,$D$6:D6,">"&(D$6-ROUND(Inputs!$D$26,0)))/ROUND(Inputs!$D$26,0)*D7) -> 574.21053 | E57: =IF(Inputs!$D$25=1,E56,SUMIFS($D$56:E56,$D$6:E6,">"&(E$6-ROUND(Inputs!$D$26,0)))/ROUND(Inputs!$D$26,0)*E7) -> 861.57895 | F57: =IF(Inputs!$D$25=1,F56,SUMIFS($D$56:F56,$D$6:F6,">"&(F$6-ROUND(Inputs!$D$26,0)))/ROUND(Inputs!$D$26,0)*F7) -> 548.94737 | G57: =IF(Inputs!$D$25=1,G56,SUMIFS($D$56:G56,$D$6:G6,">"&(G$6-ROUND(Inputs!$D$26,0)))/ROUND(Inputs!$D$26,0)*G7) -> 468.42105 | H57: =IF(Inputs!$D$25=1,H56,SUMIFS($D$56:H56,$D$6:H6,">"&(H$6-ROUND(Inputs!$D$26,0)))/ROUND(Inputs!$D$26,0)*H7) -> 478.13158 | I57: =IF(Inputs!$D$25=1,I56,SUMIFS($D$56:I56,$D$6:I6,">"&(I$6-ROUND(Inputs!$D$26,0)))/ROUND(Inputs!$D$26,0)*I7) -> 80 | J57: =IF(Inputs!$D$25=1,J56,SUMIFS($D$56:J56,$D$6:J6,">"&(J$6-ROUND(Inputs!$D$26,0)))/ROUND(Inputs!$D$26,0)*J7) -> 80 | K57: =IF(Inputs!$D$25=1,K56,SUMIFS($D$56:K56,$D$6:K6,">"&(K$6-ROUND(Inputs!$D$26,0)))/ROUND(Inputs!$D$26,0)*K7) -> 651.65889 | ... R57: =IF(Inputs!$D$25=1,R56,SUMIFS($D$56:R56,$D$6:R6,">"&(R$6-ROUND(Inputs!$D$26,0)))/ROUND(Inputs!$D$26,0)*R7) -> 793.79471
A58: Spectrum amortisation (15-yr, s.197) | B58: $mm | D58: =IF(AND(D$6>=Inputs!$D$45,D$6<Inputs!$D$45+15),Inputs!$D$44/15*D7,0) -> 0 | E58: =IF(AND(E$6>=Inputs!$D$45,E$6<Inputs!$D$45+15),Inputs!$D$44/15*E7,0) -> 36.666667 | F58: =IF(AND(F$6>=Inputs!$D$45,F$6<Inputs!$D$45+15),Inputs!$D$44/15*F7,0) -> 36.666667 | G58: =IF(AND(G$6>=Inputs!$D$45,G$6<Inputs!$D$45+15),Inputs!$D$44/15*G7,0) -> 36.666667 | H58: =IF(AND(H$6>=Inputs!$D$45,H$6<Inputs!$D$45+15),Inputs!$D$44/15*H7,0) -> 36.666667 | I58: =IF(AND(I$6>=Inputs!$D$45,I$6<Inputs!$D$45+15),Inputs!$D$44/15*I7,0) -> 36.666667 | J58: =IF(AND(J$6>=Inputs!$D$45,J$6<Inputs!$D$45+15),Inputs!$D$44/15*J7,0) -> 36.666667 | K58: =IF(AND(K$6>=Inputs!$D$45,K$6<Inputs!$D$45+15),Inputs!$D$44/15*K7,0) -> 36.666667 | ... R58: =IF(AND(R$6>=Inputs!$D$45,R$6<Inputs!$D$45+15),Inputs!$D$44/15*R7,0) -> 36.666667
A59: Taxable income | B59: $mm | D59: =D49-D57-D58 -> -891.21053 | E59: =E49-E57-E58 -> -1716.7456 | F59: =F49-F57-F58 -> -1322.2173 | G59: =G49-G57-G58 -> -1084.6198 | H59: =H49-H57-H58 -> -831.4791 | I59: =I49-I57-I58 -> -60.115318 | J59: =J49-J57-J58 -> 326.71493 | K59: =K49-K57-K58 -> 102.11183 | ... R59: =R49-R57-R58 -> 640.08099
A60: NOL pool - beginning | B60: $mm | D60: =Inputs!$D$23 -> 1000 | E60: =D62 -> 1891.2105 | F60: =E62 -> 3607.9561 | G60: =F62 -> 4930.1734 | H60: =G62 -> 6014.7932 | I60: =H62 -> 6846.2723 | J60: =I62 -> 6906.3877 | K60: =J62 -> 6645.0157 | L60: =K62 -> 6563.3263 | ... R60: =Q62 -> 2794.0102
A61: NOL utilised (80% cap) | B61: $mm | D61: =MIN(D60,MAX(0,D59)*Inputs!$D$24) -> 0 | E61: =MIN(E60,MAX(0,E59)*Inputs!$D$24) -> 0 | F61: =MIN(F60,MAX(0,F59)*Inputs!$D$24) -> 0 | G61: =MIN(G60,MAX(0,G59)*Inputs!$D$24) -> 0 | H61: =MIN(H60,MAX(0,H59)*Inputs!$D$24) -> 0 | I61: =MIN(I60,MAX(0,I59)*Inputs!$D$24) -> 0 | J61: =MIN(J60,MAX(0,J59)*Inputs!$D$24) -> 261.37194 | K61: =MIN(K60,MAX(0,K59)*Inputs!$D$24) -> 81.689467 | ... R61: =MIN(R60,MAX(0,R59)*Inputs!$D$24) -> 512.06479
A62: NOL pool - ending | B62: $mm | D62: =D60-D61+MAX(0,-D59) -> 1891.2105 | E62: =E60-E61+MAX(0,-E59) -> 3607.9561 | F62: =F60-F61+MAX(0,-F59) -> 4930.1734 | G62: =G60-G61+MAX(0,-G59) -> 6014.7932 | H62: =H60-H61+MAX(0,-H59) -> 6846.2723 | I62: =I60-I61+MAX(0,-I59) -> 6906.3877 | J62: =J60-J61+MAX(0,-J59) -> 6645.0157 | K62: =K60-K61+MAX(0,-K59) -> 6563.3263 | ... R62: =R60-R61+MAX(0,-R59) -> 2281.9454
A63: Cash taxes | B63: $mm | D63: =Inputs!$D$22*MAX(0,D59-D61) -> 0 | E63: =Inputs!$D$22*MAX(0,E59-E61) -> 0 | F63: =Inputs!$D$22*MAX(0,F59-F61) -> 0 | G63: =Inputs!$D$22*MAX(0,G59-G61) -> 0 | H63: =Inputs!$D$22*MAX(0,H59-H61) -> 0 | I63: =Inputs!$D$22*MAX(0,I59-I61) -> 0 | J63: =Inputs!$D$22*MAX(0,J59-J61) -> 16.335746 | K63: =Inputs!$D$22*MAX(0,K59-K61) -> 5.1055917 | ... R63: =Inputs!$D$22*MAX(0,R59-R61) -> 32.00405
A64: FREE CASH FLOW TO THE FIRM
A65: Annualised revenue | B65: $mm | D65: =D37/D7 -> 240 | E65: =E37/E7 -> 170 | F65: =F37/F7 -> 308.32946 | G65: =G37/G7 -> 535.98679 | H65: =H37/H7 -> 900.41765 | I65: =I37/I7 -> 1366.5351 | J65: =J37/J7 -> 1833.6268 | K65: =K37/K7 -> 2255.6093 | ... R65: =R37/R7 -> 3264.9126
A66: Increase in net working capital | B66: $mm | D66: =Inputs!$D$42*(D65-Inputs!$D$43) -> 7.3745 | E66: =Inputs!$D$42*(E65-D65) -> -3.5 | F66: =Inputs!$D$42*(F65-E65) -> 6.9164728 | G66: =Inputs!$D$42*(G65-F65) -> 11.382867 | H66: =Inputs!$D$42*(H65-G65) -> 18.221543 | I66: =Inputs!$D$42*(I65-H65) -> 23.305872 | J66: =Inputs!$D$42*(J65-I65) -> 23.354585 | K66: =Inputs!$D$42*(K65-J65) -> 21.099125 | L66: =Inputs!$D$42*(L65-K65) -> 14.936555 | ... R66: =Inputs!$D$42*(R65-Q65) -> 4.2927575
A67: Contract-liability unwind (revenue already paid in cash) | B67: $mm | D67: =IF(AND(D$6>=Inputs!$D$40,D$6<Inputs!$D$40+Inputs!$D$41),Inputs!$D$39/Inputs!$D$41*D7,0) -> 0 | E67: =IF(AND(E$6>=Inputs!$D$40,E$6<Inputs!$D$40+Inputs!$D$41),Inputs!$D$39/Inputs!$D$41*E7,0) -> 53.3866 | F67: =IF(AND(F$6>=Inputs!$D$40,F$6<Inputs!$D$40+Inputs!$D$41),Inputs!$D$39/Inputs!$D$41*F7,0) -> 53.3866 | G67: =IF(AND(G$6>=Inputs!$D$40,G$6<Inputs!$D$40+Inputs!$D$41),Inputs!$D$39/Inputs!$D$41*G7,0) -> 53.3866 | H67: =IF(AND(H$6>=Inputs!$D$40,H$6<Inputs!$D$40+Inputs!$D$41),Inputs!$D$39/Inputs!$D$41*H7,0) -> 53.3866 | I67: =IF(AND(I$6>=Inputs!$D$40,I$6<Inputs!$D$40+Inputs!$D$41),Inputs!$D$39/Inputs!$D$41*I7,0) -> 53.3866 | J67: =IF(AND(J$6>=Inputs!$D$40,J$6<Inputs!$D$40+Inputs!$D$41),Inputs!$D$39/Inputs!$D$41*J7,0) -> 0 | K67: =IF(AND(K$6>=Inputs!$D$40,K$6<Inputs!$D$40+Inputs!$D$41),Inputs!$D$39/Inputs!$D$41*K7,0) -> 0 | ... R67: =IF(AND(R$6>=Inputs!$D$40,R$6<Inputs!$D$40+Inputs!$D$41),Inputs!$D$39/Inputs!$D$41*R7,0) -> 0
A68: FCFF | B68: $mm | D68: =D49-D63-D22-D52-D53+D54-D66-D67 -> -494.3745 | E68: =E49-E63-E22-E52-E53+E54-E66-E67 -> -1908.3378 | F68: =F49-F63-F22-F52-F53+F54-F66-F67 -> -1345.8537 | G68: =G49-G63-G22-G52-G53+G54-G66-G67 -> -1112.7226 | H68: =H49-H63-H22-H52-H53+H54-H66-H67 -> -866.42058 | I68: =I49-I63-I22-I52-I53+I54-I66-I67 -> -100.14112 | J68: =J49-J63-J22-J52-J53+J54-J66-J67 -> 323.69126 | K68: =K49-K63-K22-K52-K53+K54-K66-K67 -> 112.57378 | ... R68: =R49-R63-R22-R52-R53+R54-R66-R67 -> 640.45085
A69: Cumulative FCFF from 1-Jul-2026 | B69: $mm | D69: =SUM($D$68:D68) -> -494.3745 | E69: =SUM($D$68:E68) -> -2402.7123 | F69: =SUM($D$68:F68) -> -3748.566 | G69: =SUM($D$68:G68) -> -4861.2886 | H69: =SUM($D$68:H68) -> -5727.7092 | I69: =SUM($D$68:I68) -> -5827.8503 | J69: =SUM($D$68:J68) -> -5504.1591 | K69: =SUM($D$68:K68) -> -5391.5853 | ... R69: =SUM($D$68:R68) -> -101.24406
A70: DISCOUNTING (mid-period, from valuation date)
A71: WACC | B71: % | D71: =WACC!D$21 -> 0.10349672 | E71: =WACC!E$21 -> 0.10349672 | F71: =WACC!F$21 -> 0.10349672 | G71: =WACC!G$21 -> 0.10349672 | H71: =WACC!H$21 -> 0.10349672 | I71: =WACC!I$21 -> 0.099312374 | J71: =WACC!J$21 -> 0.095128031 | K71: =WACC!K$21 -> 0.090943687 | ... R71: =WACC!R$21 -> 0.082575
A72: Compounding factor to period end | B72: f | D72: =(1+D71)^(D8+D7-Inputs!$D$6) -> 1.0310009 | E72: =D72*(1+E71)^E7 -> 1.1377061 | F72: =E72*(1+F71)^F7 -> 1.2554549 | G72: =F72*(1+G71)^G7 -> 1.3853904 | H72: =G72*(1+H71)^H7 -> 1.5287737 | I72: =H72*(1+I71)^I7 -> 1.6805999 | J72: =I72*(1+J71)^J7 -> 1.840472 | K72: =J72*(1+K71)^K7 -> 2.0078513 | L72: =K72*(1+L71)^L7 -> 2.1820512 | ... R72: =Q72*(1+R71)^R7 -> 3.5124722
A73: Discount factor (mid-period) | B73: f | D73: =1/(1+D71)^(D9-Inputs!$D$6) -> 0.99410839 | E73: =1/(D72*(1+E71)^(E7/2)) -> 0.92332682 | F73: =1/(E72*(1+F71)^(F7/2)) -> 0.8367282 | G73: =1/(F72*(1+G71)^(G7/2)) -> 0.75825165 | H73: =1/(G72*(1+H71)^(H7/2)) -> 0.68713539 | I73: =1/(H72*(1+I71)^(I7/2)) -> 0.62387306 | J73: =1/(I72*(1+J71)^(J7/2)) -> 0.56859525 | K73: =1/(J72*(1+K71)^(K7/2)) -> 0.52019912 | L73: =1/(K72*(1+L71)^(L7/2)) -> 0.47775117 | ... R73: =1/(Q72*(1+R71)^(R7/2)) -> 0.29622117
A74: PV of FCFF | B74: $mm | D74: =D68*D73 -> -491.46184 | E74: =E68*E73 -> -1762.0195 | F74: =F68*F73 -> -1126.1137 | G74: =G68*G73 -> -843.72376 | H74: =H68*H73 -> -595.34824 | I74: =I68*I73 -> -62.47535 | J74: =J68*J73 -> 184.04932 | K74: =K68*K73 -> 58.560783 | ... R74: =R68*R73 -> 189.7151
A75: TERMINAL VALUE & ENTERPRISE VALUE (col C)
A76: Terminal WACC | C76: =WACC!$C$16 -> 0.082575
A77: Terminal growth g | C77: =Inputs!$D$20 -> 0.025
A78: EBITDA 2041 (normalised) | C78: =R49*(1+C77) -> 1507.3059
A79: Normalised replacement satellite capex | C79: =Inputs!$E$63/ROUND(Inputs!$D$26,0)/(1-Inputs!$D$27)*R18*(1+C77) -> 447.75697
A80: Other capex 2041 | C80: =R52*(1+C77) -> 117.12874
A81: Normalised cash tax (tax dep = capex in steady state) | C81: =Inputs!$D$22*MAX(0,C78-C79-C80) -> 235.60506
A82: Increase in NWC 2041 | C82: =Inputs!$D$42*R37*C77 -> 4.0811407
A83: FCFF 2041 (normalised) | C83: =C78-C81-C79-C80-C82 -> 702.73403
A84: Terminal value at end-2040 (Gordon, mid-year consistent) | C84: =C83*(1+C76)^0.5/(C76-C77) -> 12699.483
A85: PV of terminal value | C85: =C84/R72 -> 3615.5397
A86: Sum of PV of explicit FCFF | C86: =SUM(D74:R74) -> -2726.2003
A87: ENTERPRISE VALUE | C87: =C86+C85 -> 889.33938
A88: Terminal value % of EV | C88: =IF(C87<=0,0,C85/C87) -> 4.0654218
A89: Implied terminal EV / EBITDA (2041) | C89: =IF(C78<=0,"n/m",C84/C78) -> 8.4252855
A90: EQUITY BRIDGE & DILUTION (col C)
A91: + Cash & liquid assets (pro forma) | C91: =Capital_Structure!$D$20 -> 3755.203
A92: - Non-convertible debt | C92: =Capital_Structure!$B$26 -> 468.638
A93: - Convertible notes at face (all treated as debt first) | C93: =Capital_Structure!$B$35 -> 3703.514
A94: Equity value before conversions | C94: =C87+C91-C92-C93 -> 472.39038
A95: Basic economic shares (mm) | C95: =Capital_Structure!$B$9 -> 389.16749
A96: Instrument | B96: Trigger K $ | C96: Shares mm | D96: D $mm | E96: Value/sh if prefix converts | F96: Converts? (1/0) | H96: Order-independent: instrument converts iff value with all K <= its K converting exceeds its K (R-07).
A97: =Capital_Structure!A48 -> 2032 4.25% converts | B97: =Capital_Structure!B48 -> 26.99 | C97: =Capital_Structure!C48 -> 0.13019637 | D97: =Capital_Structure!D48 -> 3.514 | E97: =($C$94+SUMIF($B$97:$B$106,"<="&B97,$D$97:$D$106))/($C$95+SUMIF($B$97:$B$106,"<="&B97,$C$97:$C$106)) -> 1.2382255 | F97: =IF(E97>B97,1,0) -> 0
A98: =Capital_Structure!A49 -> 2032 2.375% converts | B98: =Capital_Structure!B49 -> 72.07 | C98: =Capital_Structure!C49 -> 4.5095046 | D98: =Capital_Structure!D49 -> 325 | E98: =($C$94+SUMIF($B$97:$B$106,"<="&B98,$D$97:$D$106))/($C$95+SUMIF($B$97:$B$106,"<="&B98,$C$97:$C$106)) -> 2.019485 | F98: =IF(E98>B98,1,0) -> 0
A99: =Capital_Structure!A50 -> 2036 2.00% converts | B99: =Capital_Structure!B50 -> 96.3 | C99: =Capital_Structure!C50 -> 11.941848 | D99: =Capital_Structure!D50 -> 1150 | E99: =($C$94+SUMIF($B$97:$B$106,"<="&B99,$D$97:$D$106))/($C$95+SUMIF($B$97:$B$106,"<="&B99,$C$97:$C$106)) -> 4.6951299 | F99: =IF(E99>B99,1,0) -> 0
A100: =Capital_Structure!A51 -> 2036 2.25% converts | B100: =Capital_Structure!B51 -> 116.3 | C100: =Capital_Structure!C51 -> 9.2433362 | D100: =Capital_Structure!D51 -> 1075 | E100: =($C$94+SUMIF($B$97:$B$106,"<="&B100,$D$97:$D$106))/($C$95+SUMIF($B$97:$B$106,"<="&B100,$C$97:$C$106)) -> 7.0940189 | F100: =IF(E100>B100,1,0) -> 0
A101: =Capital_Structure!A52 -> 2034 1.625% converts (Jul-2026) | B101: =Capital_Structure!B52 -> 149.2 | C101: =Capital_Structure!C52 -> 14.452683 | D101: =Capital_Structure!D52 -> 2156.3403 | E101: =($C$94+SUMIF($B$97:$B$106,"<="&B101,$D$97:$D$106))/($C$95+SUMIF($B$97:$B$106,"<="&B101,$C$97:$C$106)) -> 11.714669 | F101: =IF(E101>B101,1,0) -> 0
A102: =Capital_Structure!A53 -> 2020 Plan stock options | B102: =Capital_Structure!B53 -> 9.2 | C102: =Capital_Structure!C53 -> 1.957612 | D102: =Capital_Structure!D53 -> 18.01003 | E102: =($C$94+SUMIF($B$97:$B$106,"<="&B102,$D$97:$D$106))/($C$95+SUMIF($B$97:$B$106,"<="&B102,$C$97:$C$106)) -> 1.226702 | F102: =IF(E102>B102,1,0) -> 0
...

Sheet Calc_Bull
A1: MODEL - BULL SCENARIO
A2: Live formulas. Inputs from 'Inputs' column G (scenario) / D (global). $mm unless stated. Periods: 2026H2 stub + 2027-2040; col S = 2041 normalised.
A5: Period | D5: 2026H2 | E5: 2027 | F5: 2028 | G5: 2029 | H5: 2030 | I5: 2031 | J5: 2032 | K5: 2033 | L5: 2034 | M5: 2035 | N5: 2036 | O5: 2037 | P5: 2038 | Q5: 2039 | R5: 2040 | S5: 2041N
A6: Calendar year | B6: yr | D6: 2026 | E6: 2027 | F6: 2028 | G6: 2029 | H6: 2030 | I6: 2031 | J6: 2032 | K6: 2033 | L6: 2034 | M6: 2035 | N6: 2036 | O6: 2037 | P6: 2038 | Q6: 2039 | R6: 2040 | S6: 2041
A7: Period length (years) | B7: yrs | D7: 0.5 | E7: 1 | F7: 1 | G7: 1 | H7: 1 | I7: 1 | J7: 1 | K7: 1 | L7: 1 | M7: 1 | N7: 1 | O7: 1 | P7: 1 | Q7: 1 | R7: 1
A8: Period start (year fraction) | B8: yrs | D8: 2026.5 | E8: 2027 | F8: 2028 | G8: 2029 | H8: 2030 | I8: 2031 | J8: 2032 | K8: 2033 | L8: 2034 | M8: 2035 | N8: 2036 | O8: 2037 | P8: 2038 | Q8: 2039 | R8: 2040
A9: Cash-flow timing (mid-period) | B9: yrs | D9: =D8+D7/2 -> 2026.75 | E9: =E8+E7/2 -> 2027.5 | F9: =F8+F7/2 -> 2028.5 | G9: =G8+G7/2 -> 2029.5 | H9: =H8+H7/2 -> 2030.5 | I9: =I8+I7/2 -> 2031.5 | J9: =J8+J7/2 -> 2032.5 | K9: =K8+K7/2 -> 2033.5 | ... R9: =R8+R7/2 -> 2040.5
A10: CONSTELLATION (Block 2 satellites)
A11: Target fleet, end of period | B11: # | D11: =IF(D$6=2026,Inputs!$G$59,IF(D$6=2027,Inputs!$G$60,IF(D$6=2028,Inputs!$G$61,IF(D$6=2029,Inputs!$G$62,Inputs!$G$63)))) -> 35 | E11: =IF(E$6=2026,Inputs!$G$59,IF(E$6=2027,Inputs!$G$60,IF(E$6=2028,Inputs!$G$61,IF(E$6=2029,Inputs!$G$62,Inputs!$G$63)))) -> 75 | F11: =IF(F$6=2026,Inputs!$G$59,IF(F$6=2027,Inputs!$G$60,IF(F$6=2028,Inputs!$G$61,IF(F$6=2029,Inputs!$G$62,Inputs!$G$63)))) -> 100 | G11: =IF(G$6=2026,Inputs!$G$59,IF(G$6=2027,Inputs!$G$60,IF(G$6=2028,Inputs!$G$61,IF(G$6=2029,Inputs!$G$62,Inputs!$G$63)))) -> 110 | H11: =IF(H$6=2026,Inputs!$G$59,IF(H$6=2027,Inputs!$G$60,IF(H$6=2028,Inputs!$G$61,IF(H$6=2029,Inputs!$G$62,Inputs!$G$63)))) -> 120 | I11: =IF(I$6=2026,Inputs!$G$59,IF(I$6=2027,Inputs!$G$60,IF(I$6=2028,Inputs!$G$61,IF(I$6=2029,Inputs!$G$62,Inputs!$G$63)))) -> 120 | J11: =IF(J$6=2026,Inputs!$G$59,IF(J$6=2027,Inputs!$G$60,IF(J$6=2028,Inputs!$G$61,IF(J$6=2029,Inputs!$G$62,Inputs!$G$63)))) -> 120 | K11: =IF(K$6=2026,Inputs!$G$59,IF(K$6=2027,Inputs!$G$60,IF(K$6=2028,Inputs!$G$61,IF(K$6=2029,Inputs!$G$62,Inputs!$G$63)))) -> 120 | ... R11: =IF(R$6=2026,Inputs!$G$59,IF(R$6=2027,Inputs!$G$60,IF(R$6=2028,Inputs!$G$61,IF(R$6=2029,Inputs!$G$62,Inputs!$G$63)))) -> 120
A12: Beginning fleet | B12: # | D12: =Inputs!$D$28 -> 4 | E12: =D15 -> 35 | F12: =E15 -> 75 | G12: =F15 -> 100 | H12: =G15 -> 110 | I12: =H15 -> 120 | J12: =I15 -> 120 | K12: =J15 -> 120 | L12: =K15 -> 120 | ... R12: =Q15 -> 120
A13: Retirements (end of design life) | B13: # | D13: =0 -> 0 | E13: =IF(E$6-ROUND(Inputs!$D$26,0)=2026,$D$14+Inputs!$D$28,IF(E$6-ROUND(Inputs!$D$26,0)>=2027,INDEX($D$14:D14,1,E$6-ROUND(Inputs!$D$26,0)-2026+1),0)) -> 0 | F13: =IF(F$6-ROUND(Inputs!$D$26,0)=2026,$D$14+Inputs!$D$28,IF(F$6-ROUND(Inputs!$D$26,0)>=2027,INDEX($D$14:E14,1,F$6-ROUND(Inputs!$D$26,0)-2026+1),0)) -> 0 | G13: =IF(G$6-ROUND(Inputs!$D$26,0)=2026,$D$14+Inputs!$D$28,IF(G$6-ROUND(Inputs!$D$26,0)>=2027,INDEX($D$14:F14,1,G$6-ROUND(Inputs!$D$26,0)-2026+1),0)) -> 0 | H13: =IF(H$6-ROUND(Inputs!$D$26,0)=2026,$D$14+Inputs!$D$28,IF(H$6-ROUND(Inputs!$D$26,0)>=2027,INDEX($D$14:G14,1,H$6-ROUND(Inputs!$D$26,0)-2026+1),0)) -> 0 | I13: =IF(I$6-ROUND(Inputs!$D$26,0)=2026,$D$14+Inputs!$D$28,IF(I$6-ROUND(Inputs!$D$26,0)>=2027,INDEX($D$14:H14,1,I$6-ROUND(Inputs!$D$26,0)-2026+1),0)) -> 0 | J13: =IF(J$6-ROUND(Inputs!$D$26,0)=2026,$D$14+Inputs!$D$28,IF(J$6-ROUND(Inputs!$D$26,0)>=2027,INDEX($D$14:I14,1,J$6-ROUND(Inputs!$D$26,0)-2026+1),0)) -> 0 | K13: =IF(K$6-ROUND(Inputs!$D$26,0)=2026,$D$14+Inputs!$D$28,IF(K$6-ROUND(Inputs!$D$26,0)>=2027,INDEX($D$14:J14,1,K$6-ROUND(Inputs!$D$26,0)-2026+1),0)) -> 35 | L13: =IF(L$6-ROUND(Inputs!$D$26,0)=2026,$D$14+Inputs!$D$28,IF(L$6-ROUND(Inputs!$D$26,0)>=2027,INDEX($D$14:K14,1,L$6-ROUND(Inputs!$D$26,0)-2026+1),0)) -> 40 | ... R13: =IF(R$6-ROUND(Inputs!$D$26,0)=2026,$D$14+Inputs!$D$28,IF(R$6-ROUND(Inputs!$D$26,0)>=2027,INDEX($D$14:Q14,1,R$6-ROUND(Inputs!$D$26,0)-2026+1),0)) -> 35
A14: Successful launches (net adds + replacements) | B14: # | D14: =MAX(0,D11-D12+D13) -> 31 | E14: =MAX(0,E11-E12+E13) -> 40 | F14: =MAX(0,F11-F12+F13) -> 25 | G14: =MAX(0,G11-G12+G13) -> 10 | H14: =MAX(0,H11-H12+H13) -> 10 | I14: =MAX(0,I11-I12+I13) -> 0 | J14: =MAX(0,J11-J12+J13) -> 0 | K14: =MAX(0,K11-K12+K13) -> 35 | ... R14: =MAX(0,R11-R12+R13) -> 35
A15: Ending fleet | B15: # | D15: =D12-D13+D14 -> 35 | E15: =E12-E13+E14 -> 75 | F15: =F12-F13+F14 -> 100 | G15: =G12-G13+G14 -> 110 | H15: =H12-H13+H14 -> 120 | I15: =I12-I13+I14 -> 120 | J15: =J12-J13+J14 -> 120 | K15: =K12-K13+K14 -> 120 | ... R15: =R12-R13+R14 -> 120
A16: Satellites built incl. launch losses | B16: # | D16: =D14/(1-Inputs!$D$27) -> 32.631579 | E16: =E14/(1-Inputs!$D$27) -> 42.105263 | F16: =F14/(1-Inputs!$D$27) -> 26.315789 | G16: =G14/(1-Inputs!$D$27) -> 10.526316 | H16: =H14/(1-Inputs!$D$27) -> 10.526316 | I16: =I14/(1-Inputs!$D$27) -> 0 | J16: =J14/(1-Inputs!$D$27) -> 0 | K16: =K14/(1-Inputs!$D$27) -> 36.842105 | ... R16: =R14/(1-Inputs!$D$27) -> 36.842105
A17: Average fleet in orbit | B17: # | D17: =(D12+D15)/2 -> 19.5 | E17: =(E12+E15)/2 -> 55 | F17: =(F12+F15)/2 -> 87.5 | G17: =(G12+G15)/2 -> 105 | H17: =(H12+H15)/2 -> 115 | I17: =(I12+I15)/2 -> 120 | J17: =(J12+J15)/2 -> 120 | K17: =(K12+K15)/2 -> 120 | ... R17: =(R12+R15)/2 -> 120
A18: Unit cost incl. launch ($mm/sat) | B18: $mm | D18: =Inputs!$G$64*(1+Inputs!$G$65)^MAX(0,D$6-2028) -> 21 | E18: =Inputs!$G$64*(1+Inputs!$G$65)^MAX(0,E$6-2028) -> 21 | F18: =Inputs!$G$64*(1+Inputs!$G$65)^MAX(0,F$6-2028) -> 21 | G18: =Inputs!$G$64*(1+Inputs!$G$65)^MAX(0,G$6-2028) -> 21.315 | H18: =Inputs!$G$64*(1+Inputs!$G$65)^MAX(0,H$6-2028) -> 21.634725 | I18: =Inputs!$G$64*(1+Inputs!$G$65)^MAX(0,I$6-2028) -> 21.959246 | J18: =Inputs!$G$64*(1+Inputs!$G$65)^MAX(0,J$6-2028) -> 22.288635 | K18: =Inputs!$G$64*(1+Inputs!$G$65)^MAX(0,K$6-2028) -> 22.622964 | ... R18: =Inputs!$G$64*(1+Inputs!$G$65)^MAX(0,R$6-2028) -> 25.107982
A19: Satellite capex (gross, placed in service) | B19: $mm | D19: =D16*D18 -> 685.26316 | E19: =E16*E18 -> 884.21053 | F19: =F16*F18 -> 552.63158 | G19: =G16*G18 -> 224.36842 | H19: =H16*H18 -> 227.73395 | I19: =I16*I18 -> 0 | J19: =J16*J18 -> 0 | K19: =K16*K18 -> 833.47762 | ... R19: =R16*R18 -> 925.0309
A20: CIP pre-funding pool (scalar, col C) | C20: =Inputs!$D$29*Inputs!$G$66 -> 1034.451
A21: CIP credit applied (already-paid capex) | B21: $mm | D21: =MIN(D19,$C$20) -> 685.26316 | E21: =MIN(E19,$C$20-SUM($D$21:D21)) -> 349.18784 | F21: =MIN(F19,$C$20-SUM($D$21:E21)) -> 0 | G21: =MIN(G19,$C$20-SUM($D$21:F21)) -> 0 | H21: =MIN(H19,$C$20-SUM($D$21:G21)) -> 0 | I21: =MIN(I19,$C$20-SUM($D$21:H21)) -> 0 | J21: =MIN(J19,$C$20-SUM($D$21:I21)) -> 0 | K21: =MIN(K19,$C$20-SUM($D$21:J21)) -> 0 | L21: =MIN(L19,$C$20-SUM($D$21:K21)) -> 0 | ... R21: =MIN(R19,$C$20-SUM($D$21:Q21)) -> 0
A22: Satellite capex, cash | B22: $mm | D22: =D19-D21 -> 0 | E22: =E19-E21 -> 535.02268 | F22: =F19-F21 -> 552.63158 | G22: =G19-G21 -> 224.36842 | H22: =H19-H21 -> 227.73395 | I22: =I19-I21 -> 0 | J22: =J19-J21 -> 0 | K22: =K19-K21 -> 833.47762 | ... R22: =R19-R21 -> 925.0309
A23: REVENUE BUILD
A24: Tier-1 coverage (fraction of partner base) | B24: % | D24: =MIN(1,MAX(0,(D17-Inputs!$D$32)/(Inputs!$D$33-Inputs!$D$32))) -> 0 | E24: =MIN(1,MAX(0,(E17-Inputs!$D$32)/(Inputs!$D$33-Inputs!$D$32))) -> 0.875 | F24: =MIN(1,MAX(0,(F17-Inputs!$D$32)/(Inputs!$D$33-Inputs!$D$32))) -> 1 | G24: =MIN(1,MAX(0,(G17-Inputs!$D$32)/(Inputs!$D$33-Inputs!$D$32))) -> 1 | H24: =MIN(1,MAX(0,(H17-Inputs!$D$32)/(Inputs!$D$33-Inputs!$D$32))) -> 1 | I24: =MIN(1,MAX(0,(I17-Inputs!$D$32)/(Inputs!$D$33-Inputs!$D$32))) -> 1 | J24: =MIN(1,MAX(0,(J17-Inputs!$D$32)/(Inputs!$D$33-Inputs!$D$32))) -> 1 | K24: =MIN(1,MAX(0,(K17-Inputs!$D$32)/(Inputs!$D$33-Inputs!$D$32))) -> 1 | ... R24: =MIN(1,MAX(0,(R17-Inputs!$D$32)/(Inputs!$D$33-Inputs!$D$32))) -> 1
A25: Tier-2 coverage | B25: % | D25: =MIN(1,MAX(0,(D17-Inputs!$D$34)/(Inputs!$D$35-Inputs!$D$34))) -> 0 | E25: =MIN(1,MAX(0,(E17-Inputs!$D$34)/(Inputs!$D$35-Inputs!$D$34))) -> 0 | F25: =MIN(1,MAX(0,(F17-Inputs!$D$34)/(Inputs!$D$35-Inputs!$D$34))) -> 0.91666667 | G25: =MIN(1,MAX(0,(G17-Inputs!$D$34)/(Inputs!$D$35-Inputs!$D$34))) -> 1 | H25: =MIN(1,MAX(0,(H17-Inputs!$D$34)/(Inputs!$D$35-Inputs!$D$34))) -> 1 | I25: =MIN(1,MAX(0,(I17-Inputs!$D$34)/(Inputs!$D$35-Inputs!$D$34))) -> 1 | J25: =MIN(1,MAX(0,(J17-Inputs!$D$34)/(Inputs!$D$35-Inputs!$D$34))) -> 1 | K25: =MIN(1,MAX(0,(K17-Inputs!$D$34)/(Inputs!$D$35-Inputs!$D$34))) -> 1 | ... R25: =MIN(1,MAX(0,(R17-Inputs!$D$34)/(Inputs!$D$35-Inputs!$D$34))) -> 1
A26: Logistic steepness k = 2 ln(19) / ramp (col C) | C26: =2*LN(19)/Inputs!$G$72 -> 1.1777756
A27: Tier-1 adoption (take rate of covered subs) | B27: % | D27: =IF(D9>=Inputs!$G$68,Inputs!$G$70/(1+EXP(-$C$26*(D9-(Inputs!$G$68+Inputs!$G$72/2)))),0) -> 0 | E27: =IF(E9>=Inputs!$G$68,Inputs!$G$70/(1+EXP(-$C$26*(E9-(Inputs!$G$68+Inputs!$G$72/2)))),0) -> 0.012993832 | F27: =IF(F9>=Inputs!$G$68,Inputs!$G$70/(1+EXP(-$C$26*(F9-(Inputs!$G$68+Inputs!$G$72/2)))),0) -> 0.035317858 | G27: =IF(G9>=Inputs!$G$68,Inputs!$G$70/(1+EXP(-$C$26*(G9-(Inputs!$G$68+Inputs!$G$72/2)))),0) -> 0.075 | H27: =IF(H9>=Inputs!$G$68,Inputs!$G$70/(1+EXP(-$C$26*(H9-(Inputs!$G$68+Inputs!$G$72/2)))),0) -> 0.11468214 | I27: =IF(I9>=Inputs!$G$68,Inputs!$G$70/(1+EXP(-$C$26*(I9-(Inputs!$G$68+Inputs!$G$72/2)))),0) -> 0.13700617 | J27: =IF(J9>=Inputs!$G$68,Inputs!$G$70/(1+EXP(-$C$26*(J9-(Inputs!$G$68+Inputs!$G$72/2)))),0) -> 0.14574319 | K27: =IF(K9>=Inputs!$G$68,Inputs!$G$70/(1+EXP(-$C$26*(K9-(Inputs!$G$68+Inputs!$G$72/2)))),0) -> 0.1486628 | ... R27: =IF(R9>=Inputs!$G$68,Inputs!$G$70/(1+EXP(-$C$26*(R9-(Inputs!$G$68+Inputs!$G$72/2)))),0) -> 0.14999965
A28: Tier-2 adoption (take rate of covered subs) | B28: % | D28: =IF(D9>=Inputs!$G$69,Inputs!$G$71/(1+EXP(-$C$26*(D9-(Inputs!$G$69+Inputs!$G$72/2)))),0) -> 0 | E28: =IF(E9>=Inputs!$G$69,Inputs!$G$71/(1+EXP(-$C$26*(E9-(Inputs!$G$69+Inputs!$G$72/2)))),0) -> 0 | F28: =IF(F9>=Inputs!$G$69,Inputs!$G$71/(1+EXP(-$C$26*(F9-(Inputs!$G$69+Inputs!$G$72/2)))),0) -> 0.0043312773 | G28: =IF(G9>=Inputs!$G$69,Inputs!$G$71/(1+EXP(-$C$26*(G9-(Inputs!$G$69+Inputs!$G$72/2)))),0) -> 0.011772619 | H28: =IF(H9>=Inputs!$G$69,Inputs!$G$71/(1+EXP(-$C$26*(H9-(Inputs!$G$69+Inputs!$G$72/2)))),0) -> 0.025 | I28: =IF(I9>=Inputs!$G$69,Inputs!$G$71/(1+EXP(-$C$26*(I9-(Inputs!$G$69+Inputs!$G$72/2)))),0) -> 0.038227381 | J28: =IF(J9>=Inputs!$G$69,Inputs!$G$71/(1+EXP(-$C$26*(J9-(Inputs!$G$69+Inputs!$G$72/2)))),0) -> 0.045668723 | K28: =IF(K9>=Inputs!$G$69,Inputs!$G$71/(1+EXP(-$C$26*(K9-(Inputs!$G$69+Inputs!$G$72/2)))),0) -> 0.048581064 | ... R28: =IF(R9>=Inputs!$G$69,Inputs!$G$71/(1+EXP(-$C$26*(R9-(Inputs!$G$69+Inputs!$G$72/2)))),0) -> 0.049999616
A29: MNO partner subscriber base (mm) | B29: mm | D29: =Inputs!$D$30*(1+Inputs!$D$51)^MAX(0,D$6-2026) -> 3000 | E29: =Inputs!$D$30*(1+Inputs!$D$51)^MAX(0,E$6-2026) -> 3030 | F29: =Inputs!$D$30*(1+Inputs!$D$51)^MAX(0,F$6-2026) -> 3060.3 | G29: =Inputs!$D$30*(1+Inputs!$D$51)^MAX(0,G$6-2026) -> 3090.903 | H29: =Inputs!$D$30*(1+Inputs!$D$51)^MAX(0,H$6-2026) -> 3121.812 | I29: =Inputs!$D$30*(1+Inputs!$D$51)^MAX(0,I$6-2026) -> 3153.0302 | J29: =Inputs!$D$30*(1+Inputs!$D$51)^MAX(0,J$6-2026) -> 3184.5605 | K29: =Inputs!$D$30*(1+Inputs!$D$51)^MAX(0,K$6-2026) -> 3216.4061 | ... R29: =Inputs!$D$30*(1+Inputs!$D$51)^MAX(0,R$6-2026) -> 3448.4226
A30: Tier-1 paying users (mm, period avg) | B30: mm | D30: =D29*Inputs!$D$31*D24*D27 -> 0 | E30: =E29*Inputs!$D$31*E24*E27 -> 8.6124741 | F30: =F29*Inputs!$D$31*F24*F27 -> 27.02081 | G30: =G29*Inputs!$D$31*G24*G27 -> 57.954431 | H30: =H29*Inputs!$D$31*H24*H27 -> 89.504023 | I30: =I29*Inputs!$D$31*I24*I27 -> 107.99614 | J30: =J29*Inputs!$D$31*J24*J27 -> 116.032 | K30: =K29*Inputs!$D$31*K24*K27 -> 119.53998 | ... R30: =R29*Inputs!$D$31*R24*R27 -> 129.31554
A31: Tier-2 paying users (mm, period avg) | B31: mm | D31: =D29*(1-Inputs!$D$31)*D25*D28 -> 0 | E31: =E29*(1-Inputs!$D$31)*E25*E28 -> 0 | F31: =F29*(1-Inputs!$D$31)*F25*F28 -> 9.1128178 | G31: =G29*(1-Inputs!$D$31)*G25*G28 -> 27.291018 | H31: =H29*(1-Inputs!$D$31)*H25*H28 -> 58.533976 | I31: =I29*(1-Inputs!$D$31)*I25*I28 -> 90.399063 | J31: =J29*(1-Inputs!$D$31)*J25*J28 -> 109.07611 | K31: =K29*(1-Inputs!$D$31)*K25*K28 -> 117.19232 | ... R31: =R29*(1-Inputs!$D$31)*R25*R28 -> 129.31486
A32: ARPU index (2027 = 1.00) | B32: x | D32: =(1+Inputs!$G$75)^MIN(MAX(0,D$6-2027),Inputs!$D$49-2027)*(1+Inputs!$D$50)^MAX(0,D$6-Inputs!$D$49) -> 1 | E32: =(1+Inputs!$G$75)^MIN(MAX(0,E$6-2027),Inputs!$D$49-2027)*(1+Inputs!$D$50)^MAX(0,E$6-Inputs!$D$49) -> 1 | F32: =(1+Inputs!$G$75)^MIN(MAX(0,F$6-2027),Inputs!$D$49-2027)*(1+Inputs!$D$50)^MAX(0,F$6-Inputs!$D$49) -> 1 | G32: =(1+Inputs!$G$75)^MIN(MAX(0,G$6-2027),Inputs!$D$49-2027)*(1+Inputs!$D$50)^MAX(0,G$6-Inputs!$D$49) -> 1 | H32: =(1+Inputs!$G$75)^MIN(MAX(0,H$6-2027),Inputs!$D$49-2027)*(1+Inputs!$D$50)^MAX(0,H$6-Inputs!$D$49) -> 1 | I32: =(1+Inputs!$G$75)^MIN(MAX(0,I$6-2027),Inputs!$D$49-2027)*(1+Inputs!$D$50)^MAX(0,I$6-Inputs!$D$49) -> 1 | J32: =(1+Inputs!$G$75)^MIN(MAX(0,J$6-2027),Inputs!$D$49-2027)*(1+Inputs!$D$50)^MAX(0,J$6-Inputs!$D$49) -> 1 | K32: =(1+Inputs!$G$75)^MIN(MAX(0,K$6-2027),Inputs!$D$49-2027)*(1+Inputs!$D$50)^MAX(0,K$6-Inputs!$D$49) -> 1.015 | ... R32: =(1+Inputs!$G$75)^MIN(MAX(0,R$6-2027),Inputs!$D$49-2027)*(1+Inputs!$D$50)^MAX(0,R$6-Inputs!$D$49) -> 1.1264926
A33: Tier-1 service revenue | B33: $mm | D33: =D30*Inputs!$G$73*D32*12*D7 -> 0 | E33: =E30*Inputs!$G$73*E32*12*E7 -> 620.09814 | F33: =F30*Inputs!$G$73*F32*12*F7 -> 1945.4983 | G33: =G30*Inputs!$G$73*G32*12*G7 -> 4172.719 | H33: =H30*Inputs!$G$73*H32*12*H7 -> 6444.2896 | I33: =I30*Inputs!$G$73*I32*12*I7 -> 7775.7224 | J33: =J30*Inputs!$G$73*J32*12*J7 -> 8354.3042 | K33: =K30*Inputs!$G$73*K32*12*K7 -> 8735.9819 | ... R33: =R30*Inputs!$G$73*R32*12*R7 -> 10488.456
A34: Tier-2 service revenue | B34: $mm | D34: =D31*Inputs!$G$74*D32*12*D7 -> 0 | E34: =E31*Inputs!$G$74*E32*12*E7 -> 0 | F34: =F31*Inputs!$G$74*F32*12*F7 -> 109.35381 | G34: =G31*Inputs!$G$74*G32*12*G7 -> 327.49222 | H34: =H31*Inputs!$G$74*H32*12*H7 -> 702.40771 | I34: =I31*Inputs!$G$74*I32*12*I7 -> 1084.7888 | J34: =J31*Inputs!$G$74*J32*12*J7 -> 1308.9133 | K34: =K31*Inputs!$G$74*K32*12*K7 -> 1427.4025 | ... R34: =R31*Inputs!$G$74*R32*12*R7 -> 1748.0667
A35: Government revenue | B35: $mm | D35: =IF(D$6=2026,Inputs!$G$78,IF(D$6=2027,Inputs!$G$79,IF(D$6=2028,Inputs!$G$80,IF(D$6=2029,Inputs!$G$81,Inputs!$G$82*(1+Inputs!$G$83)^(D$6-2030))))) -> 50 | E35: =IF(E$6=2026,Inputs!$G$78,IF(E$6=2027,Inputs!$G$79,IF(E$6=2028,Inputs!$G$80,IF(E$6=2029,Inputs!$G$81,Inputs!$G$82*(1+Inputs!$G$83)^(E$6-2030))))) -> 130 | F35: =IF(F$6=2026,Inputs!$G$78,IF(F$6=2027,Inputs!$G$79,IF(F$6=2028,Inputs!$G$80,IF(F$6=2029,Inputs!$G$81,Inputs!$G$82*(1+Inputs!$G$83)^(F$6-2030))))) -> 220 | G35: =IF(G$6=2026,Inputs!$G$78,IF(G$6=2027,Inputs!$G$79,IF(G$6=2028,Inputs!$G$80,IF(G$6=2029,Inputs!$G$81,Inputs!$G$82*(1+Inputs!$G$83)^(G$6-2030))))) -> 320 | H35: =IF(H$6=2026,Inputs!$G$78,IF(H$6=2027,Inputs!$G$79,IF(H$6=2028,Inputs!$G$80,IF(H$6=2029,Inputs!$G$81,Inputs!$G$82*(1+Inputs!$G$83)^(H$6-2030))))) -> 420 | I35: =IF(I$6=2026,Inputs!$G$78,IF(I$6=2027,Inputs!$G$79,IF(I$6=2028,Inputs!$G$80,IF(I$6=2029,Inputs!$G$81,Inputs!$G$82*(1+Inputs!$G$83)^(I$6-2030))))) -> 453.6 | J35: =IF(J$6=2026,Inputs!$G$78,IF(J$6=2027,Inputs!$G$79,IF(J$6=2028,Inputs!$G$80,IF(J$6=2029,Inputs!$G$81,Inputs!$G$82*(1+Inputs!$G$83)^(J$6-2030))))) -> 489.888 | K35: =IF(K$6=2026,Inputs!$G$78,IF(K$6=2027,Inputs!$G$79,IF(K$6=2028,Inputs!$G$80,IF(K$6=2029,Inputs!$G$81,Inputs!$G$82*(1+Inputs!$G$83)^(K$6-2030))))) -> 529.07904 | ... R35: =IF(R$6=2026,Inputs!$G$78,IF(R$6=2027,Inputs!$G$79,IF(R$6=2028,Inputs!$G$80,IF(R$6=2029,Inputs!$G$81,Inputs!$G$82*(1+Inputs!$G$83)^(R$6-2030))))) -> 906.7485
A36: Gateway / product revenue | B36: $mm | D36: =IF(D$6=2026,Inputs!$G$84,IF(D$6=2027,Inputs!$G$85,IF(D$6=2028,Inputs!$G$86,Inputs!$G$87))) -> 90 | E36: =IF(E$6=2026,Inputs!$G$84,IF(E$6=2027,Inputs!$G$85,IF(E$6=2028,Inputs!$G$86,Inputs!$G$87))) -> 150 | F36: =IF(F$6=2026,Inputs!$G$84,IF(F$6=2027,Inputs!$G$85,IF(F$6=2028,Inputs!$G$86,Inputs!$G$87))) -> 100 | G36: =IF(G$6=2026,Inputs!$G$84,IF(G$6=2027,Inputs!$G$85,IF(G$6=2028,Inputs!$G$86,Inputs!$G$87))) -> 50 | H36: =IF(H$6=2026,Inputs!$G$84,IF(H$6=2027,Inputs!$G$85,IF(H$6=2028,Inputs!$G$86,Inputs!$G$87))) -> 50 | I36: =IF(I$6=2026,Inputs!$G$84,IF(I$6=2027,Inputs!$G$85,IF(I$6=2028,Inputs!$G$86,Inputs!$G$87))) -> 50 | J36: =IF(J$6=2026,Inputs!$G$84,IF(J$6=2027,Inputs!$G$85,IF(J$6=2028,Inputs!$G$86,Inputs!$G$87))) -> 50 | K36: =IF(K$6=2026,Inputs!$G$84,IF(K$6=2027,Inputs!$G$85,IF(K$6=2028,Inputs!$G$86,Inputs!$G$87))) -> 50 | ... R36: =IF(R$6=2026,Inputs!$G$84,IF(R$6=2027,Inputs!$G$85,IF(R$6=2028,Inputs!$G$86,Inputs!$G$87))) -> 50
A37: Total revenue | B37: $mm | D37: =SUM(D33:D36) -> 140 | E37: =SUM(E33:E36) -> 900.09814 | F37: =SUM(F33:F36) -> 2374.8521 | G37: =SUM(G33:G36) -> 4870.2113 | H37: =SUM(H33:H36) -> 7616.6973 | I37: =SUM(I33:I36) -> 9364.1112 | J37: =SUM(J33:J36) -> 10203.105 | K37: =SUM(K33:K36) -> 10742.463 | ... R37: =SUM(R33:R36) -> 13193.271 | S37: =R37*(1+Inputs!$D$20) -> 13523.103
A38: Revenue growth (annualised) | B38: % | D38: =IF(Inputs!$D$36=0,0,(D37/D7)/(Inputs!$D$36/0.5)-1) -> 2.0266998 | E38: =IF(D37=0,0,(E37/E7)/(D37/D7)-1) -> 2.2146362 | F38: =IF(E37=0,0,(F37/F7)/(E37/E7)-1) -> 1.6384369 | G38: =IF(F37=0,0,(G37/G7)/(F37/F7)-1) -> 1.0507429 | H38: =IF(G37=0,0,(H37/H7)/(G37/G7)-1) -> 0.56393571 | I38: =IF(H37=0,0,(I37/I7)/(H37/H7)-1) -> 0.22941884 | J38: =IF(I37=0,0,(J37/J7)/(I37/I7)-1) -> 0.089596784 | K38: =IF(J37=0,0,(K37/K7)/(J37/J7)-1) -> 0.05286214 | L38: =IF(K37=0,0,(L37/L7)/(K37/K7)-1) -> 0.035638217 | ... R38: =IF(Q37=0,0,(R37/R7)/(Q37/Q7)-1) -> 0.028649145
A39: Paying users per satellite in orbit (mm) | B39: mm | D39: =IF(D17=0,0,(D30+D31)/D17) -> 0 | E39: =IF(E17=0,0,(E30+E31)/E17) -> 0.15659044 | F39: =IF(F17=0,0,(F30+F31)/F17) -> 0.41295575 | G39: =IF(G17=0,0,(G30+G31)/G17) -> 0.81186142 | H39: =IF(H17=0,0,(H30+H31)/H17) -> 1.2872869 | I39: =IF(I17=0,0,(I30+I31)/I17) -> 1.6532934 | J39: =IF(J17=0,0,(J30+J31)/J17) -> 1.8759009 | K39: =IF(K17=0,0,(K30+K31)/K17) -> 1.9727692 | ... R39: =IF(R17=0,0,(R30+R31)/R17) -> 2.1552533
A40: OPERATING COSTS & EBITDA
A41: Cost of revenue (gateway + government) | B41: $mm | D41: =D36*(1-Inputs!$D$52)+D35*Inputs!$D$53 -> 103 | E41: =E36*(1-Inputs!$D$52)+E35*Inputs!$D$53 -> 188 | F41: =F36*(1-Inputs!$D$52)+F35*Inputs!$D$53 -> 172 | G41: =G36*(1-Inputs!$D$52)+G35*Inputs!$D$53 -> 159.5 | H41: =H36*(1-Inputs!$D$52)+H35*Inputs!$D$53 -> 194.5 | I41: =I36*(1-Inputs!$D$52)+I35*Inputs!$D$53 -> 206.26 | J41: =J36*(1-Inputs!$D$52)+J35*Inputs!$D$53 -> 218.9608 | K41: =K36*(1-Inputs!$D$52)+K35*Inputs!$D$53 -> 232.67766 | ... R41: =R36*(1-Inputs!$D$52)+R35*Inputs!$D$53 -> 364.86197
A42: Service variable cost | B42: $mm | D42: =(D33+D34)*Inputs!$G$76 -> 0 | E42: =(E33+E34)*Inputs!$G$76 -> 68.210795 | F42: =(F33+F34)*Inputs!$G$76 -> 226.03374 | G42: =(G33+G34)*Inputs!$G$76 -> 495.02324 | H42: =(H33+H34)*Inputs!$G$76 -> 786.13671 | I42: =(I33+I34)*Inputs!$G$76 -> 974.65623 | J42: =(J33+J34)*Inputs!$G$76 -> 1062.9539 | K42: =(K33+K34)*Inputs!$G$76 -> 1117.9723 | ... R42: =(R33+R34)*Inputs!$G$76 -> 1346.0175
A43: Ligado revenue share | B43: $mm | D43: =D33*Inputs!$D$47 -> 0 | E43: =E33*Inputs!$D$47 -> 18.602944 | F43: =F33*Inputs!$D$47 -> 58.36495 | G43: =G33*Inputs!$D$47 -> 125.18157 | H43: =H33*Inputs!$D$47 -> 193.32869 | I43: =I33*Inputs!$D$47 -> 233.27167 | J43: =J33*Inputs!$D$47 -> 250.62912 | K43: =K33*Inputs!$D$47 -> 262.07946 | ... R43: =R33*Inputs!$D$47 -> 314.65368
A44: Spectrum usage payments | B44: $mm | D44: =IF(D$6>=Inputs!$D$45,Inputs!$D$46*D7,0) -> 0 | E44: =IF(E$6>=Inputs!$D$45,Inputs!$D$46*E7,0) -> 100 | F44: =IF(F$6>=Inputs!$D$45,Inputs!$D$46*F7,0) -> 100 | G44: =IF(G$6>=Inputs!$D$45,Inputs!$D$46*G7,0) -> 100 | H44: =IF(H$6>=Inputs!$D$45,Inputs!$D$46*H7,0) -> 100 | I44: =IF(I$6>=Inputs!$D$45,Inputs!$D$46*I7,0) -> 100 | J44: =IF(J$6>=Inputs!$D$45,Inputs!$D$46*J7,0) -> 100 | K44: =IF(K$6>=Inputs!$D$45,Inputs!$D$46*K7,0) -> 100 | ... R44: =IF(R$6>=Inputs!$D$45,Inputs!$D$46*R7,0) -> 100
A45: Fixed adj. opex (ex-COGS, ex-SBC) | B45: $mm | D45: =Inputs!$G$89 -> 205 | E45: =IF(E$6=2027,Inputs!$G$90,D45*(1+IF(E$6=2028,Inputs!$G$91,IF(E$6=2029,Inputs!$G$92,IF(E$6=2030,Inputs!$G$93,Inputs!$G$94))))) -> 450 | F45: =IF(F$6=2027,Inputs!$G$90,E45*(1+IF(F$6=2028,Inputs!$G$91,IF(F$6=2029,Inputs!$G$92,IF(F$6=2030,Inputs!$G$93,Inputs!$G$94))))) -> 504 | G45: =IF(G$6=2027,Inputs!$G$90,F45*(1+IF(G$6=2028,Inputs!$G$91,IF(G$6=2029,Inputs!$G$92,IF(G$6=2030,Inputs!$G$93,Inputs!$G$94))))) -> 554.4 | H45: =IF(H$6=2027,Inputs!$G$90,G45*(1+IF(H$6=2028,Inputs!$G$91,IF(H$6=2029,Inputs!$G$92,IF(H$6=2030,Inputs!$G$93,Inputs!$G$94))))) -> 598.752 | I45: =IF(I$6=2027,Inputs!$G$90,H45*(1+IF(I$6=2028,Inputs!$G$91,IF(I$6=2029,Inputs!$G$92,IF(I$6=2030,Inputs!$G$93,Inputs!$G$94))))) -> 619.70832 | J45: =IF(J$6=2027,Inputs!$G$90,I45*(1+IF(J$6=2028,Inputs!$G$91,IF(J$6=2029,Inputs!$G$92,IF(J$6=2030,Inputs!$G$93,Inputs!$G$94))))) -> 641.39811 | K45: =IF(K$6=2027,Inputs!$G$90,J45*(1+IF(K$6=2028,Inputs!$G$91,IF(K$6=2029,Inputs!$G$92,IF(K$6=2030,Inputs!$G$93,Inputs!$G$94))))) -> 663.84705 | L45: =IF(L$6=2027,Inputs!$G$90,K45*(1+IF(L$6=2028,Inputs!$G$91,IF(L$6=2029,Inputs!$G$92,IF(L$6=2030,Inputs!$G$93,Inputs!$G$94))))) -> 687.08169 | ... R45: =IF(R$6=2027,Inputs!$G$90,Q45*(1+IF(R$6=2028,Inputs!$G$91,IF(R$6=2029,Inputs!$G$92,IF(R$6=2030,Inputs!$G$93,Inputs!$G$94))))) -> 844.59883
A46: Network, ground & insurance opex | B46: $mm | D46: =D17*Inputs!$D$48*D7 -> 19.5 | E46: =E17*Inputs!$D$48*E7 -> 110 | F46: =F17*Inputs!$D$48*F7 -> 175 | G46: =G17*Inputs!$D$48*G7 -> 210 | H46: =H17*Inputs!$D$48*H7 -> 230 | I46: =I17*Inputs!$D$48*I7 -> 240 | J46: =J17*Inputs!$D$48*J7 -> 240 | K46: =K17*Inputs!$D$48*K7 -> 240 | ... R46: =R17*Inputs!$D$48*R7 -> 240
A47: Stock-based compensation (treated as cost) | B47: $mm | D47: =Inputs!$G$95 -> 120 | E47: =MAX(Inputs!$G$96*(1-Inputs!$G$97)^MAX(0,E$6-2027),Inputs!$G$98*E37) -> 230 | F47: =MAX(Inputs!$G$96*(1-Inputs!$G$97)^MAX(0,F$6-2027),Inputs!$G$98*F37) -> 202.4 | G47: =MAX(Inputs!$G$96*(1-Inputs!$G$97)^MAX(0,G$6-2027),Inputs!$G$98*G37) -> 178.112 | H47: =MAX(Inputs!$G$96*(1-Inputs!$G$97)^MAX(0,H$6-2027),Inputs!$G$98*H37) -> 228.50092 | I47: =MAX(Inputs!$G$96*(1-Inputs!$G$97)^MAX(0,I$6-2027),Inputs!$G$98*I37) -> 280.92334 | J47: =MAX(Inputs!$G$96*(1-Inputs!$G$97)^MAX(0,J$6-2027),Inputs!$G$98*J37) -> 306.09316 | K47: =MAX(Inputs!$G$96*(1-Inputs!$G$97)^MAX(0,K$6-2027),Inputs!$G$98*K37) -> 322.2739 | L47: =MAX(Inputs!$G$96*(1-Inputs!$G$97)^MAX(0,L$6-2027),Inputs!$G$98*L37) -> 333.75917 | ... R47: =MAX(Inputs!$G$96*(1-Inputs!$G$97)^MAX(0,R$6-2027),Inputs!$G$98*R37) -> 395.79814
A48: Total operating costs | B48: $mm | D48: =SUM(D41:D47) -> 447.5 | E48: =SUM(E41:E47) -> 1164.8137 | F48: =SUM(F41:F47) -> 1437.7987 | G48: =SUM(G41:G47) -> 1822.2168 | H48: =SUM(H41:H47) -> 2331.2183 | I48: =SUM(I41:I47) -> 2654.8196 | J48: =SUM(J41:J47) -> 2820.0351 | K48: =SUM(K41:K47) -> 2938.8504 | ... R48: =SUM(R41:R47) -> 3605.9301
A49: EBITDA (after SBC) | B49: $mm | D49: =D37-D48 -> -307.5 | E49: =E37-E48 -> -264.7156 | F49: =F37-F48 -> 937.05346 | G49: =G37-G48 -> 3047.9945 | H49: =H37-H48 -> 5285.479 | I49: =I37-I48 -> 6709.2916 | J49: =J37-J48 -> 7383.0703 | K49: =K37-K48 -> 7803.6131 | ... R49: =R37-R48 -> 9587.3412 | S49: =R49*(1+Inputs!$D$20) -> 9827.0247
A50: EBITDA margin | B50: % | D50: =IF(D37=0,0,D49/D37) -> -2.1964286 | E50: =IF(E37=0,0,E49/E37) -> -0.29409638 | F50: =IF(F37=0,0,F49/F37) -> 0.39457339 | G50: =IF(G37=0,0,G49/G37) -> 0.6258444 | H50: =IF(H37=0,0,H49/H37) -> 0.69393318 | I50: =IF(I37=0,0,I49/I37) -> 0.71648996 | J50: =IF(J37=0,0,J49/J37) -> 0.72361012 | K50: =IF(K37=0,0,K49/K37) -> 0.72642678 | ... R50: =IF(R37=0,0,R49/R37) -> 0.72668415
A51: CAPEX & OTHER INVESTING ITEMS
A52: Other capex (ground, facilities) | B52: $mm | D52: =IF(D$6=2026,Inputs!$G$100,IF(D$6=2027,Inputs!$G$101,IF(D$6=2028,Inputs!$G$102,MAX(Inputs!$G$104,Inputs!$G$103*D37)))) -> 150 | E52: =IF(E$6=2026,Inputs!$G$100,IF(E$6=2027,Inputs!$G$101,IF(E$6=2028,Inputs!$G$102,MAX(Inputs!$G$104,Inputs!$G$103*E37)))) -> 220 | F52: =IF(F$6=2026,Inputs!$G$100,IF(F$6=2027,Inputs!$G$101,IF(F$6=2028,Inputs!$G$102,MAX(Inputs!$G$104,Inputs!$G$103*F37)))) -> 180 | G52: =IF(G$6=2026,Inputs!$G$100,IF(G$6=2027,Inputs!$G$101,IF(G$6=2028,Inputs!$G$102,MAX(Inputs!$G$104,Inputs!$G$103*G37)))) -> 146.10634 | H52: =IF(H$6=2026,Inputs!$G$100,IF(H$6=2027,Inputs!$G$101,IF(H$6=2028,Inputs!$G$102,MAX(Inputs!$G$104,Inputs!$G$103*H37)))) -> 228.50092 | I52: =IF(I$6=2026,Inputs!$G$100,IF(I$6=2027,Inputs!$G$101,IF(I$6=2028,Inputs!$G$102,MAX(Inputs!$G$104,Inputs!$G$103*I37)))) -> 280.92334 | J52: =IF(J$6=2026,Inputs!$G$100,IF(J$6=2027,Inputs!$G$101,IF(J$6=2028,Inputs!$G$102,MAX(Inputs!$G$104,Inputs!$G$103*J37)))) -> 306.09316 | K52: =IF(K$6=2026,Inputs!$G$100,IF(K$6=2027,Inputs!$G$101,IF(K$6=2028,Inputs!$G$102,MAX(Inputs!$G$104,Inputs!$G$103*K37)))) -> 322.2739 | ... R52: =IF(R$6=2026,Inputs!$G$100,IF(R$6=2027,Inputs!$G$101,IF(R$6=2028,Inputs!$G$102,MAX(Inputs!$G$104,Inputs!$G$103*R37)))) -> 395.79814
A53: Ligado spectrum closing payment | B53: $mm | D53: =IF(D$6=Inputs!$D$45,Inputs!$D$44,0) -> 0 | E53: =IF(E$6=Inputs!$D$45,Inputs!$D$44,0) -> 550 | F53: =IF(F$6=Inputs!$D$45,Inputs!$D$44,0) -> 0 | G53: =IF(G$6=Inputs!$D$45,Inputs!$D$44,0) -> 0 | H53: =IF(H$6=Inputs!$D$45,Inputs!$D$44,0) -> 0 | I53: =IF(I$6=Inputs!$D$45,Inputs!$D$44,0) -> 0 | J53: =IF(J$6=Inputs!$D$45,Inputs!$D$44,0) -> 0 | K53: =IF(K$6=Inputs!$D$45,Inputs!$D$44,0) -> 0 | ... R53: =IF(R$6=Inputs!$D$45,Inputs!$D$44,0) -> 0
A54: J-LEO non-dilutive capital (inflow) | B54: $mm | D54: =IF(D$6=2028,Inputs!$G$105,0) -> 0 | E54: =IF(E$6=2028,Inputs!$G$105,0) -> 0 | F54: =IF(F$6=2028,Inputs!$G$105,0) -> 300 | G54: =IF(G$6=2028,Inputs!$G$105,0) -> 0 | H54: =IF(H$6=2028,Inputs!$G$105,0) -> 0 | I54: =IF(I$6=2028,Inputs!$G$105,0) -> 0 | J54: =IF(J$6=2028,Inputs!$G$105,0) -> 0 | K54: =IF(K$6=2028,Inputs!$G$105,0) -> 0 | ... R54: =IF(R$6=2028,Inputs!$G$105,0) -> 0
A55: CASH TAXES (NOL + depreciation)
A56: Tax-basis capex placed in service | B56: $mm | D56: =D19+D52 -> 835.26316 | E56: =E19+E52 -> 1104.2105 | F56: =F19+F52 -> 732.63158 | G56: =G19+G52 -> 370.47476 | H56: =H19+H52 -> 456.23487 | I56: =I19+I52 -> 280.92334 | J56: =J19+J52 -> 306.09316 | K56: =K19+K52 -> 1155.7515 | ... R56: =R19+R52 -> 1320.829
A57: Tax depreciation | B57: $mm | D57: =IF(Inputs!$D$25=1,D56,SUMIFS($D$56:D56,$D$6:D6,">"&(D$6-ROUND(Inputs!$D$26,0)))/ROUND(Inputs!$D$26,0)*D7) -> 835.26316 | E57: =IF(Inputs!$D$25=1,E56,SUMIFS($D$56:E56,$D$6:E6,">"&(E$6-ROUND(Inputs!$D$26,0)))/ROUND(Inputs!$D$26,0)*E7) -> 1104.2105 | F57: =IF(Inputs!$D$25=1,F56,SUMIFS($D$56:F56,$D$6:F6,">"&(F$6-ROUND(Inputs!$D$26,0)))/ROUND(Inputs!$D$26,0)*F7) -> 732.63158 | G57: =IF(Inputs!$D$25=1,G56,SUMIFS($D$56:G56,$D$6:G6,">"&(G$6-ROUND(Inputs!$D$26,0)))/ROUND(Inputs!$D$26,0)*G7) -> 370.47476 | H57: =IF(Inputs!$D$25=1,H56,SUMIFS($D$56:H56,$D$6:H6,">"&(H$6-ROUND(Inputs!$D$26,0)))/ROUND(Inputs!$D$26,0)*H7) -> 456.23487 | I57: =IF(Inputs!$D$25=1,I56,SUMIFS($D$56:I56,$D$6:I6,">"&(I$6-ROUND(Inputs!$D$26,0)))/ROUND(Inputs!$D$26,0)*I7) -> 280.92334 | J57: =IF(Inputs!$D$25=1,J56,SUMIFS($D$56:J56,$D$6:J6,">"&(J$6-ROUND(Inputs!$D$26,0)))/ROUND(Inputs!$D$26,0)*J7) -> 306.09316 | K57: =IF(Inputs!$D$25=1,K56,SUMIFS($D$56:K56,$D$6:K6,">"&(K$6-ROUND(Inputs!$D$26,0)))/ROUND(Inputs!$D$26,0)*K7) -> 1155.7515 | ... R57: =IF(Inputs!$D$25=1,R56,SUMIFS($D$56:R56,$D$6:R6,">"&(R$6-ROUND(Inputs!$D$26,0)))/ROUND(Inputs!$D$26,0)*R7) -> 1320.829
A58: Spectrum amortisation (15-yr, s.197) | B58: $mm | D58: =IF(AND(D$6>=Inputs!$D$45,D$6<Inputs!$D$45+15),Inputs!$D$44/15*D7,0) -> 0 | E58: =IF(AND(E$6>=Inputs!$D$45,E$6<Inputs!$D$45+15),Inputs!$D$44/15*E7,0) -> 36.666667 | F58: =IF(AND(F$6>=Inputs!$D$45,F$6<Inputs!$D$45+15),Inputs!$D$44/15*F7,0) -> 36.666667 | G58: =IF(AND(G$6>=Inputs!$D$45,G$6<Inputs!$D$45+15),Inputs!$D$44/15*G7,0) -> 36.666667 | H58: =IF(AND(H$6>=Inputs!$D$45,H$6<Inputs!$D$45+15),Inputs!$D$44/15*H7,0) -> 36.666667 | I58: =IF(AND(I$6>=Inputs!$D$45,I$6<Inputs!$D$45+15),Inputs!$D$44/15*I7,0) -> 36.666667 | J58: =IF(AND(J$6>=Inputs!$D$45,J$6<Inputs!$D$45+15),Inputs!$D$44/15*J7,0) -> 36.666667 | K58: =IF(AND(K$6>=Inputs!$D$45,K$6<Inputs!$D$45+15),Inputs!$D$44/15*K7,0) -> 36.666667 | ... R58: =IF(AND(R$6>=Inputs!$D$45,R$6<Inputs!$D$45+15),Inputs!$D$44/15*R7,0) -> 36.666667
A59: Taxable income | B59: $mm | D59: =D49-D57-D58 -> -1142.7632 | E59: =E49-E57-E58 -> -1405.5928 | F59: =F49-F57-F58 -> 167.75522 | G59: =G49-G57-G58 -> 2640.853 | H59: =H49-H57-H58 -> 4792.5775 | I59: =I49-I57-I58 -> 6391.7016 | J59: =J49-J57-J58 -> 7040.3105 | K59: =K49-K57-K58 -> 6611.1949 | ... R59: =R49-R57-R58 -> 8229.8455
A60: NOL pool - beginning | B60: $mm | D60: =Inputs!$D$23 -> 1000 | E60: =D62 -> 2142.7632 | F60: =E62 -> 3548.356 | G60: =F62 -> 3414.1518 | H60: =G62 -> 1301.4694 | I60: =H62 -> 0 | J60: =I62 -> 0 | K60: =J62 -> 0 | L60: =K62 -> 0 | ... R60: =Q62 -> 0
A61: NOL utilised (80% cap) | B61: $mm | D61: =MIN(D60,MAX(0,D59)*Inputs!$D$24) -> 0 | E61: =MIN(E60,MAX(0,E59)*Inputs!$D$24) -> 0 | F61: =MIN(F60,MAX(0,F59)*Inputs!$D$24) -> 134.20417 | G61: =MIN(G60,MAX(0,G59)*Inputs!$D$24) -> 2112.6824 | H61: =MIN(H60,MAX(0,H59)*Inputs!$D$24) -> 1301.4694 | I61: =MIN(I60,MAX(0,I59)*Inputs!$D$24) -> 0 | J61: =MIN(J60,MAX(0,J59)*Inputs!$D$24) -> 0 | K61: =MIN(K60,MAX(0,K59)*Inputs!$D$24) -> 0 | ... R61: =MIN(R60,MAX(0,R59)*Inputs!$D$24) -> 0
A62: NOL pool - ending | B62: $mm | D62: =D60-D61+MAX(0,-D59) -> 2142.7632 | E62: =E60-E61+MAX(0,-E59) -> 3548.356 | F62: =F60-F61+MAX(0,-F59) -> 3414.1518 | G62: =G60-G61+MAX(0,-G59) -> 1301.4694 | H62: =H60-H61+MAX(0,-H59) -> 0 | I62: =I60-I61+MAX(0,-I59) -> 0 | J62: =J60-J61+MAX(0,-J59) -> 0 | K62: =K60-K61+MAX(0,-K59) -> 0 | ... R62: =R60-R61+MAX(0,-R59) -> 0
A63: Cash taxes | B63: $mm | D63: =Inputs!$D$22*MAX(0,D59-D61) -> 0 | E63: =Inputs!$D$22*MAX(0,E59-E61) -> 0 | F63: =Inputs!$D$22*MAX(0,F59-F61) -> 8.3877608 | G63: =Inputs!$D$22*MAX(0,G59-G61) -> 132.04265 | H63: =Inputs!$D$22*MAX(0,H59-H61) -> 872.77703 | I63: =Inputs!$D$22*MAX(0,I59-I61) -> 1597.9254 | J63: =Inputs!$D$22*MAX(0,J59-J61) -> 1760.0776 | K63: =Inputs!$D$22*MAX(0,K59-K61) -> 1652.7987 | ... R63: =Inputs!$D$22*MAX(0,R59-R61) -> 2057.4614
A64: FREE CASH FLOW TO THE FIRM
A65: Annualised revenue | B65: $mm | D65: =D37/D7 -> 280 | E65: =E37/E7 -> 900.09814 | F65: =F37/F7 -> 2374.8521 | G65: =G37/G7 -> 4870.2113 | H65: =H37/H7 -> 7616.6973 | I65: =I37/I7 -> 9364.1112 | J65: =J37/J7 -> 10203.105 | K65: =K37/K7 -> 10742.463 | ... R65: =R37/R7 -> 13193.271
A66: Increase in net working capital | B66: $mm | D66: =Inputs!$D$42*(D65-Inputs!$D$43) -> 9.3745 | E66: =Inputs!$D$42*(E65-D65) -> 31.004907 | F66: =Inputs!$D$42*(F65-E65) -> 73.737701 | G66: =Inputs!$D$42*(G65-F65) -> 124.76796 | H66: =Inputs!$D$42*(H65-G65) -> 137.3243 | I66: =Inputs!$D$42*(I65-H65) -> 87.370692 | J66: =Inputs!$D$42*(J65-I65) -> 41.949712 | K66: =Inputs!$D$42*(K65-J65) -> 26.967899 | L66: =Inputs!$D$42*(L65-K65) -> 19.142112 | ... R66: =Inputs!$D$42*(R65-Q65) -> 18.372442
A67: Contract-liability unwind (revenue already paid in cash) | B67: $mm | D67: =IF(AND(D$6>=Inputs!$D$40,D$6<Inputs!$D$40+Inputs!$D$41),Inputs!$D$39/Inputs!$D$41*D7,0) -> 0 | E67: =IF(AND(E$6>=Inputs!$D$40,E$6<Inputs!$D$40+Inputs!$D$41),Inputs!$D$39/Inputs!$D$41*E7,0) -> 53.3866 | F67: =IF(AND(F$6>=Inputs!$D$40,F$6<Inputs!$D$40+Inputs!$D$41),Inputs!$D$39/Inputs!$D$41*F7,0) -> 53.3866 | G67: =IF(AND(G$6>=Inputs!$D$40,G$6<Inputs!$D$40+Inputs!$D$41),Inputs!$D$39/Inputs!$D$41*G7,0) -> 53.3866 | H67: =IF(AND(H$6>=Inputs!$D$40,H$6<Inputs!$D$40+Inputs!$D$41),Inputs!$D$39/Inputs!$D$41*H7,0) -> 53.3866 | I67: =IF(AND(I$6>=Inputs!$D$40,I$6<Inputs!$D$40+Inputs!$D$41),Inputs!$D$39/Inputs!$D$41*I7,0) -> 53.3866 | J67: =IF(AND(J$6>=Inputs!$D$40,J$6<Inputs!$D$40+Inputs!$D$41),Inputs!$D$39/Inputs!$D$41*J7,0) -> 0 | K67: =IF(AND(K$6>=Inputs!$D$40,K$6<Inputs!$D$40+Inputs!$D$41),Inputs!$D$39/Inputs!$D$41*K7,0) -> 0 | ... R67: =IF(AND(R$6>=Inputs!$D$40,R$6<Inputs!$D$40+Inputs!$D$41),Inputs!$D$39/Inputs!$D$41*R7,0) -> 0
A68: FCFF | B68: $mm | D68: =D49-D63-D22-D52-D53+D54-D66-D67 -> -466.8745 | E68: =E49-E63-E22-E52-E53+E54-E66-E67 -> -1654.1298 | F68: =F49-F63-F22-F52-F53+F54-F66-F67 -> 368.90982 | G68: =G49-G63-G22-G52-G53+G54-G66-G67 -> 2367.3225 | H68: =H49-H63-H22-H52-H53+H54-H66-H67 -> 3765.7562 | I68: =I49-I63-I22-I52-I53+I54-I66-I67 -> 4689.6856 | J68: =J49-J63-J22-J52-J53+J54-J66-J67 -> 5274.9498 | K68: =K49-K63-K22-K52-K53+K54-K66-K67 -> 4968.0949 | ... R68: =R49-R63-R22-R52-R53+R54-R66-R67 -> 6190.6783
A69: Cumulative FCFF from 1-Jul-2026 | B69: $mm | D69: =SUM($D$68:D68) -> -466.8745 | E69: =SUM($D$68:E68) -> -2121.0043 | F69: =SUM($D$68:F68) -> -1752.0945 | G69: =SUM($D$68:G68) -> 615.22802 | H69: =SUM($D$68:H68) -> 4380.9842 | I69: =SUM($D$68:I68) -> 9070.6698 | J69: =SUM($D$68:J68) -> 14345.62 | K69: =SUM($D$68:K68) -> 19313.715 | ... R69: =SUM($D$68:R68) -> 61443.48
A70: DISCOUNTING (mid-period, from valuation date)
A71: WACC | B71: % | D71: =WACC!D$21 -> 0.10349672 | E71: =WACC!E$21 -> 0.10349672 | F71: =WACC!F$21 -> 0.10349672 | G71: =WACC!G$21 -> 0.10349672 | H71: =WACC!H$21 -> 0.10349672 | I71: =WACC!I$21 -> 0.099312374 | J71: =WACC!J$21 -> 0.095128031 | K71: =WACC!K$21 -> 0.090943687 | ... R71: =WACC!R$21 -> 0.082575
A72: Compounding factor to period end | B72: f | D72: =(1+D71)^(D8+D7-Inputs!$D$6) -> 1.0310009 | E72: =D72*(1+E71)^E7 -> 1.1377061 | F72: =E72*(1+F71)^F7 -> 1.2554549 | G72: =F72*(1+G71)^G7 -> 1.3853904 | H72: =G72*(1+H71)^H7 -> 1.5287737 | I72: =H72*(1+I71)^I7 -> 1.6805999 | J72: =I72*(1+J71)^J7 -> 1.840472 | K72: =J72*(1+K71)^K7 -> 2.0078513 | L72: =K72*(1+L71)^L7 -> 2.1820512 | ... R72: =Q72*(1+R71)^R7 -> 3.5124722
A73: Discount factor (mid-period) | B73: f | D73: =1/(1+D71)^(D9-Inputs!$D$6) -> 0.99410839 | E73: =1/(D72*(1+E71)^(E7/2)) -> 0.92332682 | F73: =1/(E72*(1+F71)^(F7/2)) -> 0.8367282 | G73: =1/(F72*(1+G71)^(G7/2)) -> 0.75825165 | H73: =1/(G72*(1+H71)^(H7/2)) -> 0.68713539 | I73: =1/(H72*(1+I71)^(I7/2)) -> 0.62387306 | J73: =1/(I72*(1+J71)^(J7/2)) -> 0.56859525 | K73: =1/(J72*(1+K71)^(K7/2)) -> 0.52019912 | L73: =1/(K72*(1+L71)^(L7/2)) -> 0.47775117 | ... R73: =1/(Q72*(1+R71)^(R7/2)) -> 0.29622117
A74: PV of FCFF | B74: $mm | D74: =D68*D73 -> -464.12386 | E74: =E68*E73 -> -1527.3024 | F74: =F68*F73 -> 308.67725 | G74: =G68*G73 -> 1795.0262 | H74: =H68*H73 -> 2587.5844 | I74: =I68*I73 -> 2925.7685 | J74: =J68*J73 -> 2999.3114 | K74: =K68*K73 -> 2584.3986 | ... R74: =R68*R73 -> 1833.81
A75: TERMINAL VALUE & ENTERPRISE VALUE (col C)
A76: Terminal WACC | C76: =WACC!$C$16 -> 0.082575
A77: Terminal growth g | C77: =Inputs!$D$20 -> 0.025
A78: EBITDA 2041 (normalised) | C78: =R49*(1+C77) -> 9827.0247
A79: Normalised replacement satellite capex | C79: =Inputs!$G$63/ROUND(Inputs!$D$26,0)/(1-Inputs!$D$27)*R18*(1+C77) -> 464.40327
A80: Other capex 2041 | C80: =R52*(1+C77) -> 405.69309
A81: Normalised cash tax (tax dep = capex in steady state) | C81: =Inputs!$D$22*MAX(0,C78-C79-C80) -> 2239.2321
A82: Increase in NWC 2041 | C82: =Inputs!$D$42*R37*C77 -> 16.491589
A83: FCFF 2041 (normalised) | C83: =C78-C81-C79-C80-C82 -> 6701.2047
A84: Terminal value at end-2040 (Gordon, mid-year consistent) | C84: =C83*(1+C76)^0.5/(C76-C77) -> 121101.06
A85: PV of terminal value | C85: =C84/R72 -> 34477.442
A86: Sum of PV of explicit FCFF | C86: =SUM(D74:R74) -> 27054.94
A87: ENTERPRISE VALUE | C87: =C86+C85 -> 61532.382
A88: Terminal value % of EV | C88: =IF(C87<=0,0,C85/C87) -> 0.56031379
A89: Implied terminal EV / EBITDA (2041) | C89: =IF(C78<=0,"n/m",C84/C78) -> 12.323268
A90: EQUITY BRIDGE & DILUTION (col C)
A91: + Cash & liquid assets (pro forma) | C91: =Capital_Structure!$D$20 -> 3755.203
A92: - Non-convertible debt | C92: =Capital_Structure!$B$26 -> 468.638
A93: - Convertible notes at face (all treated as debt first) | C93: =Capital_Structure!$B$35 -> 3703.514
A94: Equity value before conversions | C94: =C87+C91-C92-C93 -> 61115.433
A95: Basic economic shares (mm) | C95: =Capital_Structure!$B$9 -> 389.16749
A96: Instrument | B96: Trigger K $ | C96: Shares mm | D96: D $mm | E96: Value/sh if prefix converts | F96: Converts? (1/0) | H96: Order-independent: instrument converts iff value with all K <= its K converting exceeds its K (R-07).
A97: =Capital_Structure!A48 -> 2032 4.25% converts | B97: =Capital_Structure!B48 -> 26.99 | C97: =Capital_Structure!C48 -> 0.13019637 | D97: =Capital_Structure!D48 -> 3.514 | E97: =($C$94+SUMIF($B$97:$B$106,"<="&B97,$D$97:$D$106))/($C$95+SUMIF($B$97:$B$106,"<="&B97,$C$97:$C$106)) -> 151.21919 | F97: =IF(E97>B97,1,0) -> 1
A98: =Capital_Structure!A49 -> 2032 2.375% converts | B98: =Capital_Structure!B49 -> 72.07 | C98: =Capital_Structure!C49 -> 4.5095046 | D98: =Capital_Structure!D49 -> 325 | E98: =($C$94+SUMIF($B$97:$B$106,"<="&B98,$D$97:$D$106))/($C$95+SUMIF($B$97:$B$106,"<="&B98,$C$97:$C$106)) -> 150.34619 | F98: =IF(E98>B98,1,0) -> 1
A99: =Capital_Structure!A50 -> 2036 2.00% converts | B99: =Capital_Structure!B50 -> 96.3 | C99: =Capital_Structure!C50 -> 11.941848 | D99: =Capital_Structure!D50 -> 1150 | E99: =($C$94+SUMIF($B$97:$B$106,"<="&B99,$D$97:$D$106))/($C$95+SUMIF($B$97:$B$106,"<="&B99,$C$97:$C$106)) -> 148.81238 | F99: =IF(E99>B99,1,0) -> 1
A100: =Capital_Structure!A51 -> 2036 2.25% converts | B100: =Capital_Structure!B51 -> 116.3 | C100: =Capital_Structure!C51 -> 9.2433362 | D100: =Capital_Structure!D51 -> 1075 | E100: =($C$94+SUMIF($B$97:$B$106,"<="&B100,$D$97:$D$106))/($C$95+SUMIF($B$97:$B$106,"<="&B100,$C$97:$C$106)) -> 148.11354 | F100: =IF(E100>B100,1,0) -> 1
A101: =Capital_Structure!A52 -> 2034 1.625% converts (Jul-2026) | B101: =Capital_Structure!B52 -> 149.2 | C101: =Capital_Structure!C52 -> 14.452683 | D101: =Capital_Structure!D52 -> 2156.3403 | E101: =($C$94+SUMIF($B$97:$B$106,"<="&B101,$D$97:$D$106))/($C$95+SUMIF($B$97:$B$106,"<="&B101,$C$97:$C$106)) -> 148.14887 | F101: =IF(E101>B101,1,0) -> 0
A102: =Capital_Structure!A53 -> 2020 Plan stock options | B102: =Capital_Structure!B53 -> 9.2 | C102: =Capital_Structure!C53 -> 1.957612 | D102: =Capital_Structure!D53 -> 18.01003 | E102: =($C$94+SUMIF($B$97:$B$106,"<="&B102,$D$97:$D$106))/($C$95+SUMIF($B$97:$B$106,"<="&B102,$C$97:$C$106)) -> 151.27666 | F102: =IF(E102>B102,1,0) -> 1
...

Sheet Calc_Distress
A1: MODEL - DISTRESS SCENARIO
A2: Live formulas. Inputs from 'Inputs' column D (scenario) / D (global). $mm unless stated. Periods: 2026H2 stub + 2027-2040; col S = 2041 normalised.
A5: Period | D5: 2026H2 | E5: 2027 | F5: 2028 | G5: 2029 | H5: 2030 | I5: 2031 | J5: 2032 | K5: 2033 | L5: 2034 | M5: 2035 | N5: 2036 | O5: 2037 | P5: 2038 | Q5: 2039 | R5: 2040 | S5: 2041N
A6: Calendar year | B6: yr | D6: 2026 | E6: 2027 | F6: 2028 | G6: 2029 | H6: 2030 | I6: 2031 | J6: 2032 | K6: 2033 | L6: 2034 | M6: 2035 | N6: 2036 | O6: 2037 | P6: 2038 | Q6: 2039 | R6: 2040 | S6: 2041
A7: Period length (years) | B7: yrs | D7: 0.5 | E7: 1 | F7: 1 | G7: 1 | H7: 1 | I7: 1 | J7: 1 | K7: 1 | L7: 1 | M7: 1 | N7: 1 | O7: 1 | P7: 1 | Q7: 1 | R7: 1
A8: Period start (year fraction) | B8: yrs | D8: 2026.5 | E8: 2027 | F8: 2028 | G8: 2029 | H8: 2030 | I8: 2031 | J8: 2032 | K8: 2033 | L8: 2034 | M8: 2035 | N8: 2036 | O8: 2037 | P8: 2038 | Q8: 2039 | R8: 2040
A9: Cash-flow timing (mid-period) | B9: yrs | D9: =D8+D7/2 -> 2026.75 | E9: =E8+E7/2 -> 2027.5 | F9: =F8+F7/2 -> 2028.5 | G9: =G8+G7/2 -> 2029.5 | H9: =H8+H7/2 -> 2030.5 | I9: =I8+I7/2 -> 2031.5 | J9: =J8+J7/2 -> 2032.5 | K9: =K8+K7/2 -> 2033.5 | ... R9: =R8+R7/2 -> 2040.5
A10: CONSTELLATION (Block 2 satellites)
A11: Target fleet, end of period | B11: # | D11: =IF(D$6=2026,Inputs!$D$59,IF(D$6=2027,Inputs!$D$60,IF(D$6=2028,Inputs!$D$61,IF(D$6=2029,Inputs!$D$62,Inputs!$D$63)))) -> 15 | E11: =IF(E$6=2026,Inputs!$D$59,IF(E$6=2027,Inputs!$D$60,IF(E$6=2028,Inputs!$D$61,IF(E$6=2029,Inputs!$D$62,Inputs!$D$63)))) -> 30 | F11: =IF(F$6=2026,Inputs!$D$59,IF(F$6=2027,Inputs!$D$60,IF(F$6=2028,Inputs!$D$61,IF(F$6=2029,Inputs!$D$62,Inputs!$D$63)))) -> 45 | G11: =IF(G$6=2026,Inputs!$D$59,IF(G$6=2027,Inputs!$D$60,IF(G$6=2028,Inputs!$D$61,IF(G$6=2029,Inputs!$D$62,Inputs!$D$63)))) -> 45 | H11: =IF(H$6=2026,Inputs!$D$59,IF(H$6=2027,Inputs!$D$60,IF(H$6=2028,Inputs!$D$61,IF(H$6=2029,Inputs!$D$62,Inputs!$D$63)))) -> 45 | I11: =IF(I$6=2026,Inputs!$D$59,IF(I$6=2027,Inputs!$D$60,IF(I$6=2028,Inputs!$D$61,IF(I$6=2029,Inputs!$D$62,Inputs!$D$63)))) -> 45 | J11: =IF(J$6=2026,Inputs!$D$59,IF(J$6=2027,Inputs!$D$60,IF(J$6=2028,Inputs!$D$61,IF(J$6=2029,Inputs!$D$62,Inputs!$D$63)))) -> 45 | K11: =IF(K$6=2026,Inputs!$D$59,IF(K$6=2027,Inputs!$D$60,IF(K$6=2028,Inputs!$D$61,IF(K$6=2029,Inputs!$D$62,Inputs!$D$63)))) -> 45 | ... R11: =IF(R$6=2026,Inputs!$D$59,IF(R$6=2027,Inputs!$D$60,IF(R$6=2028,Inputs!$D$61,IF(R$6=2029,Inputs!$D$62,Inputs!$D$63)))) -> 45
A12: Beginning fleet | B12: # | D12: =Inputs!$D$28 -> 4 | E12: =D15 -> 15 | F12: =E15 -> 30 | G12: =F15 -> 45 | H12: =G15 -> 45 | I12: =H15 -> 45 | J12: =I15 -> 45 | K12: =J15 -> 45 | L12: =K15 -> 45 | ... R12: =Q15 -> 45
A13: Retirements (end of design life) | B13: # | D13: =0 -> 0 | E13: =IF(E$6-ROUND(Inputs!$D$26,0)=2026,$D$14+Inputs!$D$28,IF(E$6-ROUND(Inputs!$D$26,0)>=2027,INDEX($D$14:D14,1,E$6-ROUND(Inputs!$D$26,0)-2026+1),0)) -> 0 | F13: =IF(F$6-ROUND(Inputs!$D$26,0)=2026,$D$14+Inputs!$D$28,IF(F$6-ROUND(Inputs!$D$26,0)>=2027,INDEX($D$14:E14,1,F$6-ROUND(Inputs!$D$26,0)-2026+1),0)) -> 0 | G13: =IF(G$6-ROUND(Inputs!$D$26,0)=2026,$D$14+Inputs!$D$28,IF(G$6-ROUND(Inputs!$D$26,0)>=2027,INDEX($D$14:F14,1,G$6-ROUND(Inputs!$D$26,0)-2026+1),0)) -> 0 | H13: =IF(H$6-ROUND(Inputs!$D$26,0)=2026,$D$14+Inputs!$D$28,IF(H$6-ROUND(Inputs!$D$26,0)>=2027,INDEX($D$14:G14,1,H$6-ROUND(Inputs!$D$26,0)-2026+1),0)) -> 0 | I13: =IF(I$6-ROUND(Inputs!$D$26,0)=2026,$D$14+Inputs!$D$28,IF(I$6-ROUND(Inputs!$D$26,0)>=2027,INDEX($D$14:H14,1,I$6-ROUND(Inputs!$D$26,0)-2026+1),0)) -> 0 | J13: =IF(J$6-ROUND(Inputs!$D$26,0)=2026,$D$14+Inputs!$D$28,IF(J$6-ROUND(Inputs!$D$26,0)>=2027,INDEX($D$14:I14,1,J$6-ROUND(Inputs!$D$26,0)-2026+1),0)) -> 0 | K13: =IF(K$6-ROUND(Inputs!$D$26,0)=2026,$D$14+Inputs!$D$28,IF(K$6-ROUND(Inputs!$D$26,0)>=2027,INDEX($D$14:J14,1,K$6-ROUND(Inputs!$D$26,0)-2026+1),0)) -> 15 | L13: =IF(L$6-ROUND(Inputs!$D$26,0)=2026,$D$14+Inputs!$D$28,IF(L$6-ROUND(Inputs!$D$26,0)>=2027,INDEX($D$14:K14,1,L$6-ROUND(Inputs!$D$26,0)-2026+1),0)) -> 15 | ... R13: =IF(R$6-ROUND(Inputs!$D$26,0)=2026,$D$14+Inputs!$D$28,IF(R$6-ROUND(Inputs!$D$26,0)>=2027,INDEX($D$14:Q14,1,R$6-ROUND(Inputs!$D$26,0)-2026+1),0)) -> 15
A14: Successful launches (net adds + replacements) | B14: # | D14: =MAX(0,D11-D12+D13) -> 11 | E14: =MAX(0,E11-E12+E13) -> 15 | F14: =MAX(0,F11-F12+F13) -> 15 | G14: =MAX(0,G11-G12+G13) -> 0 | H14: =MAX(0,H11-H12+H13) -> 0 | I14: =MAX(0,I11-I12+I13) -> 0 | J14: =MAX(0,J11-J12+J13) -> 0 | K14: =MAX(0,K11-K12+K13) -> 15 | ... R14: =MAX(0,R11-R12+R13) -> 15
A15: Ending fleet | B15: # | D15: =D12-D13+D14 -> 15 | E15: =E12-E13+E14 -> 30 | F15: =F12-F13+F14 -> 45 | G15: =G12-G13+G14 -> 45 | H15: =H12-H13+H14 -> 45 | I15: =I12-I13+I14 -> 45 | J15: =J12-J13+J14 -> 45 | K15: =K12-K13+K14 -> 45 | ... R15: =R12-R13+R14 -> 45
A16: Satellites built incl. launch losses | B16: # | D16: =D14/(1-Inputs!$D$27) -> 11.578947 | E16: =E14/(1-Inputs!$D$27) -> 15.789474 | F16: =F14/(1-Inputs!$D$27) -> 15.789474 | G16: =G14/(1-Inputs!$D$27) -> 0 | H16: =H14/(1-Inputs!$D$27) -> 0 | I16: =I14/(1-Inputs!$D$27) -> 0 | J16: =J14/(1-Inputs!$D$27) -> 0 | K16: =K14/(1-Inputs!$D$27) -> 15.789474 | ... R16: =R14/(1-Inputs!$D$27) -> 15.789474
A17: Average fleet in orbit | B17: # | D17: =(D12+D15)/2 -> 9.5 | E17: =(E12+E15)/2 -> 22.5 | F17: =(F12+F15)/2 -> 37.5 | G17: =(G12+G15)/2 -> 45 | H17: =(H12+H15)/2 -> 45 | I17: =(I12+I15)/2 -> 45 | J17: =(J12+J15)/2 -> 45 | K17: =(K12+K15)/2 -> 45 | ... R17: =(R12+R15)/2 -> 45
A18: Unit cost incl. launch ($mm/sat) | B18: $mm | D18: =Inputs!$D$64*(1+Inputs!$D$65)^MAX(0,D$6-2028) -> 25 | E18: =Inputs!$D$64*(1+Inputs!$D$65)^MAX(0,E$6-2028) -> 25 | F18: =Inputs!$D$64*(1+Inputs!$D$65)^MAX(0,F$6-2028) -> 25 | G18: =Inputs!$D$64*(1+Inputs!$D$65)^MAX(0,G$6-2028) -> 25.625 | H18: =Inputs!$D$64*(1+Inputs!$D$65)^MAX(0,H$6-2028) -> 26.265625 | I18: =Inputs!$D$64*(1+Inputs!$D$65)^MAX(0,I$6-2028) -> 26.922266 | J18: =Inputs!$D$64*(1+Inputs!$D$65)^MAX(0,J$6-2028) -> 27.595322 | K18: =Inputs!$D$64*(1+Inputs!$D$65)^MAX(0,K$6-2028) -> 28.285205 | ... R18: =Inputs!$D$64*(1+Inputs!$D$65)^MAX(0,R$6-2028) -> 33.622221
A19: Satellite capex (gross, placed in service) | B19: $mm | D19: =D16*D18 -> 289.47368 | E19: =E16*E18 -> 394.73684 | F19: =F16*F18 -> 394.73684 | G19: =G16*G18 -> 0 | H19: =H16*H18 -> 0 | I19: =I16*I18 -> 0 | J19: =J16*J18 -> 0 | K19: =K16*K18 -> 446.60851 | ... R19: =R16*R18 -> 530.87717
A20: CIP pre-funding pool (scalar, col C) | C20: =Inputs!$D$29*Inputs!$D$66 -> 689.634
A21: CIP credit applied (already-paid capex) | B21: $mm | D21: =MIN(D19,$C$20) -> 289.47368 | E21: =MIN(E19,$C$20-SUM($D$21:D21)) -> 394.73684 | F21: =MIN(F19,$C$20-SUM($D$21:E21)) -> 5.4234737 | G21: =MIN(G19,$C$20-SUM($D$21:F21)) -> 0 | H21: =MIN(H19,$C$20-SUM($D$21:G21)) -> 0 | I21: =MIN(I19,$C$20-SUM($D$21:H21)) -> 0 | J21: =MIN(J19,$C$20-SUM($D$21:I21)) -> 0 | K21: =MIN(K19,$C$20-SUM($D$21:J21)) -> 0 | L21: =MIN(L19,$C$20-SUM($D$21:K21)) -> 0 | ... R21: =MIN(R19,$C$20-SUM($D$21:Q21)) -> 0
A22: Satellite capex, cash | B22: $mm | D22: =D19-D21 -> 0 | E22: =E19-E21 -> 0 | F22: =F19-F21 -> 389.31337 | G22: =G19-G21 -> 0 | H22: =H19-H21 -> 0 | I22: =I19-I21 -> 0 | J22: =J19-J21 -> 0 | K22: =K19-K21 -> 446.60851 | ... R22: =R19-R21 -> 530.87717
A23: REVENUE BUILD
A24: Tier-1 coverage (fraction of partner base) | B24: % | D24: =MIN(1,MAX(0,(D17-Inputs!$D$32)/(Inputs!$D$33-Inputs!$D$32))) -> 0 | E24: =MIN(1,MAX(0,(E17-Inputs!$D$32)/(Inputs!$D$33-Inputs!$D$32))) -> 0.0625 | F24: =MIN(1,MAX(0,(F17-Inputs!$D$32)/(Inputs!$D$33-Inputs!$D$32))) -> 0.4375 | G24: =MIN(1,MAX(0,(G17-Inputs!$D$32)/(Inputs!$D$33-Inputs!$D$32))) -> 0.625 | H24: =MIN(1,MAX(0,(H17-Inputs!$D$32)/(Inputs!$D$33-Inputs!$D$32))) -> 0.625 | I24: =MIN(1,MAX(0,(I17-Inputs!$D$32)/(Inputs!$D$33-Inputs!$D$32))) -> 0.625 | J24: =MIN(1,MAX(0,(J17-Inputs!$D$32)/(Inputs!$D$33-Inputs!$D$32))) -> 0.625 | K24: =MIN(1,MAX(0,(K17-Inputs!$D$32)/(Inputs!$D$33-Inputs!$D$32))) -> 0.625 | ... R24: =MIN(1,MAX(0,(R17-Inputs!$D$32)/(Inputs!$D$33-Inputs!$D$32))) -> 0.625
A25: Tier-2 coverage | B25: % | D25: =MIN(1,MAX(0,(D17-Inputs!$D$34)/(Inputs!$D$35-Inputs!$D$34))) -> 0 | E25: =MIN(1,MAX(0,(E17-Inputs!$D$34)/(Inputs!$D$35-Inputs!$D$34))) -> 0 | F25: =MIN(1,MAX(0,(F17-Inputs!$D$34)/(Inputs!$D$35-Inputs!$D$34))) -> 0 | G25: =MIN(1,MAX(0,(G17-Inputs!$D$34)/(Inputs!$D$35-Inputs!$D$34))) -> 0 | H25: =MIN(1,MAX(0,(H17-Inputs!$D$34)/(Inputs!$D$35-Inputs!$D$34))) -> 0 | I25: =MIN(1,MAX(0,(I17-Inputs!$D$34)/(Inputs!$D$35-Inputs!$D$34))) -> 0 | J25: =MIN(1,MAX(0,(J17-Inputs!$D$34)/(Inputs!$D$35-Inputs!$D$34))) -> 0 | K25: =MIN(1,MAX(0,(K17-Inputs!$D$34)/(Inputs!$D$35-Inputs!$D$34))) -> 0 | ... R25: =MIN(1,MAX(0,(R17-Inputs!$D$34)/(Inputs!$D$35-Inputs!$D$34))) -> 0
A26: Logistic steepness k = 2 ln(19) / ramp (col C) | C26: =2*LN(19)/Inputs!$D$72 -> 0.73610974
A27: Tier-1 adoption (take rate of covered subs) | B27: % | D27: =IF(D9>=Inputs!$D$68,Inputs!$D$70/(1+EXP(-$C$26*(D9-(Inputs!$D$68+Inputs!$D$72/2)))),0) -> 0 | E27: =IF(E9>=Inputs!$D$68,Inputs!$D$70/(1+EXP(-$C$26*(E9-(Inputs!$D$68+Inputs!$D$72/2)))),0) -> 0 | F27: =IF(F9>=Inputs!$D$68,Inputs!$D$70/(1+EXP(-$C$26*(F9-(Inputs!$D$68+Inputs!$D$72/2)))),0) -> 0 | G27: =IF(G9>=Inputs!$D$68,Inputs!$D$70/(1+EXP(-$C$26*(G9-(Inputs!$D$68+Inputs!$D$72/2)))),0) -> 0.0021202155 | H27: =IF(H9>=Inputs!$D$68,Inputs!$D$70/(1+EXP(-$C$26*(H9-(Inputs!$D$68+Inputs!$D$72/2)))),0) -> 0.0041105654 | I27: =IF(I9>=Inputs!$D$68,Inputs!$D$70/(1+EXP(-$C$26*(I9-(Inputs!$D$68+Inputs!$D$72/2)))),0) -> 0.0074688115 | J27: =IF(J9>=Inputs!$D$68,Inputs!$D$70/(1+EXP(-$C$26*(J9-(Inputs!$D$68+Inputs!$D$72/2)))),0) -> 0.012270333 | K27: =IF(K9>=Inputs!$D$68,Inputs!$D$70/(1+EXP(-$C$26*(K9-(Inputs!$D$68+Inputs!$D$72/2)))),0) -> 0.017729667 | ... R27: =IF(R9>=Inputs!$D$68,Inputs!$D$70/(1+EXP(-$C$26*(R9-(Inputs!$D$68+Inputs!$D$72/2)))),0) -> 0.029880402
A28: Tier-2 adoption (take rate of covered subs) | B28: % | D28: =IF(D9>=Inputs!$D$69,Inputs!$D$71/(1+EXP(-$C$26*(D9-(Inputs!$D$69+Inputs!$D$72/2)))),0) -> 0 | E28: =IF(E9>=Inputs!$D$69,Inputs!$D$71/(1+EXP(-$C$26*(E9-(Inputs!$D$69+Inputs!$D$72/2)))),0) -> 0 | F28: =IF(F9>=Inputs!$D$69,Inputs!$D$71/(1+EXP(-$C$26*(F9-(Inputs!$D$69+Inputs!$D$72/2)))),0) -> 0 | G28: =IF(G9>=Inputs!$D$69,Inputs!$D$71/(1+EXP(-$C$26*(G9-(Inputs!$D$69+Inputs!$D$72/2)))),0) -> 0 | H28: =IF(H9>=Inputs!$D$69,Inputs!$D$71/(1+EXP(-$C$26*(H9-(Inputs!$D$69+Inputs!$D$72/2)))),0) -> 0 | I28: =IF(I9>=Inputs!$D$69,Inputs!$D$71/(1+EXP(-$C$26*(I9-(Inputs!$D$69+Inputs!$D$72/2)))),0) -> 0.00035336925 | J28: =IF(J9>=Inputs!$D$69,Inputs!$D$71/(1+EXP(-$C$26*(J9-(Inputs!$D$69+Inputs!$D$72/2)))),0) -> 0.00068509424 | K28: =IF(K9>=Inputs!$D$69,Inputs!$D$71/(1+EXP(-$C$26*(K9-(Inputs!$D$69+Inputs!$D$72/2)))),0) -> 0.0012448019 | ... R28: =IF(R9>=Inputs!$D$69,Inputs!$D$71/(1+EXP(-$C$26*(R9-(Inputs!$D$69+Inputs!$D$72/2)))),0) -> 0.0049142622
A29: MNO partner subscriber base (mm) | B29: mm | D29: =Inputs!$D$30*(1+Inputs!$D$51)^MAX(0,D$6-2026) -> 3000 | E29: =Inputs!$D$30*(1+Inputs!$D$51)^MAX(0,E$6-2026) -> 3030 | F29: =Inputs!$D$30*(1+Inputs!$D$51)^MAX(0,F$6-2026) -> 3060.3 | G29: =Inputs!$D$30*(1+Inputs!$D$51)^MAX(0,G$6-2026) -> 3090.903 | H29: =Inputs!$D$30*(1+Inputs!$D$51)^MAX(0,H$6-2026) -> 3121.812 | I29: =Inputs!$D$30*(1+Inputs!$D$51)^MAX(0,I$6-2026) -> 3153.0302 | J29: =Inputs!$D$30*(1+Inputs!$D$51)^MAX(0,J$6-2026) -> 3184.5605 | K29: =Inputs!$D$30*(1+Inputs!$D$51)^MAX(0,K$6-2026) -> 3216.4061 | ... R29: =Inputs!$D$30*(1+Inputs!$D$51)^MAX(0,R$6-2026) -> 3448.4226
A30: Tier-1 paying users (mm, period avg) | B30: mm | D30: =D29*Inputs!$D$31*D24*D27 -> 0 | E30: =E29*Inputs!$D$31*E24*E27 -> 0 | F30: =F29*Inputs!$D$31*F24*F27 -> 0 | G30: =G29*Inputs!$D$31*G24*G27 -> 1.0239657 | H30: =H29*Inputs!$D$31*H24*H27 -> 2.0050645 | I30: =I29*Inputs!$D$31*I24*I27 -> 3.6795919 | J30: =J29*Inputs!$D$31*J24*J27 -> 6.1055654 | K30: =K29*Inputs!$D$31*K24*K27 -> 8.9102823 | ... R30: =R29*Inputs!$D$31*R24*R27 -> 16.10004
A31: Tier-2 paying users (mm, period avg) | B31: mm | D31: =D29*(1-Inputs!$D$31)*D25*D28 -> 0 | E31: =E29*(1-Inputs!$D$31)*E25*E28 -> 0 | F31: =F29*(1-Inputs!$D$31)*F25*F28 -> 0 | G31: =G29*(1-Inputs!$D$31)*G25*G28 -> 0 | H31: =H29*(1-Inputs!$D$31)*H25*H28 -> 0 | I31: =I29*(1-Inputs!$D$31)*I25*I28 -> 0 | J31: =J29*(1-Inputs!$D$31)*J25*J28 -> 0 | K31: =K29*(1-Inputs!$D$31)*K25*K28 -> 0 | ... R31: =R29*(1-Inputs!$D$31)*R25*R28 -> 0
A32: ARPU index (2027 = 1.00) | B32: x | D32: =(1+Inputs!$D$75)^MIN(MAX(0,D$6-2027),Inputs!$D$49-2027)*(1+Inputs!$D$50)^MAX(0,D$6-Inputs!$D$49) -> 1 | E32: =(1+Inputs!$D$75)^MIN(MAX(0,E$6-2027),Inputs!$D$49-2027)*(1+Inputs!$D$50)^MAX(0,E$6-Inputs!$D$49) -> 1 | F32: =(1+Inputs!$D$75)^MIN(MAX(0,F$6-2027),Inputs!$D$49-2027)*(1+Inputs!$D$50)^MAX(0,F$6-Inputs!$D$49) -> 0.97 | G32: =(1+Inputs!$D$75)^MIN(MAX(0,G$6-2027),Inputs!$D$49-2027)*(1+Inputs!$D$50)^MAX(0,G$6-Inputs!$D$49) -> 0.9409 | H32: =(1+Inputs!$D$75)^MIN(MAX(0,H$6-2027),Inputs!$D$49-2027)*(1+Inputs!$D$50)^MAX(0,H$6-Inputs!$D$49) -> 0.912673 | I32: =(1+Inputs!$D$75)^MIN(MAX(0,I$6-2027),Inputs!$D$49-2027)*(1+Inputs!$D$50)^MAX(0,I$6-Inputs!$D$49) -> 0.88529281 | J32: =(1+Inputs!$D$75)^MIN(MAX(0,J$6-2027),Inputs!$D$49-2027)*(1+Inputs!$D$50)^MAX(0,J$6-Inputs!$D$49) -> 0.85873403 | K32: =(1+Inputs!$D$75)^MIN(MAX(0,K$6-2027),Inputs!$D$49-2027)*(1+Inputs!$D$50)^MAX(0,K$6-Inputs!$D$49) -> 0.87161504 | ... R32: =(1+Inputs!$D$75)^MIN(MAX(0,R$6-2027),Inputs!$D$49-2027)*(1+Inputs!$D$50)^MAX(0,R$6-Inputs!$D$49) -> 0.96735751
A33: Tier-1 service revenue | B33: $mm | D33: =D30*Inputs!$D$73*D32*12*D7 -> 0 | E33: =E30*Inputs!$D$73*E32*12*E7 -> 0 | F33: =F30*Inputs!$D$73*F32*12*F7 -> 0 | G33: =G30*Inputs!$D$73*G32*12*G7 -> 40.464872 | H33: =H30*Inputs!$D$73*H32*12*H7 -> 76.858665 | I33: =I30*Inputs!$D$73*I32*12*I7 -> 136.81568 | J33: =J30*Inputs!$D$73*J32*12*J7 -> 220.20838 | K33: =K30*Inputs!$D$73*K32*12*K7 -> 326.18611 | ... R33: =R30*Inputs!$D$73*R32*12*R7 -> 654.12877
A34: Tier-2 service revenue | B34: $mm | D34: =D31*Inputs!$D$74*D32*12*D7 -> 0 | E34: =E31*Inputs!$D$74*E32*12*E7 -> 0 | F34: =F31*Inputs!$D$74*F32*12*F7 -> 0 | G34: =G31*Inputs!$D$74*G32*12*G7 -> 0 | H34: =H31*Inputs!$D$74*H32*12*H7 -> 0 | I34: =I31*Inputs!$D$74*I32*12*I7 -> 0 | J34: =J31*Inputs!$D$74*J32*12*J7 -> 0 | K34: =K31*Inputs!$D$74*K32*12*K7 -> 0 | ... R34: =R31*Inputs!$D$74*R32*12*R7 -> 0
A35: Government revenue | B35: $mm | D35: =IF(D$6=2026,Inputs!$D$78,IF(D$6=2027,Inputs!$D$79,IF(D$6=2028,Inputs!$D$80,IF(D$6=2029,Inputs!$D$81,Inputs!$D$82*(1+Inputs!$D$83)^(D$6-2030))))) -> 35 | E35: =IF(E$6=2026,Inputs!$D$78,IF(E$6=2027,Inputs!$D$79,IF(E$6=2028,Inputs!$D$80,IF(E$6=2029,Inputs!$D$81,Inputs!$D$82*(1+Inputs!$D$83)^(E$6-2030))))) -> 60 | F35: =IF(F$6=2026,Inputs!$D$78,IF(F$6=2027,Inputs!$D$79,IF(F$6=2028,Inputs!$D$80,IF(F$6=2029,Inputs!$D$81,Inputs!$D$82*(1+Inputs!$D$83)^(F$6-2030))))) -> 80 | G35: =IF(G$6=2026,Inputs!$D$78,IF(G$6=2027,Inputs!$D$79,IF(G$6=2028,Inputs!$D$80,IF(G$6=2029,Inputs!$D$81,Inputs!$D$82*(1+Inputs!$D$83)^(G$6-2030))))) -> 90 | H35: =IF(H$6=2026,Inputs!$D$78,IF(H$6=2027,Inputs!$D$79,IF(H$6=2028,Inputs!$D$80,IF(H$6=2029,Inputs!$D$81,Inputs!$D$82*(1+Inputs!$D$83)^(H$6-2030))))) -> 100 | I35: =IF(I$6=2026,Inputs!$D$78,IF(I$6=2027,Inputs!$D$79,IF(I$6=2028,Inputs!$D$80,IF(I$6=2029,Inputs!$D$81,Inputs!$D$82*(1+Inputs!$D$83)^(I$6-2030))))) -> 102 | J35: =IF(J$6=2026,Inputs!$D$78,IF(J$6=2027,Inputs!$D$79,IF(J$6=2028,Inputs!$D$80,IF(J$6=2029,Inputs!$D$81,Inputs!$D$82*(1+Inputs!$D$83)^(J$6-2030))))) -> 104.04 | K35: =IF(K$6=2026,Inputs!$D$78,IF(K$6=2027,Inputs!$D$79,IF(K$6=2028,Inputs!$D$80,IF(K$6=2029,Inputs!$D$81,Inputs!$D$82*(1+Inputs!$D$83)^(K$6-2030))))) -> 106.1208 | ... R35: =IF(R$6=2026,Inputs!$D$78,IF(R$6=2027,Inputs!$D$79,IF(R$6=2028,Inputs!$D$80,IF(R$6=2029,Inputs!$D$81,Inputs!$D$82*(1+Inputs!$D$83)^(R$6-2030))))) -> 121.89944
A36: Gateway / product revenue | B36: $mm | D36: =IF(D$6=2026,Inputs!$D$84,IF(D$6=2027,Inputs!$D$85,IF(D$6=2028,Inputs!$D$86,Inputs!$D$87))) -> 70 | E36: =IF(E$6=2026,Inputs!$D$84,IF(E$6=2027,Inputs!$D$85,IF(E$6=2028,Inputs!$D$86,Inputs!$D$87))) -> 60 | F36: =IF(F$6=2026,Inputs!$D$84,IF(F$6=2027,Inputs!$D$85,IF(F$6=2028,Inputs!$D$86,Inputs!$D$87))) -> 30 | G36: =IF(G$6=2026,Inputs!$D$84,IF(G$6=2027,Inputs!$D$85,IF(G$6=2028,Inputs!$D$86,Inputs!$D$87))) -> 20 | H36: =IF(H$6=2026,Inputs!$D$84,IF(H$6=2027,Inputs!$D$85,IF(H$6=2028,Inputs!$D$86,Inputs!$D$87))) -> 20 | I36: =IF(I$6=2026,Inputs!$D$84,IF(I$6=2027,Inputs!$D$85,IF(I$6=2028,Inputs!$D$86,Inputs!$D$87))) -> 20 | J36: =IF(J$6=2026,Inputs!$D$84,IF(J$6=2027,Inputs!$D$85,IF(J$6=2028,Inputs!$D$86,Inputs!$D$87))) -> 20 | K36: =IF(K$6=2026,Inputs!$D$84,IF(K$6=2027,Inputs!$D$85,IF(K$6=2028,Inputs!$D$86,Inputs!$D$87))) -> 20 | ... R36: =IF(R$6=2026,Inputs!$D$84,IF(R$6=2027,Inputs!$D$85,IF(R$6=2028,Inputs!$D$86,Inputs!$D$87))) -> 20
A37: Total revenue | B37: $mm | D37: =SUM(D33:D36) -> 105 | E37: =SUM(E33:E36) -> 120 | F37: =SUM(F33:F36) -> 110 | G37: =SUM(G33:G36) -> 150.46487 | H37: =SUM(H33:H36) -> 196.85866 | I37: =SUM(I33:I36) -> 258.81568 | J37: =SUM(J33:J36) -> 344.24838 | K37: =SUM(K33:K36) -> 452.30691 | ... R37: =SUM(R33:R36) -> 796.02821 | S37: =R37*(1+Inputs!$D$20) -> 815.92892
A38: Revenue growth (annualised) | B38: % | D38: =IF(Inputs!$D$36=0,0,(D37/D7)/(Inputs!$D$36/0.5)-1) -> 1.2700249 | E38: =IF(D37=0,0,(E37/E7)/(D37/D7)-1) -> -0.42857143 | F38: =IF(E37=0,0,(F37/F7)/(E37/E7)-1) -> -0.083333333 | G38: =IF(F37=0,0,(G37/G7)/(F37/F7)-1) -> 0.36786247 | H38: =IF(G37=0,0,(H37/H7)/(G37/G7)-1) -> 0.30833637 | I38: =IF(H37=0,0,(I37/I7)/(H37/H7)-1) -> 0.31472842 | J38: =IF(I37=0,0,(J37/J7)/(I37/I7)-1) -> 0.33009091 | K38: =IF(J37=0,0,(K37/K7)/(J37/J7)-1) -> 0.31389698 | L38: =IF(K37=0,0,(L37/L7)/(K37/K7)-1) -> 0.22304527 | ... R38: =IF(Q37=0,0,(R37/R7)/(Q37/Q7)-1) -> 0.027351732
A39: Paying users per satellite in orbit (mm) | B39: mm | D39: =IF(D17=0,0,(D30+D31)/D17) -> 0 | E39: =IF(E17=0,0,(E30+E31)/E17) -> 0 | F39: =IF(F17=0,0,(F30+F31)/F17) -> 0 | G39: =IF(G17=0,0,(G30+G31)/G17) -> 0.022754794 | H39: =IF(H17=0,0,(H30+H31)/H17) -> 0.044556988 | I39: =IF(I17=0,0,(I30+I31)/I17) -> 0.081768708 | J39: =IF(J17=0,0,(J30+J31)/J17) -> 0.13567923 | K39: =IF(K17=0,0,(K30+K31)/K17) -> 0.19800627 | ... R39: =IF(R17=0,0,(R30+R31)/R17) -> 0.35777866
A40: OPERATING COSTS & EBITDA
A41: Cost of revenue (gateway + government) | B41: $mm | D41: =D36*(1-Inputs!$D$52)+D35*Inputs!$D$53 -> 78.75 | E41: =E36*(1-Inputs!$D$52)+E35*Inputs!$D$53 -> 78 | F41: =F36*(1-Inputs!$D$52)+F35*Inputs!$D$53 -> 56.5 | G41: =G36*(1-Inputs!$D$52)+G35*Inputs!$D$53 -> 50.5 | H41: =H36*(1-Inputs!$D$52)+H35*Inputs!$D$53 -> 54 | I41: =I36*(1-Inputs!$D$52)+I35*Inputs!$D$53 -> 54.7 | J41: =J36*(1-Inputs!$D$52)+J35*Inputs!$D$53 -> 55.414 | K41: =K36*(1-Inputs!$D$52)+K35*Inputs!$D$53 -> 56.14228 | ... R41: =R36*(1-Inputs!$D$52)+R35*Inputs!$D$53 -> 61.664805
A42: Service variable cost | B42: $mm | D42: =(D33+D34)*Inputs!$D$76 -> 0 | E42: =(E33+E34)*Inputs!$D$76 -> 0 | F42: =(F33+F34)*Inputs!$D$76 -> 0 | G42: =(G33+G34)*Inputs!$D$76 -> 6.0697308 | H42: =(H33+H34)*Inputs!$D$76 -> 11.5288 | I42: =(I33+I34)*Inputs!$D$76 -> 20.522352 | J42: =(J33+J34)*Inputs!$D$76 -> 33.031258 | K42: =(K33+K34)*Inputs!$D$76 -> 48.927917 | ... R42: =(R33+R34)*Inputs!$D$76 -> 98.119316
A43: Ligado revenue share | B43: $mm | D43: =D33*Inputs!$D$47 -> 0 | E43: =E33*Inputs!$D$47 -> 0 | F43: =F33*Inputs!$D$47 -> 0 | G43: =G33*Inputs!$D$47 -> 1.2139462 | H43: =H33*Inputs!$D$47 -> 2.3057599 | I43: =I33*Inputs!$D$47 -> 4.1044704 | J43: =J33*Inputs!$D$47 -> 6.6062515 | K43: =K33*Inputs!$D$47 -> 9.7855834 | ... R43: =R33*Inputs!$D$47 -> 19.623863
A44: Spectrum usage payments | B44: $mm | D44: =IF(D$6>=Inputs!$D$45,Inputs!$D$46*D7,0) -> 0 | E44: =IF(E$6>=Inputs!$D$45,Inputs!$D$46*E7,0) -> 100 | F44: =IF(F$6>=Inputs!$D$45,Inputs!$D$46*F7,0) -> 100 | G44: =IF(G$6>=Inputs!$D$45,Inputs!$D$46*G7,0) -> 100 | H44: =IF(H$6>=Inputs!$D$45,Inputs!$D$46*H7,0) -> 100 | I44: =IF(I$6>=Inputs!$D$45,Inputs!$D$46*I7,0) -> 100 | J44: =IF(J$6>=Inputs!$D$45,Inputs!$D$46*J7,0) -> 100 | K44: =IF(K$6>=Inputs!$D$45,Inputs!$D$46*K7,0) -> 100 | ... R44: =IF(R$6>=Inputs!$D$45,Inputs!$D$46*R7,0) -> 100
A45: Fixed adj. opex (ex-COGS, ex-SBC) | B45: $mm | D45: =Inputs!$D$89 -> 215 | E45: =IF(E$6=2027,Inputs!$D$90,D45*(1+IF(E$6=2028,Inputs!$D$91,IF(E$6=2029,Inputs!$D$92,IF(E$6=2030,Inputs!$D$93,Inputs!$D$94))))) -> 480 | F45: =IF(F$6=2027,Inputs!$D$90,E45*(1+IF(F$6=2028,Inputs!$D$91,IF(F$6=2029,Inputs!$D$92,IF(F$6=2030,Inputs!$D$93,Inputs!$D$94))))) -> 518.4 | G45: =IF(G$6=2027,Inputs!$D$90,F45*(1+IF(G$6=2028,Inputs!$D$91,IF(G$6=2029,Inputs!$D$92,IF(G$6=2030,Inputs!$D$93,Inputs!$D$94))))) -> 544.32 | H45: =IF(H$6=2027,Inputs!$D$90,G45*(1+IF(H$6=2028,Inputs!$D$91,IF(H$6=2029,Inputs!$D$92,IF(H$6=2030,Inputs!$D$93,Inputs!$D$94))))) -> 560.6496 | I45: =IF(I$6=2027,Inputs!$D$90,H45*(1+IF(I$6=2028,Inputs!$D$91,IF(I$6=2029,Inputs!$D$92,IF(I$6=2030,Inputs!$D$93,Inputs!$D$94))))) -> 580.27234 | J45: =IF(J$6=2027,Inputs!$D$90,I45*(1+IF(J$6=2028,Inputs!$D$91,IF(J$6=2029,Inputs!$D$92,IF(J$6=2030,Inputs!$D$93,Inputs!$D$94))))) -> 600.58187 | K45: =IF(K$6=2027,Inputs!$D$90,J45*(1+IF(K$6=2028,Inputs!$D$91,IF(K$6=2029,Inputs!$D$92,IF(K$6=2030,Inputs!$D$93,Inputs!$D$94))))) -> 621.60223 | L45: =IF(L$6=2027,Inputs!$D$90,K45*(1+IF(L$6=2028,Inputs!$D$91,IF(L$6=2029,Inputs!$D$92,IF(L$6=2030,Inputs!$D$93,Inputs!$D$94))))) -> 643.35831 | ... R45: =IF(R$6=2027,Inputs!$D$90,Q45*(1+IF(R$6=2028,Inputs!$D$91,IF(R$6=2029,Inputs!$D$92,IF(R$6=2030,Inputs!$D$93,Inputs!$D$94))))) -> 790.85163
A46: Network, ground & insurance opex | B46: $mm | D46: =D17*Inputs!$D$48*D7 -> 9.5 | E46: =E17*Inputs!$D$48*E7 -> 45 | F46: =F17*Inputs!$D$48*F7 -> 75 | G46: =G17*Inputs!$D$48*G7 -> 90 | H46: =H17*Inputs!$D$48*H7 -> 90 | I46: =I17*Inputs!$D$48*I7 -> 90 | J46: =J17*Inputs!$D$48*J7 -> 90 | K46: =K17*Inputs!$D$48*K7 -> 90 | ... R46: =R17*Inputs!$D$48*R7 -> 90
A47: Stock-based compensation (treated as cost) | B47: $mm | D47: =Inputs!$D$95 -> 125 | E47: =MAX(Inputs!$D$96*(1-Inputs!$D$97)^MAX(0,E$6-2027),Inputs!$D$98*E37) -> 250 | F47: =MAX(Inputs!$D$96*(1-Inputs!$D$97)^MAX(0,F$6-2027),Inputs!$D$98*F37) -> 230 | G47: =MAX(Inputs!$D$96*(1-Inputs!$D$97)^MAX(0,G$6-2027),Inputs!$D$98*G37) -> 211.6 | H47: =MAX(Inputs!$D$96*(1-Inputs!$D$97)^MAX(0,H$6-2027),Inputs!$D$98*H37) -> 194.672 | I47: =MAX(Inputs!$D$96*(1-Inputs!$D$97)^MAX(0,I$6-2027),Inputs!$D$98*I37) -> 179.09824 | J47: =MAX(Inputs!$D$96*(1-Inputs!$D$97)^MAX(0,J$6-2027),Inputs!$D$98*J37) -> 164.77038 | K47: =MAX(Inputs!$D$96*(1-Inputs!$D$97)^MAX(0,K$6-2027),Inputs!$D$98*K37) -> 151.58875 | L47: =MAX(Inputs!$D$96*(1-Inputs!$D$97)^MAX(0,L$6-2027),Inputs!$D$98*L37) -> 139.46165 | ... R47: =MAX(Inputs!$D$96*(1-Inputs!$D$97)^MAX(0,R$6-2027),Inputs!$D$98*R37) -> 84.563269
A48: Total operating costs | B48: $mm | D48: =SUM(D41:D47) -> 428.25 | E48: =SUM(E41:E47) -> 953 | F48: =SUM(F41:F47) -> 979.9 | G48: =SUM(G41:G47) -> 1003.7037 | H48: =SUM(H41:H47) -> 1013.1562 | I48: =SUM(I41:I47) -> 1028.6974 | J48: =SUM(J41:J47) -> 1050.4038 | K48: =SUM(K41:K47) -> 1078.0468 | ... R48: =SUM(R41:R47) -> 1244.8229
A49: EBITDA (after SBC) | B49: $mm | D49: =D37-D48 -> -323.25 | E49: =E37-E48 -> -833 | F49: =F37-F48 -> -869.9 | G49: =G37-G48 -> -853.2388 | H49: =H37-H48 -> -816.2975 | I49: =I37-I48 -> -769.88172 | J49: =J37-J48 -> -706.15537 | K49: =K37-K48 -> -625.73985 | ... R49: =R37-R48 -> -448.79467 | S49: =R49*(1+Inputs!$D$20) -> -460.01454
A50: EBITDA margin | B50: % | D50: =IF(D37=0,0,D49/D37) -> -3.0785714 | E50: =IF(E37=0,0,E49/E37) -> -6.9416667 | F50: =IF(F37=0,0,F49/F37) -> -7.9081818 | G50: =IF(G37=0,0,G49/G37) -> -5.6706844 | H50: =IF(H37=0,0,H49/H37) -> -4.1466171 | I50: =IF(I37=0,0,I49/I37) -> -2.9746332 | J50: =IF(J37=0,0,J49/J37) -> -2.0512961 | K50: =IF(K37=0,0,K49/K37) -> -1.3834408 | ... R50: =IF(R37=0,0,R49/R37) -> -0.56379242
A51: CAPEX & OTHER INVESTING ITEMS
A52: Other capex (ground, facilities) | B52: $mm | D52: =IF(D$6=2026,Inputs!$D$100,IF(D$6=2027,Inputs!$D$101,IF(D$6=2028,Inputs!$D$102,MAX(Inputs!$D$104,Inputs!$D$103*D37)))) -> 180 | E52: =IF(E$6=2026,Inputs!$D$100,IF(E$6=2027,Inputs!$D$101,IF(E$6=2028,Inputs!$D$102,MAX(Inputs!$D$104,Inputs!$D$103*E37)))) -> 250 | F52: =IF(F$6=2026,Inputs!$D$100,IF(F$6=2027,Inputs!$D$101,IF(F$6=2028,Inputs!$D$102,MAX(Inputs!$D$104,Inputs!$D$103*F37)))) -> 150 | G52: =IF(G$6=2026,Inputs!$D$100,IF(G$6=2027,Inputs!$D$101,IF(G$6=2028,Inputs!$D$102,MAX(Inputs!$D$104,Inputs!$D$103*G37)))) -> 60 | H52: =IF(H$6=2026,Inputs!$D$100,IF(H$6=2027,Inputs!$D$101,IF(H$6=2028,Inputs!$D$102,MAX(Inputs!$D$104,Inputs!$D$103*H37)))) -> 60 | I52: =IF(I$6=2026,Inputs!$D$100,IF(I$6=2027,Inputs!$D$101,IF(I$6=2028,Inputs!$D$102,MAX(Inputs!$D$104,Inputs!$D$103*I37)))) -> 60 | J52: =IF(J$6=2026,Inputs!$D$100,IF(J$6=2027,Inputs!$D$101,IF(J$6=2028,Inputs!$D$102,MAX(Inputs!$D$104,Inputs!$D$103*J37)))) -> 60 | K52: =IF(K$6=2026,Inputs!$D$100,IF(K$6=2027,Inputs!$D$101,IF(K$6=2028,Inputs!$D$102,MAX(Inputs!$D$104,Inputs!$D$103*K37)))) -> 60 | ... R52: =IF(R$6=2026,Inputs!$D$100,IF(R$6=2027,Inputs!$D$101,IF(R$6=2028,Inputs!$D$102,MAX(Inputs!$D$104,Inputs!$D$103*R37)))) -> 60
A53: Ligado spectrum closing payment | B53: $mm | D53: =IF(D$6=Inputs!$D$45,Inputs!$D$44,0) -> 0 | E53: =IF(E$6=Inputs!$D$45,Inputs!$D$44,0) -> 550 | F53: =IF(F$6=Inputs!$D$45,Inputs!$D$44,0) -> 0 | G53: =IF(G$6=Inputs!$D$45,Inputs!$D$44,0) -> 0 | H53: =IF(H$6=Inputs!$D$45,Inputs!$D$44,0) -> 0 | I53: =IF(I$6=Inputs!$D$45,Inputs!$D$44,0) -> 0 | J53: =IF(J$6=Inputs!$D$45,Inputs!$D$44,0) -> 0 | K53: =IF(K$6=Inputs!$D$45,Inputs!$D$44,0) -> 0 | ... R53: =IF(R$6=Inputs!$D$45,Inputs!$D$44,0) -> 0
A54: J-LEO non-dilutive capital (inflow) | B54: $mm | D54: =IF(D$6=2028,Inputs!$D$105,0) -> 0 | E54: =IF(E$6=2028,Inputs!$D$105,0) -> 0 | F54: =IF(F$6=2028,Inputs!$D$105,0) -> 0 | G54: =IF(G$6=2028,Inputs!$D$105,0) -> 0 | H54: =IF(H$6=2028,Inputs!$D$105,0) -> 0 | I54: =IF(I$6=2028,Inputs!$D$105,0) -> 0 | J54: =IF(J$6=2028,Inputs!$D$105,0) -> 0 | K54: =IF(K$6=2028,Inputs!$D$105,0) -> 0 | ... R54: =IF(R$6=2028,Inputs!$D$105,0) -> 0
A55: CASH TAXES (NOL + depreciation)
A56: Tax-basis capex placed in service | B56: $mm | D56: =D19+D52 -> 469.47368 | E56: =E19+E52 -> 644.73684 | F56: =F19+F52 -> 544.73684 | G56: =G19+G52 -> 60 | H56: =H19+H52 -> 60 | I56: =I19+I52 -> 60 | J56: =J19+J52 -> 60 | K56: =K19+K52 -> 506.60851 | ... R56: =R19+R52 -> 590.87717
A57: Tax depreciation | B57: $mm | D57: =IF(Inputs!$D$25=1,D56,SUMIFS($D$56:D56,$D$6:D6,">"&(D$6-ROUND(Inputs!$D$26,0)))/ROUND(Inputs!$D$26,0)*D7) -> 469.47368 | E57: =IF(Inputs!$D$25=1,E56,SUMIFS($D$56:E56,$D$6:E6,">"&(E$6-ROUND(Inputs!$D$26,0)))/ROUND(Inputs!$D$26,0)*E7) -> 644.73684 | F57: =IF(Inputs!$D$25=1,F56,SUMIFS($D$56:F56,$D$6:F6,">"&(F$6-ROUND(Inputs!$D$26,0)))/ROUND(Inputs!$D$26,0)*F7) -> 544.73684 | G57: =IF(Inputs!$D$25=1,G56,SUMIFS($D$56:G56,$D$6:G6,">"&(G$6-ROUND(Inputs!$D$26,0)))/ROUND(Inputs!$D$26,0)*G7) -> 60 | H57: =IF(Inputs!$D$25=1,H56,SUMIFS($D$56:H56,$D$6:H6,">"&(H$6-ROUND(Inputs!$D$26,0)))/ROUND(Inputs!$D$26,0)*H7) -> 60 | I57: =IF(Inputs!$D$25=1,I56,SUMIFS($D$56:I56,$D$6:I6,">"&(I$6-ROUND(Inputs!$D$26,0)))/ROUND(Inputs!$D$26,0)*I7) -> 60 | J57: =IF(Inputs!$D$25=1,J56,SUMIFS($D$56:J56,$D$6:J6,">"&(J$6-ROUND(Inputs!$D$26,0)))/ROUND(Inputs!$D$26,0)*J7) -> 60 | K57: =IF(Inputs!$D$25=1,K56,SUMIFS($D$56:K56,$D$6:K6,">"&(K$6-ROUND(Inputs!$D$26,0)))/ROUND(Inputs!$D$26,0)*K7) -> 506.60851 | ... R57: =IF(Inputs!$D$25=1,R56,SUMIFS($D$56:R56,$D$6:R6,">"&(R$6-ROUND(Inputs!$D$26,0)))/ROUND(Inputs!$D$26,0)*R7) -> 590.87717
A58: Spectrum amortisation (15-yr, s.197) | B58: $mm | D58: =IF(AND(D$6>=Inputs!$D$45,D$6<Inputs!$D$45+15),Inputs!$D$44/15*D7,0) -> 0 | E58: =IF(AND(E$6>=Inputs!$D$45,E$6<Inputs!$D$45+15),Inputs!$D$44/15*E7,0) -> 36.666667 | F58: =IF(AND(F$6>=Inputs!$D$45,F$6<Inputs!$D$45+15),Inputs!$D$44/15*F7,0) -> 36.666667 | G58: =IF(AND(G$6>=Inputs!$D$45,G$6<Inputs!$D$45+15),Inputs!$D$44/15*G7,0) -> 36.666667 | H58: =IF(AND(H$6>=Inputs!$D$45,H$6<Inputs!$D$45+15),Inputs!$D$44/15*H7,0) -> 36.666667 | I58: =IF(AND(I$6>=Inputs!$D$45,I$6<Inputs!$D$45+15),Inputs!$D$44/15*I7,0) -> 36.666667 | J58: =IF(AND(J$6>=Inputs!$D$45,J$6<Inputs!$D$45+15),Inputs!$D$44/15*J7,0) -> 36.666667 | K58: =IF(AND(K$6>=Inputs!$D$45,K$6<Inputs!$D$45+15),Inputs!$D$44/15*K7,0) -> 36.666667 | ... R58: =IF(AND(R$6>=Inputs!$D$45,R$6<Inputs!$D$45+15),Inputs!$D$44/15*R7,0) -> 36.666667
A59: Taxable income | B59: $mm | D59: =D49-D57-D58 -> -792.72368 | E59: =E49-E57-E58 -> -1514.4035 | F59: =F49-F57-F58 -> -1451.3035 | G59: =G49-G57-G58 -> -949.90547 | H59: =H49-H57-H58 -> -912.96416 | I59: =I49-I57-I58 -> -866.54838 | J59: =J49-J57-J58 -> -802.82204 | K59: =K49-K57-K58 -> -1169.015 | ... R59: =R49-R57-R58 -> -1076.3385
A60: NOL pool - beginning | B60: $mm | D60: =Inputs!$D$23 -> 1000 | E60: =D62 -> 1792.7237 | F60: =E62 -> 3307.1272 | G60: =F62 -> 4758.4307 | H60: =G62 -> 5708.3362 | I60: =H62 -> 6621.3003 | J60: =I62 -> 7487.8487 | K60: =J62 -> 8290.6708 | L60: =K62 -> 9459.6858 | ... R60: =Q62 -> 13838.207
A61: NOL utilised (80% cap) | B61: $mm | D61: =MIN(D60,MAX(0,D59)*Inputs!$D$24) -> 0 | E61: =MIN(E60,MAX(0,E59)*Inputs!$D$24) -> 0 | F61: =MIN(F60,MAX(0,F59)*Inputs!$D$24) -> 0 | G61: =MIN(G60,MAX(0,G59)*Inputs!$D$24) -> 0 | H61: =MIN(H60,MAX(0,H59)*Inputs!$D$24) -> 0 | I61: =MIN(I60,MAX(0,I59)*Inputs!$D$24) -> 0 | J61: =MIN(J60,MAX(0,J59)*Inputs!$D$24) -> 0 | K61: =MIN(K60,MAX(0,K59)*Inputs!$D$24) -> 0 | ... R61: =MIN(R60,MAX(0,R59)*Inputs!$D$24) -> 0
A62: NOL pool - ending | B62: $mm | D62: =D60-D61+MAX(0,-D59) -> 1792.7237 | E62: =E60-E61+MAX(0,-E59) -> 3307.1272 | F62: =F60-F61+MAX(0,-F59) -> 4758.4307 | G62: =G60-G61+MAX(0,-G59) -> 5708.3362 | H62: =H60-H61+MAX(0,-H59) -> 6621.3003 | I62: =I60-I61+MAX(0,-I59) -> 7487.8487 | J62: =J60-J61+MAX(0,-J59) -> 8290.6708 | K62: =K60-K61+MAX(0,-K59) -> 9459.6858 | ... R62: =R60-R61+MAX(0,-R59) -> 14914.545
A63: Cash taxes | B63: $mm | D63: =Inputs!$D$22*MAX(0,D59-D61) -> 0 | E63: =Inputs!$D$22*MAX(0,E59-E61) -> 0 | F63: =Inputs!$D$22*MAX(0,F59-F61) -> 0 | G63: =Inputs!$D$22*MAX(0,G59-G61) -> 0 | H63: =Inputs!$D$22*MAX(0,H59-H61) -> 0 | I63: =Inputs!$D$22*MAX(0,I59-I61) -> 0 | J63: =Inputs!$D$22*MAX(0,J59-J61) -> 0 | K63: =Inputs!$D$22*MAX(0,K59-K61) -> 0 | ... R63: =Inputs!$D$22*MAX(0,R59-R61) -> 0
A64: FREE CASH FLOW TO THE FIRM
A65: Annualised revenue | B65: $mm | D65: =D37/D7 -> 210 | E65: =E37/E7 -> 120 | F65: =F37/F7 -> 110 | G65: =G37/G7 -> 150.46487 | H65: =H37/H7 -> 196.85866 | I65: =I37/I7 -> 258.81568 | J65: =J37/J7 -> 344.24838 | K65: =K37/K7 -> 452.30691 | ... R65: =R37/R7 -> 796.02821
A66: Increase in net working capital | B66: $mm | D66: =Inputs!$D$42*(D65-Inputs!$D$43) -> 5.8745 | E66: =Inputs!$D$42*(E65-D65) -> -4.5 | F66: =Inputs!$D$42*(F65-E65) -> -0.5 | G66: =Inputs!$D$42*(G65-F65) -> 2.0232436 | H66: =Inputs!$D$42*(H65-G65) -> 2.3196896 | I66: =Inputs!$D$42*(I65-H65) -> 3.0978508 | J66: =Inputs!$D$42*(J65-I65) -> 4.2716352 | K66: =Inputs!$D$42*(K65-J65) -> 5.4029264 | L66: =Inputs!$D$42*(L65-K65) -> 5.0442459 | ... R66: =Inputs!$D$42*(R65-Q65) -> 1.0596542
A67: Contract-liability unwind (revenue already paid in cash) | B67: $mm | D67: =IF(AND(D$6>=Inputs!$D$40,D$6<Inputs!$D$40+Inputs!$D$41),Inputs!$D$39/Inputs!$D$41*D7,0) -> 0 | E67: =IF(AND(E$6>=Inputs!$D$40,E$6<Inputs!$D$40+Inputs!$D$41),Inputs!$D$39/Inputs!$D$41*E7,0) -> 53.3866 | F67: =IF(AND(F$6>=Inputs!$D$40,F$6<Inputs!$D$40+Inputs!$D$41),Inputs!$D$39/Inputs!$D$41*F7,0) -> 53.3866 | G67: =IF(AND(G$6>=Inputs!$D$40,G$6<Inputs!$D$40+Inputs!$D$41),Inputs!$D$39/Inputs!$D$41*G7,0) -> 53.3866 | H67: =IF(AND(H$6>=Inputs!$D$40,H$6<Inputs!$D$40+Inputs!$D$41),Inputs!$D$39/Inputs!$D$41*H7,0) -> 53.3866 | I67: =IF(AND(I$6>=Inputs!$D$40,I$6<Inputs!$D$40+Inputs!$D$41),Inputs!$D$39/Inputs!$D$41*I7,0) -> 53.3866 | J67: =IF(AND(J$6>=Inputs!$D$40,J$6<Inputs!$D$40+Inputs!$D$41),Inputs!$D$39/Inputs!$D$41*J7,0) -> 0 | K67: =IF(AND(K$6>=Inputs!$D$40,K$6<Inputs!$D$40+Inputs!$D$41),Inputs!$D$39/Inputs!$D$41*K7,0) -> 0 | ... R67: =IF(AND(R$6>=Inputs!$D$40,R$6<Inputs!$D$40+Inputs!$D$41),Inputs!$D$39/Inputs!$D$41*R7,0) -> 0
A68: FCFF | B68: $mm | D68: =D49-D63-D22-D52-D53+D54-D66-D67 -> -509.1245 | E68: =E49-E63-E22-E52-E53+E54-E66-E67 -> -1681.8866 | F68: =F49-F63-F22-F52-F53+F54-F66-F67 -> -1462.1 | G68: =G49-G63-G22-G52-G53+G54-G66-G67 -> -968.64865 | H68: =H49-H63-H22-H52-H53+H54-H66-H67 -> -932.00378 | I68: =I49-I63-I22-I52-I53+I54-I66-I67 -> -886.36617 | J68: =J49-J63-J22-J52-J53+J54-J66-J67 -> -770.42701 | K68: =K49-K63-K22-K52-K53+K54-K66-K67 -> -1137.7513 | ... R68: =R49-R63-R22-R52-R53+R54-R66-R67 -> -1040.7315
A69: Cumulative FCFF from 1-Jul-2026 | B69: $mm | D69: =SUM($D$68:D68) -> -509.1245 | E69: =SUM($D$68:E68) -> -2191.0111 | F69: =SUM($D$68:F68) -> -3653.1111 | G69: =SUM($D$68:G68) -> -4621.7597 | H69: =SUM($D$68:H68) -> -5553.7635 | I69: =SUM($D$68:I68) -> -6440.1297 | J69: =SUM($D$68:J68) -> -7210.5567 | K69: =SUM($D$68:K68) -> -8348.308 | ... R69: =SUM($D$68:R68) -> -13563.687
A70: DISCOUNTING (mid-period, from valuation date)
A71: WACC | B71: % | D71: =WACC!D$21 -> 0.10349672 | E71: =WACC!E$21 -> 0.10349672 | F71: =WACC!F$21 -> 0.10349672 | G71: =WACC!G$21 -> 0.10349672 | H71: =WACC!H$21 -> 0.10349672 | I71: =WACC!I$21 -> 0.099312374 | J71: =WACC!J$21 -> 0.095128031 | K71: =WACC!K$21 -> 0.090943687 | ... R71: =WACC!R$21 -> 0.082575
A72: Compounding factor to period end | B72: f | D72: =(1+D71)^(D8+D7-Inputs!$D$6) -> 1.0310009 | E72: =D72*(1+E71)^E7 -> 1.1377061 | F72: =E72*(1+F71)^F7 -> 1.2554549 | G72: =F72*(1+G71)^G7 -> 1.3853904 | H72: =G72*(1+H71)^H7 -> 1.5287737 | I72: =H72*(1+I71)^I7 -> 1.6805999 | J72: =I72*(1+J71)^J7 -> 1.840472 | K72: =J72*(1+K71)^K7 -> 2.0078513 | L72: =K72*(1+L71)^L7 -> 2.1820512 | ... R72: =Q72*(1+R71)^R7 -> 3.5124722
A73: Discount factor (mid-period) | B73: f | D73: =1/(1+D71)^(D9-Inputs!$D$6) -> 0.99410839 | E73: =1/(D72*(1+E71)^(E7/2)) -> 0.92332682 | F73: =1/(E72*(1+F71)^(F7/2)) -> 0.8367282 | G73: =1/(F72*(1+G71)^(G7/2)) -> 0.75825165 | H73: =1/(G72*(1+H71)^(H7/2)) -> 0.68713539 | I73: =1/(H72*(1+I71)^(I7/2)) -> 0.62387306 | J73: =1/(I72*(1+J71)^(J7/2)) -> 0.56859525 | K73: =1/(J72*(1+K71)^(K7/2)) -> 0.52019912 | L73: =1/(K72*(1+L71)^(L7/2)) -> 0.47775117 | ... R73: =1/(Q72*(1+R71)^(R7/2)) -> 0.29622117
A74: PV of FCFF | B74: $mm | D74: =D68*D73 -> -506.12493 | E74: =E68*E73 -> -1552.931 | F74: =F68*F73 -> -1223.3803 | G74: =G68*G73 -> -734.47943 | H74: =H68*H73 -> -640.41278 | I74: =I68*I73 -> -552.97998 | J74: =J68*J73 -> -438.06114 | K74: =K68*K73 -> -591.85722 | ... R74: =R68*R73 -> -308.28671
A75: TERMINAL VALUE & ENTERPRISE VALUE (col C)
A76: Terminal WACC | C76: =WACC!$C$16 -> 0.082575
A77: Terminal growth g | C77: =Inputs!$D$20 -> 0.025
A78: EBITDA 2041 (normalised) | C78: =R49*(1+C77) -> -460.01454
A79: Normalised replacement satellite capex | C79: =Inputs!$D$63/ROUND(Inputs!$D$26,0)/(1-Inputs!$D$27)*R18*(1+C77) -> 233.20676
A80: Other capex 2041 | C80: =R52*(1+C77) -> 61.5
A81: Normalised cash tax (tax dep = capex in steady state) | C81: =Inputs!$D$22*MAX(0,C78-C79-C80) -> 0
A82: Increase in NWC 2041 | C82: =Inputs!$D$42*R37*C77 -> 0.99503527
A83: FCFF 2041 (normalised) | C83: =C78-C81-C79-C80-C82 -> -755.71633
A84: Terminal value at end-2040 (Gordon, mid-year consistent) | C84: =C83*(1+C76)^0.5/(C76-C77) -> -13656.954
A85: PV of terminal value | C85: =C84/R72 -> -3888.1316
A86: Sum of PV of explicit FCFF | C86: =SUM(D74:R74) -> -8267.9018
A87: ENTERPRISE VALUE | C87: =C86+C85 -> -12156.033
A88: Terminal value % of EV | C88: =IF(C87<=0,0,C85/C87) -> 0
A89: Implied terminal EV / EBITDA (2041) | C89: =IF(C78<=0,"n/m",C84/C78) -> n/m
A90: EQUITY BRIDGE & DILUTION (col C)
A91: + Cash & liquid assets (pro forma) | C91: =Capital_Structure!$D$20 -> 3755.203
A92: - Non-convertible debt | C92: =Capital_Structure!$B$26 -> 468.638
A93: - Convertible notes at face (all treated as debt first) | C93: =Capital_Structure!$B$35 -> 3703.514
A94: Equity value before conversions | C94: =C87+C91-C92-C93 -> -12572.982
A95: Basic economic shares (mm) | C95: =Capital_Structure!$B$9 -> 389.16749
A96: Instrument | B96: Trigger K $ | C96: Shares mm | D96: D $mm | E96: Value/sh if prefix converts | F96: Converts? (1/0) | H96: Order-independent: instrument converts iff value with all K <= its K converting exceeds its K (R-07).
A97: =Capital_Structure!A48 -> 2032 4.25% converts | B97: =Capital_Structure!B48 -> 26.99 | C97: =Capital_Structure!C48 -> 0.13019637 | D97: =Capital_Structure!D48 -> 3.514 | E97: =($C$94+SUMIF($B$97:$B$106,"<="&B97,$D$97:$D$106))/($C$95+SUMIF($B$97:$B$106,"<="&B97,$C$97:$C$106)) -> -31.025287 | F97: =IF(E97>B97,1,0) -> 0
A98: =Capital_Structure!A49 -> 2032 2.375% converts | B98: =Capital_Structure!B49 -> 72.07 | C98: =Capital_Structure!C49 -> 4.5095046 | D98: =Capital_Structure!D49 -> 325 | E98: =($C$94+SUMIF($B$97:$B$106,"<="&B98,$D$97:$D$106))/($C$95+SUMIF($B$97:$B$106,"<="&B98,$C$97:$C$106)) -> -29.888168 | F98: =IF(E98>B98,1,0) -> 0
A99: =Capital_Structure!A50 -> 2036 2.00% converts | B99: =Capital_Structure!B50 -> 96.3 | C99: =Capital_Structure!C50 -> 11.941848 | D99: =Capital_Structure!D50 -> 1150 | E99: =($C$94+SUMIF($B$97:$B$106,"<="&B99,$D$97:$D$106))/($C$95+SUMIF($B$97:$B$106,"<="&B99,$C$97:$C$106)) -> -26.306996 | F99: =IF(E99>B99,1,0) -> 0
A100: =Capital_Structure!A51 -> 2036 2.25% converts | B100: =Capital_Structure!B51 -> 116.3 | C100: =Capital_Structure!C51 -> 9.2433362 | D100: =Capital_Structure!D51 -> 1075 | E100: =($C$94+SUMIF($B$97:$B$106,"<="&B100,$D$97:$D$106))/($C$95+SUMIF($B$97:$B$106,"<="&B100,$C$97:$C$106)) -> -23.241732 | F100: =IF(E100>B100,1,0) -> 0
A101: =Capital_Structure!A52 -> 2034 1.625% converts (Jul-2026) | B101: =Capital_Structure!B52 -> 149.2 | C101: =Capital_Structure!C52 -> 14.452683 | D101: =Capital_Structure!D52 -> 2156.3403 | E101: =($C$94+SUMIF($B$97:$B$106,"<="&B101,$D$97:$D$106))/($C$95+SUMIF($B$97:$B$106,"<="&B101,$C$97:$C$106)) -> -17.634699 | F101: =IF(E101>B101,1,0) -> 0
A102: =Capital_Structure!A53 -> 2020 Plan stock options | B102: =Capital_Structure!B53 -> 9.2 | C102: =Capital_Structure!C53 -> 1.957612 | D102: =Capital_Structure!D53 -> 18.01003 | E102: =($C$94+SUMIF($B$97:$B$106,"<="&B102,$D$97:$D$106))/($C$95+SUMIF($B$97:$B$106,"<="&B102,$C$97:$C$106)) -> -31.051652 | F102: =IF(E102>B102,1,0) -> 0
...

Sheet Sensitivity
A1: SENSITIVITY ANALYSIS
A2: Top grid is LIVE (Base scenario, WACC shift x terminal g, full dilution engine per cell). Lower tables are generated by engine.py (values stamped; re-run to refresh).
A4: Value per share ($) - Base scenario
A5: WACC shift (rows) / terminal g (cols) | B5: =Inputs!$D$20+(-0.01) -> 0.015 | C5: =Inputs!$D$20+(-0.005) -> 0.02 | D5: =Inputs!$D$20+(0) -> 0.025 | E5: =Inputs!$D$20+(0.005) -> 0.03 | F5: =Inputs!$D$20+(0.01) -> 0.035
A6: -0.02 | B6: =R81 -> 82.284569 | C6: =R82 -> 89.184846 | D6: =R83 -> 97.875506 | E6: =R84 -> 108.97014 | F6: =R85 -> 123.92082
A7: -0.01 | B7: =R86 -> 64.301467 | C7: =R87 -> 68.442638 | D7: =R88 -> 73.438992 | E7: =R89 -> 79.559482 | F7: =R90 -> 87.308844
A8: 0 | B8: =R91 -> 51.67617 | C8: =R92 -> 54.308569 | D8: =R93 -> 57.398181 | E8: =R94 -> 61.07545 | F8: =R95 -> 65.525661
A9: 0.01 | B9: =R96 -> 42.400612 | C9: =R97 -> 44.158155 | D9: =R98 -> 46.175785 | E9: =R99 -> 48.515849 | F9: =R100 -> 51.262351
A10: 0.02 | B10: =R101 -> 35.322417 | C10: =R102 -> 36.54008 | D10: =R103 -> 37.914709 | E10: =R104 -> 39.478747 | F10: =R105 -> 41.274236
A12: Check: centre cell equals Calc_Base value per share | D12: =D8-Calc_Base!$C$109 -> 0
A15: Tornado - Base value per share at P10 / P90 of each driver (engine.py)
A16: Generated by analytics.py (seed 20260910, 20,000 paths) on 10-Sep-2026 from Base inputs as delivered. Values, not formulas: re-run to refresh.
A17: Driver | B17: P10 input | C17: $/sh at P10 | D17: P90 input | E17: $/sh at P90 | F17: Swing $
A18: take_t1 | B18: 0.049418104 | C18: 16.998484 | D18: 0.20235499 | E18: 135.58012 | F18: 118.58163
A19: wacc_shift | B19: -0.012815516 | C19: 79.212537 | D19: 0.012815516 | E19: 43.60503 | F19: 35.607507
A20: arpu_t1 | B20: 4.1708204 | C20: 44.268451 | D20: 5.8291796 | E20: 70.494102 | F20: 26.225651
A21: take_t2 | B21: 0.012232683 | C21: 51.606985 | D21: 0.073573395 | E21: 71.588678 | F21: 19.981693
A22: px_g | B22: -0.027 | C22: 50.406124 | D22: -0.003 | E22: 60.412957 | F22: 10.006833
A23: delay | B23: 0 | C23: 57.398181 | D23: 2 | E23: 47.92381 | F23: 9.4743702
A24: opex_mult | B24: 0.82511481 | C24: 60.43802 | D24: 1.2119525 | E24: 53.714039 | F24: 6.7239815
A25: var_cost | B25: 0.097 | C25: 59.991839 | D25: 0.153 | E25: 53.676844 | F25: 6.3149947
A26: g | B26: 0.018872983 | C26: 53.679143 | D26: 0.027261387 | E26: 58.978983 | F26: 5.2998404
A27: arpu_t2 | B27: 0.55652476 | C27: 54.875677 | D27: 0.94347524 | E27: 59.920118 | F27: 5.0444407
A28: gov_mult | B28: 0.63855782 | C28: 55.433288 | D28: 1.5660289 | E28: 60.470219 | F28: 5.0369311
A29: sat_life | B29: 6 | C29: 55.507859 | D29: 8 | E29: 58.388245 | F29: 2.8803855
... A31: cip_credit | B31: 0.3 | C31: 56.610774 | D31: 0.7 | E31: 58.185588 | F31: 1.574814
A32: Base value per share (reference): $57.40
A34: Base $/share: Tier-1 peak take rate x Tier-1 ARPU
A35: Generated by analytics.py (seed 20260910, 20,000 paths) on 10-Sep-2026 from Base inputs as delivered. Values, not formulas: re-run to refresh.
A36: Take rate (rows) / ARPU $/mo (cols) | B36: 3.5 | C36: 4 | D36: 4.5 | E36: 5 | F36: 5.5 | G36: 6 | H36: 6.5
A37: 0.04 | B37: 0 | C37: 2.3381387 | D37: 5.942986 | E37: 9.2776606 | F37: 12.570902 | G37: 15.842685 | H37: 19.099326
A38: 0.06 | B38: 10.925948 | C38: 15.842685 | D38: 20.721072 | E38: 25.573436 | F38: 30.391606 | G38: 35.189581 | H38: 39.967577
A39: 0.08 | B39: 22.342819 | C39: 28.788633 | D39: 35.189581 | E39: 41.556539 | F39: 47.90489 | G39: 54.233751 | H39: 60.558407
A40: 0.1 | B40: 33.590256 | C40: 41.556539 | D40: 49.487105 | E40: 57.398181 | F40: 65.29586 | G40: 73.175244 | H40: 80.962832
A41: 0.12 | B41: 44.731701 | C41: 54.233751 | D41: 63.716709 | E41: 73.175244 | F41: 82.52035 | G41: 91.859924 | H41: 101.05526
A42: 0.15 | B42: 61.347982 | C42: 73.175244 | D42: 84.856627 | E42: 96.521484 | F42: 107.84745 | G42: 119.10291 | H42: 130.15897
A43: 0.2 | B43: 88.747905 | C43: 104.07401 | D43: 119.10291 | E43: 133.84432 | F43: 148.58573 | G43: 162.86778 | H43: 177.12755
A45: Base $/share: satellite unit cost x CIP pre-funding share
A46: Generated by analytics.py (seed 20260910, 20,000 paths) on 10-Sep-2026 from Base inputs as delivered. Values, not formulas: re-run to refresh.
A47: Unit cost $mm (rows) / CIP credit (cols) | B47: 0.25 | C47: 0.4 | D47: 0.5 | E47: 0.6 | F47: 0.75
A48: 20 | B48: 57.309596 | C48: 57.902092 | D48: 58.295795 | E48: 58.689499 | F48: 59.255613
A49: 22 | B49: 56.404242 | C49: 57.004477 | D49: 57.398181 | E49: 57.791884 | F49: 58.382439
A50: 24 | B50: 55.498888 | C50: 56.106862 | D50: 56.500566 | E50: 56.894269 | F50: 57.484825
A51: 26 | B51: 54.593534 | C51: 55.209248 | D51: 55.602951 | E51: 55.996655 | F51: 56.58721
A52: 28 | B52: 53.68818 | C52: 54.311633 | D52: 54.705337 | E52: 55.09904 | F52: 55.689595
A54: Reverse DCF - what the $62.42 share price implies (engine.py)
A55: Base-case Tier-1 peak take rate that equates value to price | E55: 0.10635771
A56: Base-case parallel WACC shift that equates value to price | E56: -0.0035595247
A57: implied growth-phase WACC | E57: 0.099937193
A58: implied terminal WACC | E58: 0.079015475
A59: Multiplier on every scenario's Tier-1 take rate for prob-weighted value = price | E59: 1.1370103
A60: ="WACC+"&TEXT(A6,"0.0%") -> WACC+-2.0% | B60: =Calc_Base!D71+$A$6 -> 0.083496718 | C60: =Calc_Base!E71+$A$6 -> 0.083496718 | D60: =Calc_Base!F71+$A$6 -> 0.083496718 | E60: =Calc_Base!G71+$A$6 -> 0.083496718 | F60: =Calc_Base!H71+$A$6 -> 0.083496718 | G60: =Calc_Base!I71+$A$6 -> 0.079312374 | H60: =Calc_Base!J71+$A$6 -> 0.075128031 | I60: =Calc_Base!K71+$A$6 -> 0.070943687 | ... P60: =Calc_Base!R71+$A$6 -> 0.062575
B61: =(1+B60)^(Calc_Base!D8+Calc_Base!D7-Inputs!$D$6) -> 1.0251716 | C61: =B61*(1+C60)^Calc_Base!E7 -> 1.11077 | D61: =C61*(1+D60)^Calc_Base!F7 -> 1.2035157 | E61: =D61*(1+E60)^Calc_Base!G7 -> 1.3040053 | F61: =E61*(1+F60)^Calc_Base!H7 -> 1.4128855 | G61: =F61*(1+G60)^Calc_Base!I7 -> 1.5249448 | H61: =G61*(1+H60)^Calc_Base!J7 -> 1.6395109 | I61: =H61*(1+I60)^Calc_Base!K7 -> 1.7558238 | J61: =I61*(1+J60)^Calc_Base!L7 -> 1.8730414 | ... P61: =O61*(1+P60)^Calc_Base!R7 -> 2.6959073
B62: =1/(1+B60)^(Calc_Base!D9-Inputs!$D$6) -> 0.99519995 | C62: =1/(B61*(1+C60)^(Calc_Base!E7/2)) -> 0.937108 | D62: =1/(C61*(1+D60)^(Calc_Base!F7/2)) -> 0.86489233 | E62: =1/(D61*(1+E60)^(Calc_Base!G7/2)) -> 0.79824176 | F62: =1/(E61*(1+F60)^(Calc_Base!H7/2)) -> 0.73672744 | G62: =1/(F61*(1+G60)^(Calc_Base!I7/2)) -> 0.68127032 | H62: =1/(G61*(1+H60)^(Calc_Base!J7/2)) -> 0.63243485 | I62: =1/(H61*(1+I60)^(Calc_Base!K7/2)) -> 0.58938949 | J62: =1/(I61*(1+J60)^(Calc_Base!L7/2)) -> 0.55142422 | ... P62: =1/(O61*(1+P60)^(Calc_Base!R7/2)) -> 0.38236211
A63: ="WACC+"&TEXT(A7,"0.0%") -> WACC+-1.0% | B63: =Calc_Base!D71+$A$7 -> 0.093496718 | C63: =Calc_Base!E71+$A$7 -> 0.093496718 | D63: =Calc_Base!F71+$A$7 -> 0.093496718 | E63: =Calc_Base!G71+$A$7 -> 0.093496718 | F63: =Calc_Base!H71+$A$7 -> 0.093496718 | G63: =Calc_Base!I71+$A$7 -> 0.089312374 | H63: =Calc_Base!J71+$A$7 -> 0.085128031 | I63: =Calc_Base!K71+$A$7 -> 0.080943687 | ... P63: =Calc_Base!R71+$A$7 -> 0.072575
B64: =(1+B63)^(Calc_Base!D8+Calc_Base!D7-Inputs!$D$6) -> 1.0280954 | C64: =B64*(1+C63)^Calc_Base!E7 -> 1.124219 | D64: =C64*(1+D63)^Calc_Base!F7 -> 1.2293297 | E64: =D64*(1+E63)^Calc_Base!G7 -> 1.344268 | F64: =E64*(1+F63)^Calc_Base!H7 -> 1.4699527 | G64: =F64*(1+G63)^Calc_Base!I7 -> 1.6012376 | H64: =G64*(1+H63)^Calc_Base!J7 -> 1.7375479 | I64: =H64*(1+I63)^Calc_Base!K7 -> 1.8781914 | J64: =I64*(1+J63)^Calc_Base!L7 -> 2.0223601 | ... P64: =O64*(1+P63)^Calc_Base!R7 -> 3.0791051
B65: =1/(1+B63)^(Calc_Base!D9-Inputs!$D$6) -> 0.99465152 | C65: =1/(B64*(1+C63)^(Calc_Base!E7/2)) -> 0.93016038 | D65: =1/(C64*(1+D63)^(Calc_Base!F7/2)) -> 0.85062933 | E65: =1/(D64*(1+E63)^(Calc_Base!G7/2)) -> 0.77789839 | F65: =1/(E64*(1+F63)^(Calc_Base!H7/2)) -> 0.71138612 | G65: =1/(F64*(1+G63)^(Calc_Base!I7/2)) -> 0.65180911 | H65: =1/(G64*(1+H63)^(Calc_Base!J7/2)) -> 0.59952006 | I65: =1/(H64*(1+I63)^(Calc_Base!K7/2)) -> 0.55355616 | J65: =1/(I64*(1+J63)^(Calc_Base!L7/2)) -> 0.5130986 | ... P65: =1/(O64*(1+P63)^(Calc_Base!R7/2)) -> 0.33634837
A66: ="WACC+"&TEXT(A8,"0.0%") -> WACC+0.0% | B66: =Calc_Base!D71+$A$8 -> 0.10349672 | C66: =Calc_Base!E71+$A$8 -> 0.10349672 | D66: =Calc_Base!F71+$A$8 -> 0.10349672 | E66: =Calc_Base!G71+$A$8 -> 0.10349672 | F66: =Calc_Base!H71+$A$8 -> 0.10349672 | G66: =Calc_Base!I71+$A$8 -> 0.099312374 | H66: =Calc_Base!J71+$A$8 -> 0.095128031 | I66: =Calc_Base!K71+$A$8 -> 0.090943687 | ... P66: =Calc_Base!R71+$A$8 -> 0.082575
B67: =(1+B66)^(Calc_Base!D8+Calc_Base!D7-Inputs!$D$6) -> 1.0310009 | C67: =B67*(1+C66)^Calc_Base!E7 -> 1.1377061 | D67: =C67*(1+D66)^Calc_Base!F7 -> 1.2554549 | E67: =D67*(1+E66)^Calc_Base!G7 -> 1.3853904 | F67: =E67*(1+F66)^Calc_Base!H7 -> 1.5287737 | G67: =F67*(1+G66)^Calc_Base!I7 -> 1.6805999 | H67: =G67*(1+H66)^Calc_Base!J7 -> 1.840472 | I67: =H67*(1+I66)^Calc_Base!K7 -> 2.0078513 | J67: =I67*(1+J66)^Calc_Base!L7 -> 2.1820512 | ... P67: =O67*(1+P66)^Calc_Base!R7 -> 3.5124722
B68: =1/(1+B66)^(Calc_Base!D9-Inputs!$D$6) -> 0.99410839 | C68: =1/(B67*(1+C66)^(Calc_Base!E7/2)) -> 0.92332682 | D68: =1/(C67*(1+D66)^(Calc_Base!F7/2)) -> 0.8367282 | E68: =1/(D67*(1+E66)^(Calc_Base!G7/2)) -> 0.75825165 | F68: =1/(E67*(1+F66)^(Calc_Base!H7/2)) -> 0.68713539 | G68: =1/(F67*(1+G66)^(Calc_Base!I7/2)) -> 0.62387306 | H68: =1/(G67*(1+H66)^(Calc_Base!J7/2)) -> 0.56859525 | I68: =1/(H67*(1+I66)^(Calc_Base!K7/2)) -> 0.52019912 | J68: =1/(I67*(1+J66)^(Calc_Base!L7/2)) -> 0.47775117 | ... P68: =1/(O67*(1+P66)^(Calc_Base!R7/2)) -> 0.29622117
A69: ="WACC+"&TEXT(A9,"0.0%") -> WACC+1.0% | B69: =Calc_Base!D71+$A$9 -> 0.11349672 | C69: =Calc_Base!E71+$A$9 -> 0.11349672 | D69: =Calc_Base!F71+$A$9 -> 0.11349672 | E69: =Calc_Base!G71+$A$9 -> 0.11349672 | F69: =Calc_Base!H71+$A$9 -> 0.11349672 | G69: =Calc_Base!I71+$A$9 -> 0.10931237 | H69: =Calc_Base!J71+$A$9 -> 0.10512803 | I69: =Calc_Base!K71+$A$9 -> 0.10094369 | ... P69: =Calc_Base!R71+$A$9 -> 0.092575
B70: =(1+B69)^(Calc_Base!D8+Calc_Base!D7-Inputs!$D$6) -> 1.0338882 | C70: =B70*(1+C69)^Calc_Base!E7 -> 1.1512311 | D70: =C70*(1+D69)^Calc_Base!F7 -> 1.281892 | E70: =D70*(1+E69)^Calc_Base!G7 -> 1.4273826 | F70: =E70*(1+F69)^Calc_Base!H7 -> 1.5893858 | G70: =F70*(1+G69)^Calc_Base!I7 -> 1.7631254 | H70: =G70*(1+H69)^Calc_Base!J7 -> 1.9484793 | I70: =H70*(1+I69)^Calc_Base!K7 -> 2.1451659 | J70: =I70*(1+J69)^Calc_Base!L7 -> 2.3527308 | ... P70: =O70*(1+P69)^Calc_Base!R7 -> 4.0020249
B71: =1/(1+B69)^(Calc_Base!D9-Inputs!$D$6) -> 0.99357044 | C71: =1/(B70*(1+C69)^(Calc_Base!E7/2)) -> 0.91660444 | D71: =1/(C70*(1+D69)^(Calc_Base!F7/2)) -> 0.8231766 | E71: =1/(D70*(1+E69)^(Calc_Base!G7/2)) -> 0.73927169 | F71: =1/(E70*(1+F69)^(Calc_Base!H7/2)) -> 0.66391906 | G71: =1/(F70*(1+G69)^(Calc_Base!I7/2)) -> 0.59737045 | H71: =1/(G70*(1+H69)^(Calc_Base!J7/2)) -> 0.53952368 | I71: =1/(H70*(1+I69)^(Calc_Base!K7/2)) -> 0.48912702 | J71: =1/(I70*(1+J69)^(Calc_Base!L7/2)) -> 0.44512648 | ... P71: =1/(O70*(1+P69)^(Calc_Base!R7/2)) -> 0.26118356
A72: ="WACC+"&TEXT(A10,"0.0%") -> WACC+2.0% | B72: =Calc_Base!D71+$A$10 -> 0.12349672 | C72: =Calc_Base!E71+$A$10 -> 0.12349672 | D72: =Calc_Base!F71+$A$10 -> 0.12349672 | E72: =Calc_Base!G71+$A$10 -> 0.12349672 | F72: =Calc_Base!H71+$A$10 -> 0.12349672 | G72: =Calc_Base!I71+$A$10 -> 0.11931237 | H72: =Calc_Base!J71+$A$10 -> 0.11512803 | I72: =Calc_Base!K71+$A$10 -> 0.11094369 | ... P72: =Calc_Base!R71+$A$10 -> 0.102575
